Workbook

Sheet Carátula
C4: REPORTE MENSUAL ENCUBIERTO DISMAC
C12: FEBRERO 2025

Sheet Dimensiones y Pesos
C2: Dimensiones y Pesos
B4: El índice de calidad de Dismac, esta compuesto por una seis dimensiones. Estas a su vez, están conformadas por subdimesiones que paralelamente se descomponen en atributos.
B6: DIMENSIONES | D6: SUBDIMENSIONES | E6: PESOS DIMENSIONES | F6: PESOS ATRIBUTOS | G6: ATRIBUTOS
B8: Atención del Vendedor | C8: 0.42 | D8: PRIMER CONTACTO | E8: 0.25 | F8: 0.3 | G8: El vendedor/a se percató de la presencia del cliente y se aproximó para atenderlo (si tiene otro cliente, no aplica, indique).
F9: 0.3 | G9: El vendedor/a lo saludó amablemente o pregunto en modo de bienvenida (Inicie la conversación)
F10: 0.2 | G10: El vendedor/a pregunta al cliente lo que busca o sus preferencias.
F11: 0.2 | G11: El vendedor/a dirige al cliente a donde debe, según su necesidad
D12: GESTION DE VENTA | E12: 0.4 | F12: 0.06 | G12: El vendedor/a mostró el producto solicitado de forma rápida y sin hacer esperar mucho tiempo al cliente.
F13: 0.07 | G13: El vendedor/a en caso de no disponer del producto en tienda, utilizó la página ecommerce de DISMAC para ofrecer otras opciones al cliente.
F14: 0.06 | G14: El vendedor/a demostró tener conocimiento del producto y proporcionó toda la información (garantía) y especificaciones del mismo.
F15: 0.06 | G15: El vendedor/a mostró diferentes opciones de productos e hizo recomendaciones de acuerdo a sus necesidades.
F16: 0.07 | G16: El vendedor/a le comunicó que Dismac tiene los precios más bajos del mercado y explicó la garantía de precios
F17: 0.06 | G17: El vendedor/a le comunicó sobre las promociones especiales, productos en combo o lanzamientos.
F18: 0.07 | G18: El vendedor/a explicó de qué trata la garantía extendida y sus beneficios
F19: 0.06 | G19: El vendedor/a se esmeró en brindar argumentos para incentivar la compra del producto. (Ej.: Buena calidad, diseño, última tecnología, etc.)
F20: 0.05 | G20: El vendedor/a cerró la venta?
F21: 0.07 | G21: El vendedor/a ofreció y explicó los beneficios del servicio de entrega gratuita, tiempo de entrega, áreas de cobertura.
F22: 0.07 | G22: El vendedor/a ofreció y explicó los beneficios del servicio de instalación garantizada.
F23: 0.07 | G23: El vendedor/a explicó los beneficios de la política de cambios y devoluciones.
F24: 0.06 | G24: El vendedor/a tuvo la capacidad/ habilidad de ofrecer productos ADICIONALES diferentes al que solicitó.
... F27: 0.05 | G27: En caso de interrupción durante la venta, el vendedor le pidió disculpas por la interrupción.
D28: INFORMACIÓN SOBRE LA ENTREGA E INSTALACIÓN DE PRODUCTOS | E28: 0.15 | F28: 0.3333 | G28: El vendedor/a coordinó y programó la entrega a domicilio del producto
F29: 0.3333 | G29: El vendedor/a coordinó y programó la instalación del producto
F30: 0.3333 | G30: El vendedor/a informó y explicó los requisitos previos de instalación del producto
D31: DESPEDIDA | E31: 0.1 | F31: 0.3333 | G31: El vendedor/a le solicitó sus datos personales y en caso de no estar registrado en su sistema, lo registró
F32: 0.3333 | G32: El vendedor/a lo dirigió a caja para efectuar el pago.
F33: 0.3333 | G33: El vendedor/a se despidió amablemente y lo invito a visitar nuevamente la tienda
D34: PRESENTACIÓN PERSONAL DEL VENDEDOR/A | E34: 0.1 | F34: 0.5 | G34: El vendedor/a se encontraba con el uniforme de la empresa.
F35: 0.5 | G35: El vendedor/a tenía buena presencia (El cabello no está en su rostro, está limpio y prolijo)
D36: DISMAC CLUB | E36: 0 | G36: El vendedor/a explicó de qué trata el Dismaclub
B37: Atención en Caja | C37: 0.22 | D37: ATENCIÓN EN CAJA | E37: 0.4 | F37: 0.1429 | G37: El cajero/a saludó amablemente. "Buenos días" "Buen día, en qué puedo ayudarle" "Cómo está"
F38: 0.1429 | G38: El cajero/a respetó el orden de llegada.
F39: 0.1429 | G39: El cajero/a le comunicó sobre el monto a pagar y realizó el proceso de facturación (Pide NIT y explica la implementación de la facturación electrónica, es decir pide los datos al cliente, explica que la factura le llegará por correo o a su teléfono (opcional) y efectivamente la factura le llegó por uno de estos medios).
F40: 0.1429 | G40: El cajero/a entregó la garantía del producto. (Aplica solo en caso de refrigeradores, cocinas, freezers, lavadoras, microondas y Aires Acondicionados)
F41: 0.1429 | G41: El cajero/a lo dirigió o le indicó quien es el encargado de hacer la entrega
F42: 0.1429 | G42: El cajero/a lo atendió con rapidez en el cobro, facturación.
F43: 0.1429 | G43: El cajero agradecio la compra, se despidió amablemente "Hasta luego" "Que tenga un buen día" "Que le vaya bien" y lo invitó a visitar la tienda nuevamente
D44: INFORMACIÓN SOBRE LA ENTREGA E INSTALACIÓN DE PRODUCTOS | E44: 0.2 | F44: 0.25 | G44: El cajero/a validó la fecha de entrega a domicilio del producto
F45: 0.25 | G45: El cajero/a validó la fecha de instalación del producto
F46: 0.25 | G46: El cajero/a validó que el vendedor explicó los requisitos previos de instalacion del producto, que el cliente entiende estos requisitos, y el cajero entregó los requisitos impresos al cliente.
F47: 0.25 | G47: El cajero informó y explicó al cliente que para cualquier cambio de horario que quiera realizar en la programacion de la entrega o instalación debe llamar al número 800 10 2000
D48: PRESENTACIÓN PERSONAL DEL CAJERO/A | E48: 0.2 | F48: 0.5 | G48: El cajero/a se encontraba con el uniforme de la empresa.
F49: 0.5 | G49: El cajero/a tenía buena presencia (El cabello no está en su rostro, está limpio y prolijo)
D50: OFERTA MINI CUOTAS | E50: 0.2 | G50: El cajero/a consultó el método de pago y ofreció MINICUOTAS
B51: Atención postpago | C51: 0.11 | D51: ENTREGA DE PRODUCTOS EN TIENDA | E51: 1 | F51: 0.3333 | G51: El vendedor/a mostró los accesorios con los que viene el producto
F52: 0.3333 | G52: El vendedor/a probó el producto
F53: 0.3333 | G53: El vendedor/a se despidió amablemente y lo invito a visitar nuevamente la tienda
B54: Ambiente | C54: 0.15 | D54: LIMPIEZA Y ORDEN | E54: 0.5 | F54: 0.3333 | G54: El interior de la tienda se encontraba limpio y en buenas condiciones (pisos, paredes y techo)
F55: 0.3333 | G55: Los pasillos se encontraban libres y permitían la libre circulación
F56: 0.3333 | G56: Los productos se encontraban ordenados y limpios
D57: LETREROS Y SEÑALETICA | E57: 0.5 | F57: 0.5 | G57: Los productos cuentan con la cartelería o letreros que indican sus precios
F58: 0.5 | G58: Los letreros de promociones y la señalética eran visibles
B59: Delivery | C59: 0 | D59: ENTREGA A DOMICILIO | E59: 1 | F59: 0.25 | G59: El chofer se comunicó con el cliente por lo menos 30 minutos antes para confirmar la entrega
F60: 0.25 | G60: El producto llegó a su casa en el rango de tiempo indicado (No más de 24 Hr)
F61: 0.25 | G61: El chofer dejó el producto dentro del inmueble y en el lugar solicitado por el cliente
F62: 0.25 | G62: El producto llegó en perfecto estatodo sin daños estéticos
B63: Devolución | C63: 0.1 | D63: DEVOLUCIÓN EN TIENDA | E63: 1 | F63: 0.1667 | G63: El encargado/a lo saludó amablemente
F64: 0.1667 | G64: El encargado/a escuchó atentamente, con paciencia y con interés
F65: 0.1667 | G65: El encargado/a demostró una buena actitud ante su solicitud
F66: 0.1667 | G66: El encargado/a verificó el estado del producto, y determinó si cumple con la política de cambios y devoluciones
F67: 0.1667 | G67: El encargado/a hizo efectiva la devolución
F68: 0.1667 | G68: La atención por parte del encargado/a fue ágil y rápida.
F69: 0 | G69: El encargado le brindó toda la información necesaria con respecto a la devolución (sólo en caso de demora)

Sheet Ficha Metodológica
D2: FICHA METODOLÓGICA
B5: Objetivo General: Auditar la calidad del servicio, productos e infraestructura en las agencias de Dismac. El fin último de la investigación es saber dónde hay que hacer cambios para conseguir mejoras.
B8: MUESTRA | D8: VISITAS | E8: %
B9: Santa Cruz | D9: 26 | E9: =+D9/$D$14 -> 0.52
B10: La Paz | D10: 14 | E10: =+D10/$D$14 -> 0.28
B11: Cochabamba | D11: =SUM(D37:D39) -> 6 | E11: =+D11/$D$14 -> 0.12
B12: Sucre | D12: 2 | E12: =+D12/$D$14 -> 0.04
B13: Tarija | D13: 2 | E13: =+D13/$D$14 -> 0.04
B14: TOTAL | D14: =SUM(D9:D13) -> 50 | E14: =SUM(E9:E13) -> 1
B16: Sucursales Visitadas | D16: Visitas
B17: DISMAC | C17: Cristobal de Mendoza #1055 | D17: 2
C18: Doble Vía entre 5to y 6to anillo | D18: 2
C19: Isabel 1 | D19: 2
C20: Pampa de la Isla | D20: 2
C21: Show Room (P.I.) | D21: 2
C22: Villa 1ero de Mayo | D22: 2
C23: 4to anillo e Isuto | D23: 2
C24: Plan 3000 | D24: 2
C25: Omar Chávez | D25: 2
C26: Av. Cristo Redentor entre 5to y 6to anillo | D26: 2
C27: Montero | D27: 2
C28: Av. Santos Dumont | D28: 2
C29: Isabel 2 | D29: 2
... C41: Tarija | D41: 2
B42: Visitas Totales | D42: =SUM(D17:D41) -> 50

Sheet Reporte General
G2: Reporte Febrero 2025 - Visitas encubiertas DISMAC
G3: Nivel de cumplimiento de protocolos - Bolivia
F7: DIMENSIONES EVALUADAS | G7: SANTA CRUZ | H7: LA PAZ | I7: COCHABAMBA | J7: SUCRE | K7: TARIJA | L7: BOLIVIA | N7: VARIACIÓN (Febrero - Diciembre) | P7: ASPECTOS DE MEJORA
F8: Atención del vendedor | G8: 0.88597891 | H8: 0.75184435 | I8: 0.8615345 | J8: 0.87855787 | K8: 0.91354724 | L8: 0.83311926 | N8: -0.024324675
F9: Atención en caja | G9: 0.91153846 | H9: 0.82857143 | I9: 0.93333333 | J9: 1 | K9: 1 | L9: 0.89114774 | N9: -0.011034799
F10: Atención post pago | G10: 0.95445455 | H10: 0.93326 | I10: 0.74995 | J10: 1 | K10: 1 | L10: 0.87922152 | N10: -0.12067848
F11: Ambiente de la tienda | G11: 0.99358974 | H11: 0.76190476 | I11: 1 | J11: 1 | K11: 1 | L11: 0.91849817 | N11: -0.066124847
F12: Delivery | G12: 1 | H12: 1 | I12: 1 | J12: n/a | K12: n/a | L12: 1 | N12: 0.083333333
F13: Devolución | G13: 1 | H13: 0.97619048 | I13: 1 | J13: 1 | K13: 1 | L13: 0.99206349 | N13: -0.0033068783
F14: Medidas de bioseguridad | G14: n/a | H14: n/a | I14: 0 | J14: 0 | K14: 0 | L14: 0 | N14: n/a
F15: ÍNDICES GENERALES FEBRERO | G15: 0.92665767 | H15: 0.80846731 | I15: 0.90511423 | J15: 0.94899431 | K15: 0.96368984 | L15: 0.88007974 | N15: -0.033043607
F16: ÍNDICES GENERALES DICIEMBRE | G16: 0.94008842 | H16: 0.91086333 | I16: 0.88841828 | J16: 0.94234194 | K16: 0.83623977 | L16: 0.91312334 | N16: -
F17: VARIACIÓN (Diciembre - Noviembre) | G17: -0.013430755 | H17: -0.10239602 | I17: 0.016695956 | J17: 0.0066523662 | K17: 0.12745007 | L17: -0.033043607 | N17: -
F18: CASOS | G18: 26 | H18: 14 | I18: 6 | J18: 2 | K18: 2 | L18: 50 | N18: -
F20: Nota: En rojo los valores más bajos por dimensión. En el caso de Cochabamba y La Paz, el Delivery no pondera la nota. La nota general de Bolivia, no toma en cuenta las notas de Sucre y Tarija en su promedio.
B21: Delivery | C21: 1
B22: Devolución | C22: 0.99206349
B23: Ambiente de la tienda | C23: 0.91849817
B24: Atención en caja | C24: 0.89114774
B25: ÍNDICES GENERALES | C25: 0.88007974
B26: Atención post pago | C26: 0.87922152
B27: Atención del vendedor | C27: 0.83311926
B28: Medidas de bioseguridad | C28: 0
B40: TARIJA | C40: 0.96368984
B41: SUCRE | C41: 0.94899431
B42: SANTA CRUZ | C42: 0.92665767
B43: COCHABAMBA | C43: 0.90511423
... B45: LA PAZ | C45: 0.80846731

Sheet Indices Generales
AE2: Reporte Febrero 2025 - Visitas encubiertas DISMAC
AE3: Índices generales de evaluación
AF5: SANTA CRUZ | AY5: LA PAZ | BJ5: COCHABAMBA | BO5: SUCRE | BP5: TARIJA | BQ5: COMPETENCIA | BW5: ÍNDICES GENERALES
AC7: PESOS | AE7: DIMENSIONES EVALUADAS | AF7: Cristobal de Mendoza #1055 | AG7: Doble Vía entre 5to y 6to anillo | AH7: Grigota 2 | AI7: Isabel 1 | AJ7: Isabel 4 | AK7: Isabel10 | AL7: Montero | AM7: Pampa de la Isla | AN7: Pico de Monte (Piraí) | AO7: Show Room (P.I.) | AP7: Viedma | AQ7: Villa 1ero de Mayo | AR7: 4to anillo e Isuto | AS7: Plan 3000 | AT7: Omar Chávez | AU7: Av. Cristo Redentor | AV7: Av. Santos Dumont | AW7: Doble Vía km13 | AX7: Isabel 2 | AY7: Calacoto Av. Ballivian 1305 | AZ7: E. Salmon 1053 | BA7: El Alto 4 | BB7: El Alto 5 | BC7: L. Barra 617 | BD7: Leon de la B. 743 | BE7: Socabaya | BF7: Obrajes | BG7: Multicine Río Seco | BH7: El Alto Satélite | BI7: El Alto Cruce Villa Adela | BJ7: Av.Pando #1377 | BK7: Nataniel Aguirre 310 | BL7: Ayacucho | BM7: Av. América #459 | BN7: Quillacollo | BO7: Sucre | BP7: Tarija | BQ7: 1er Anillo Brasil (Competencia) | BR7: 4to anillo Equipetrol (Competencia) | BS7: Santos Dumont (Competencia) | BT7: Villa 1ro de mayo (Competencia) | BU7: Pampa de la Isla (Competencia) | BW7: Santa Cruz | BX7: La Paz | BY7: Cochabamba | BZ7: Bolivia
AF8: % | AG8: % | AH8: % | AI8: % | AJ8: % | AK8: % | AL8: % | AM8: % | AN8: % | AO8: % | AP8: % | AQ8: % | AR8: % | AS8: % | AT8: % | AU8: % | AV8: % | AW8: % | AX8: % | AY8: % | AZ8: % | BA8: % | BB8: % | BC8: % | BD8: % | BE8: % | BF8: % | BG8: % | BH8: % | BI8: % | BJ8: % | BK8: % | BL8: % | BM8: % | BN8: % | BO8: % | BP8: % | BQ8: % | BR8: % | BS8: % | BT8: % | BU8: % | BW8: % | BX8: % | BY8: % | BZ8: %
AE10: ÍNDICE GENERAL | AF10: 0.97792679 | AG10: 0.9228767 | AH10: n/a | AI10: 0.93471667 | AJ10: n/a | AK10: n/a | AL10: 0.97661139 | AM10: 0.90143113 | AN10: n/a | AO10: 0.99175371 | AP10: n/a | AQ10: 0.74431765 | AR10: 0.88286524 | AS10: 0.97332429 | AT10: 0.89185959 | AU10: 0.92857143 | AV10: 0.92720076 | AW10: n/a | AX10: 0.99309434 | AY10: 0.73410958 | AZ10: 0.76637353 | BA10: 0.86791248 | BB10: n/a | BC10: n/a | BD10: n/a | BE10: 0.82028938 | BF10: n/a | BG10: 0.73114643 | BH10: 0.89099782 | BI10: 0.84844194 | BJ10: n/a | BK10: n/a | BL10: 0.87619545 | BM10: 0.89836568 | BN10: 0.94078157 | BO10: 0.94899431 | BP10: 0.96368984 | BQ10: n/a | BR10: n/a | BS10: n/a | BT10: n/a | BU10: n/a | BW10: 0.92665767 | BX10: 0.80846731 | BY10: 0.90511423 | BZ10: 0.88007974
AC12: 0.42 | AE12: ATENCIÓN DEL VENDEDOR | AF12: 0.95322581 | AG12: 0.81639929 | AH12: n/a | AI12: 0.84458969 | AJ12: n/a | AK12: n/a | AL12: 0.94433903 | AM12: 0.76533839 | AN12: n/a | AO12: 0.98039216 | AP12: n/a | AQ12: 0.65313725 | AR12: 0.92691622 | AS12: 0.96627451 | AT12: 0.74254902 | AU12: 0.98333333 | AV12: 0.95764706 | AW12: n/a | AX12: 0.98358413 | AY12: 0.6702957 | AZ12: 0.70862745 | BA12: 0.80938596 | BB12: n/a | BC12: n/a | BD12: n/a | BE12: 0.76261994 | BF12: n/a | BG12: 0.6376677 | BH12: 0.81490196 | BI12: 0.85941176 | BJ12: n/a | BK12: n/a | BL12: 0.83617963 | BM12: 0.88939394 | BN12: 0.85902993 | BO12: 0.87855787 | BP12: 0.91354724 | BQ12: n/a | BR12: n/a | BS12: 0 | BT12: 0 | BU12: n/a | BW12: 0.88597891 | BX12: 0.75184435 | BY12: 0.8615345 | BZ12: 0.83311926
AC13: 0.25 | AE13: PRIMER CONTACTO | AF13: 1 | AG13: 1 | AH13: n/a | AI13: 1 | AJ13: n/a | AK13: n/a | AL13: 1 | AM13: 1 | AN13: n/a | AO13: 1 | AP13: n/a | AQ13: 0.85 | AR13: 1 | AS13: 1 | AT13: 0.85 | AU13: 1 | AV13: 1 | AW13: n/a | AX13: 1 | AY13: 0.55 | AZ13: 0.7 | BA13: 0.7 | BB13: n/a | BC13: n/a | BD13: n/a | BE13: 0.7 | BF13: n/a | BG13: 0.6 | BH13: 1 | BI13: 0.85 | BJ13: n/a | BK13: n/a | BL13: 1 | BM13: 1 | BN13: 1 | BO13: 1 | BP13: 1 | BQ13: n/a | BR13: n/a | BS13: n/a | BT13: n/a | BU13: n/a | BW13: 0.97692308 | BX13: 0.72857143 | BY13: 1 | BZ13: 0.9018315
U14: n/a | V14: n/a | W14: n/a | X14: 0.375 | Y14: 0.5 | Z14: 0.42857143 | AA14: n/a | AB14: 0.375 | AC14: 0.3 | AE14: El vendedor/a se percató de la presencia del cliente y se aproximó para atenderlo | AF14: 1 | AG14: 1 | AH14: n/a | AI14: 1 | AJ14: n/a | AK14: n/a | AL14: 1 | AM14: 1 | AN14: n/a | AO14: 1 | AP14: n/a | AQ14: 1 | AR14: 1 | AS14: 1 | AT14: 1 | AU14: 1 | AV14: 1 | AW14: n/a | AX14: 1 | AY14: 0 | AZ14: 0 | BA14: 0.5 | BB14: n/a | BC14: n/a | BD14: n/a | BE14: 0.5 | BF14: n/a | BG14: 0.5 | BH14: 1 | BI14: 0.5 | BJ14: n/a | BK14: n/a | BL14: 1 | BM14: 1 | BN14: 1 | BO14: 1 | BP14: 1 | BQ14: n/a | BR14: n/a | BS14: n/a | BT14: n/a | BU14: n/a | BW14: 1 | BX14: 0.42857143 | BY14: 1 | BZ14: 0.80952381
U15: 0.6 | V15: 0.6 | W15: n/a | X15: 0.375 | Y15: 0.5 | Z15: n/a | AA15: 0.42857143 | AB15: 0.375 | AC15: 0.3 | AE15: El vendedor/a lo saludó amablemente o pregunto en modo de bienvenida | AF15: 1 | AG15: 1 | AH15: n/a | AI15: 1 | AJ15: n/a | AK15: n/a | AL15: 1 | AM15: 1 | AN15: n/a | AO15: 1 | AP15: n/a | AQ15: 0.5 | AR15: 1 | AS15: 1 | AT15: 0.5 | AU15: 1 | AV15: 1 | AW15: n/a | AX15: 1 | AY15: 0.5 | AZ15: 1 | BA15: 0.5 | BB15: n/a | BC15: n/a | BD15: n/a | BE15: 0.5 | BF15: n/a | BG15: 0.5 | BH15: 1 | BI15: 1 | BJ15: n/a | BK15: n/a | BL15: 1 | BM15: 1 | BN15: 1 | BO15: 1 | BP15: 1 | BQ15: n/a | BR15: n/a | BS15: n/a | BT15: n/a | BU15: n/a | BW15: 0.92307692 | BX15: 0.71428571 | BY15: 1 | BZ15: 0.87912088
U16: n/a | V16: 0.4 | W16: 0.5 | X16: 0.25 | Y16: n/a | Z16: 0.28571429 | AA16: 0.28571429 | AB16: n/a | AC16: 0.2 | AE16: El vendedor/a pregunta al cliente lo que busca o sus preferencias. | AF16: 1 | AG16: 1 | AH16: n/a | AI16: 1 | AJ16: n/a | AK16: n/a | AL16: 1 | AM16: 1 | AN16: n/a | AO16: 1 | AP16: n/a | AQ16: 1 | AR16: 1 | AS16: 1 | AT16: 1 | AU16: 1 | AV16: 1 | AW16: n/a | AX16: 1 | AY16: 1 | AZ16: 1 | BA16: 1 | BB16: n/a | BC16: n/a | BD16: n/a | BE16: 1 | BF16: n/a | BG16: 0.5 | BH16: 1 | BI16: 1 | BJ16: n/a | BK16: n/a | BL16: 1 | BM16: 1 | BN16: 1 | BO16: 1 | BP16: 1 | BQ16: n/a | BR16: n/a | BS16: n/a | BT16: n/a | BU16: n/a | BW16: 1 | BX16: 0.92857143 | BY16: 1 | BZ16: 0.97619048
U17: 0.4 | V17: n/a | W17: 0.5 | X17: n/a | Y17: n/a | Z17: 0.28571429 | AA17: 0.28571429 | AB17: 0.25 | AC17: 0.2 | AE17: El vendedor/a dirige al cliente a donde debe, según su necesidad | AF17: 1 | AG17: 1 | AH17: n/a | AI17: 1 | AJ17: n/a | AK17: n/a | AL17: 1 | AM17: 1 | AN17: n/a | AO17: 1 | AP17: n/a | AQ17: 1 | AR17: 1 | AS17: 1 | AT17: 1 | AU17: 1 | AV17: 1 | AW17: n/a | AX17: 1 | AY17: 1 | AZ17: 1 | BA17: 1 | BB17: n/a | BC17: n/a | BD17: n/a | BE17: 1 | BF17: n/a | BG17: 1 | BH17: 1 | BI17: 1 | BJ17: n/a | BK17: n/a | BL17: 1 | BM17: 1 | BN17: 1 | BO17: 1 | BP17: 1 | BQ17: n/a | BR17: n/a | BS17: n/a | BT17: n/a | BU17: n/a | BW17: 1 | BX17: 1 | BY17: 1 | BZ17: 1
AC18: 0.3 | AE18: GESTION DE VENTA | AF18: 0.92473118 | AG18: 0.69318182 | AH18: n/a | AI18: 0.75308642 | AJ18: n/a | AK18: n/a | AL18: 0.88172043 | AM18: 0.54301075 | AN18: n/a | AO18: 1 | AP18: n/a | AQ18: 0.44 | AR18: 0.88636364 | AS18: 0.97 | AT18: 0.63 | AU18: 1 | AV18: 0.91 | AW18: n/a | AX18: 0.96511628 | AY18: 0.62365591 | AZ18: 0.61 | BA18: 0.75263158 | BB18: n/a | BC18: n/a | BD18: n/a | BE18: 0.78723404 | BF18: n/a | BG18: 0.58421053 | BH18: 0.69 | BI18: 0.795 | BJ18: n/a | BK18: n/a | BL18: 0.69354839 | BM18: 0.80681818 | BN18: 0.74210526 | BO18: 0.74193548 | BP18: 0.92045455 | BQ18: 0 | BR18: 0 | BS18: 0 | BT18: 0 | BU18: 0 | BW18: 0.81517004 | BX18: 0.69181887 | BY18: 0.74749061 | BZ18: 0.75149317
A19: 0.068965517 | B19: 0.075 | C19: 0.068181818 | D19: 0.075949367 | E19: 0.08 | F19: 0.073170732 | G19: 0.074074074 | H19: 0.069767442 | I19: 0.074074074 | J19: 0.081081081 | K19: 0.069767442 | L19: 0.068181818 | M19: 0.064516129 | N19: 0.069767442 | O19: n/a | P19: n/a | Q19: 0.06741573 | R19: 0.064516129 | S19: 0.068181818 | T19: n/a | U19: 0.063157895 | V19: 0.063157895 | W19: 0.063829787 | X19: 0.064516129 | Y19: n/a | Z19: 0.073170732 | AA19: 0.068181818 | AB19: 0.064516129 | AC19: 0.06 | AE19: El vendedor/a mostró el producto solicitado de forma rápida y sin hacer esperar mucho tiempo al cliente. | AF19: 1 | AG19: 1 | AH19: n/a | AI19: 1 | AJ19: n/a | AK19: n/a | AL19: 1 | AM19: 1 | AN19: n/a | AO19: 1 | AP19: n/a | AQ19: 1 | AR19: 1 | AS19: 1 | AT19: 1 | AU19: 1 | AV19: 1 | AW19: n/a | AX19: 1 | AY19: 1 | AZ19: 1 | BA19: 1 | BB19: n/a | BC19: n/a | BD19: n/a | BE19: 1 | BF19: n/a | BG19: 1 | BH19: 1 | BI19: 1 | BJ19: n/a | BK19: n/a | BL19: 1 | BM19: 1 | BN19: 1 | BO19: 1 | BP19: 1 | BQ19: n/a | BR19: n/a | BS19: n/a | BT19: n/a | BU19: n/a | BW19: 1 | BX19: 1 | BY19: 1 | BZ19: 1
A20: n/a | B20: n/a | C20: 0.079545455 | D20: n/a | E20: n/a | F20: n/a | G20: 0.086419753 | H20: 0.081395349 | I20: n/a | J20: n/a | K20: n/a | L20: n/a | M20: n/a | N20: 0.081395349 | O20: 0.079545455 | P20: 0.085365854 | Q20: 0.078651685 | R20: 0.075268817 | S20: 0.079545455 | T20: 0.078651685 | U20: 0.073684211 | V20: 0.073684211 | W20: 0.074468085 | X20: 0.075268817 | Y20: 0.074468085 | Z20: 0.085365854 | AA20: 0.079545455 | AB20: 0.075268817 | AC20: 0.07 | AE20: El vendedor/a en caso de no disponer del producto en tienda, utilizó la página ecommerce de DISMAC para ofrecer otras opciones al cliente. | AF20: n/a | AG20: 1 | AH20: n/a | AI20: n/a | AJ20: n/a | AK20: n/a | AL20: n/a | AM20: n/a | AN20: n/a | AO20: 1 | AP20: n/a | AQ20: 1 | AR20: 1 | AS20: 1 | AT20: 1 | AU20: n/a | AV20: 1 | AW20: n/a | AX20: n/a | AY20: n/a | AZ20: 1 | BA20: 0.5 | BB20: n/a | BC20: n/a | BD20: n/a | BE20: 1 | BF20: n/a | BG20: 0 | BH20: 0 | BI20: 1 | BJ20: n/a | BK20: n/a | BL20: n/a | BM20: n/a | BN20: 1 | BO20: 1 | BP20: 1 | BQ20: n/a | BR20: n/a | BS20: n/a | BT20: n/a | BU20: n/a | BW20: 1 | BX20: 0.58333333 | BY20: 1 | BZ20: 0.86111111
A21: 0.068965517 | B21: 0.075 | C21: 0.068181818 | D21: 0.075949367 | E21: 0.08 | F21: 0.073170732 | G21: 0.074074074 | H21: 0.069767442 | I21: 0.074074074 | J21: 0.081081081 | K21: 0.069767442 | L21: 0.068181818 | M21: 0.064516129 | N21: 0.069767442 | O21: 0.068181818 | P21: 0.073170732 | Q21: 0.06741573 | R21: 0.064516129 | S21: 0.068181818 | T21: 0.06741573 | U21: 0.063157895 | V21: 0.063157895 | W21: 0.063829787 | X21: 0.064516129 | Y21: 0.063829787 | Z21: 0.073170732 | AA21: 0.068181818 | AB21: 0.064516129 | AC21: 0.06 | AE21: El vendedor/a demostró tener conocimiento del producto y proporcionó toda la información (garantía) y especificaciones del mismo. | AF21: 1 | AG21: 1 | AH21: n/a | AI21: 1 | AJ21: n/a | AK21: n/a | AL21: 1 | AM21: 1 | AN21: n/a | AO21: 1 | AP21: n/a | AQ21: 1 | AR21: 1 | AS21: 1 | AT21: 1 | AU21: 1 | AV21: 1 | AW21: n/a | AX21: 1 | AY21: 1 | AZ21: 1 | BA21: 0.5 | BB21: n/a | BC21: n/a | BD21: n/a | BE21: 1 | BF21: n/a | BG21: 0 | BH21: 1 | BI21: 1 | BJ21: n/a | BK21: n/a | BL21: 1 | BM21: 1 | BN21: 1 | BO21: 1 | BP21: 1 | BQ21: n/a | BR21: n/a | BS21: n/a | BT21: n/a | BU21: n/a | BW21: 1 | BX21: 0.78571429 | BY21: 1 | BZ21: 0.92857143
A22: 0.068965517 | B22: 0.075 | C22: 0.068181818 | D22: 0.075949367 | E22: 0.08 | F22: 0.073170732 | G22: 0.074074074 | H22: 0.069767442 | I22: 0.074074074 | J22: 0.081081081 | K22: 0.069767442 | L22: 0.068181818 | M22: 0.064516129 | N22: 0.069767442 | O22: 0.068181818 | P22: 0.073170732 | Q22: 0.06741573 | R22: 0.064516129 | S22: 0.068181818 | T22: 0.06741573 | U22: 0.063157895 | V22: 0.063157895 | W22: 0.063829787 | X22: 0.064516129 | Y22: 0.063829787 | Z22: 0.073170732 | AA22: 0.068181818 | AB22: 0.064516129 | AC22: 0.06 | AE22: El vendedor/a mostró diferentes opciones de productos e hizo recomendaciones de acuerdo a sus necesidades. | AF22: 1 | AG22: 1 | AH22: n/a | AI22: 1 | AJ22: n/a | AK22: n/a | AL22: 0.5 | AM22: 0.5 | AN22: n/a | AO22: 1 | AP22: n/a | AQ22: 1 | AR22: 1 | AS22: 1 | AT22: 1 | AU22: 1 | AV22: 1 | AW22: n/a | AX22: 1 | AY22: 1 | AZ22: 1 | BA22: 1 | BB22: n/a | BC22: n/a | BD22: n/a | BE22: 1 | BF22: n/a | BG22: 1 | BH22: 1 | BI22: 1 | BJ22: n/a | BK22: n/a | BL22: 0.5 | BM22: 1 | BN22: 1 | BO22: 1 | BP22: 1 | BQ22: n/a | BR22: n/a | BS22: n/a | BT22: n/a | BU22: n/a | BW22: 0.92307692 | BX22: 1 | BY22: 0.83333333 | BZ22: 0.91880342
A23: 0.08045977 | B23: 0.0875 | C23: 0.079545455 | D23: 0.088607595 | E23: 0.093333333 | F23: 0.085365854 | G23: 0.086419753 | H23: 0.081395349 | I23: 0.086419753 | J23: 0.094594595 | K23: 0.081395349 | L23: 0.079545455 | M23: 0.075268817 | N23: 0.081395349 | O23: 0.079545455 | P23: 0.085365854 | Q23: 0.078651685 | R23: 0.075268817 | S23: 0.079545455 | T23: 0.078651685 | U23: 0.073684211 | V23: 0.073684211 | W23: 0.074468085 | X23: n/a | Y23: 0.074468085 | Z23: 0.085365854 | AA23: 0.079545455 | AB23: 0.075268817 | AC23: 0.07 | AE23: El vendedor/a le comunicó que Dismac tiene los precios más bajos del mercado y explicó la garantía de precios | AF23: 1 | AG23: 0.5 | AH23: n/a | AI23: 0.5 | AJ23: n/a | AK23: n/a | AL23: 1 | AM23: 0.5 | AN23: n/a | AO23: 1 | AP23: n/a | AQ23: 0 | AR23: 1 | AS23: 1 | AT23: 0.5 | AU23: 1 | AV23: 1 | AW23: n/a | AX23: 1 | AY23: 0.5 | AZ23: 0 | BA23: 0.5 | BB23: n/a | BC23: n/a | BD23: n/a | BE23: 0.5 | BF23: n/a | BG23: 0 | BH23: 0.5 | BI23: 0.5 | BJ23: n/a | BK23: n/a | BL23: 0.5 | BM23: 0.5 | BN23: 0.5 | BO23: 0 | BP23: 0.5 | BQ23: n/a | BR23: n/a | BS23: n/a | BT23: n/a | BU23: n/a | BW23: 0.76923077 | BX23: 0.35714286 | BY23: 0.5 | BZ23: 0.54212454
A24: 0.068965517 | B24: 0.075 | C24: 0.068181818 | D24: 0.075949367 | E24: 0.08 | F24: 0.073170732 | G24: 0.074074074 | H24: 0.069767442 | I24: 0.074074074 | J24: 0.081081081 | K24: 0.069767442 | L24: 0.068181818 | M24: 0.064516129 | N24: 0.069767442 | O24: 0.068181818 | P24: 0.073170732 | Q24: 0.06741573 | R24: 0.064516129 | S24: 0.068181818 | T24: 0.06741573 | U24: 0.063157895 | V24: 0.063157895 | W24: 0.063829787 | X24: 0.064516129 | Y24: 0.063829787 | Z24: 0.073170732 | AA24: 0.068181818 | AB24: 0.064516129 | AC24: 0.06 | AE24: El vendedor/a le comunicó sobre las promociones especiales, productos en combo, descuentos o lanzamientos. | AF24: 1 | AG24: 0.5 | AH24: n/a | AI24: 1 | AJ24: n/a | AK24: n/a | AL24: 1 | AM24: 0.5 | AN24: n/a | AO24: 1 | AP24: n/a | AQ24: 0.5 | AR24: 1 | AS24: 1 | AT24: 0.5 | AU24: 1 | AV24: 1 | AW24: n/a | AX24: 1 | AY24: 0.5 | AZ24: 0.5 | BA24: 0.5 | BB24: n/a | BC24: n/a | BD24: n/a | BE24: 0.5 | BF24: n/a | BG24: 0.5 | BH24: 0.5 | BI24: 0.5 | BJ24: n/a | BK24: n/a | BL24: 0.5 | BM24: 1 | BN24: 1 | BO24: 0.5 | BP24: 1 | BQ24: n/a | BR24: n/a | BS24: n/a | BT24: n/a | BU24: n/a | BW24: 0.84615385 | BX24: 0.5 | BY24: 0.83333333 | BZ24: 0.72649573
A25: 0.08045977 | B25: 0.0875 | C25: 0.079545455 | D25: 0.088607595 | E25: 0.093333333 | F25: 0.085365854 | G25: 0.086419753 | H25: 0.081395349 | I25: 0.086419753 | J25: 0.094594595 | K25: 0.081395349 | L25: 0.079545455 | M25: 0.075268817 | N25: 0.081395349 | O25: 0.079545455 | P25: 0.085365854 | Q25: 0.078651685 | R25: 0.075268817 | S25: 0.079545455 | T25: 0.078651685 | U25: 0.073684211 | V25: 0.073684211 | W25: 0.074468085 | X25: 0.075268817 | Y25: 0.074468085 | Z25: 0.085365854 | AA25: 0.079545455 | AB25: 0.075268817 | AC25: 0.07 | AE25: El vendedor/a explicó de qué trata la garantía extendida y sus beneficios | AF25: 0.5 | AG25: 0.5 | AH25: n/a | AI25: 0.5 | AJ25: n/a | AK25: n/a | AL25: 1 | AM25: 0.5 | AN25: n/a | AO25: 1 | AP25: n/a | AQ25: 0 | AR25: 0.5 | AS25: 1 | AT25: 0.5 | AU25: 1 | AV25: 0.5 | AW25: n/a | AX25: 1 | AY25: 0.5 | AZ25: 0.5 | BA25: 0.5 | BB25: n/a | BC25: n/a | BD25: n/a | BE25: 1 | BF25: n/a | BG25: 0 | BH25: 0.5 | BI25: 0 | BJ25: n/a | BK25: n/a | BL25: 1 | BM25: 1 | BN25: 0.5 | BO25: 0.5 | BP25: 1 | BQ25: n/a | BR25: n/a | BS25: n/a | BT25: n/a | BU25: n/a | BW25: 0.65384615 | BX25: 0.42857143 | BY25: 0.83333333 | BZ25: 0.63858364
A26: 0.068965517 | B26: 0.075 | C26: 0.068181818 | D26: 0.075949367 | E26: 0.08 | F26: 0.073170732 | G26: 0.074074074 | H26: 0.069767442 | I26: 0.074074074 | J26: 0.081081081 | K26: 0.069767442 | L26: 0.068181818 | M26: 0.064516129 | N26: 0.069767442 | O26: 0.068181818 | P26: 0.073170732 | Q26: 0.06741573 | R26: 0.064516129 | S26: 0.068181818 | T26: 0.06741573 | U26: 0.063157895 | V26: 0.063157895 | W26: 0.063829787 | X26: 0.064516129 | Y26: 0.063829787 | Z26: 0.073170732 | AA26: 0.068181818 | AB26: 0.064516129 | AC26: 0.06 | AE26: El vendedor/a se esmeró en brindar argumentos para incentivar la compra del producto. | AF26: 1 | AG26: 1 | AH26: n/a | AI26: 1 | AJ26: n/a | AK26: n/a | AL26: 1 | AM26: 0.5 | AN26: n/a | AO26: 1 | AP26: n/a | AQ26: 1 | AR26: 0.5 | AS26: 0.5 | AT26: 0.5 | AU26: 1 | AV26: 1 | AW26: n/a | AX26: 1 | AY26: 1 | AZ26: 0.5 | BA26: 1 | BB26: n/a | BC26: n/a | BD26: n/a | BE26: 0.5 | BF26: n/a | BG26: 1 | BH26: 1 | BI26: 1 | BJ26: n/a | BK26: n/a | BL26: 0.5 | BM26: 1 | BN26: 1 | BO26: 1 | BP26: 1 | BQ26: n/a | BR26: n/a | BS26: n/a | BT26: n/a | BU26: n/a | BW26: 0.84615385 | BX26: 0.85714286 | BY26: 0.83333333 | BZ26: 0.84554335
A27: 0.057471264 | B27: 0.0625 | C27: 0.056818182 | D27: 0.063291139 | E27: 0.066666667 | F27: 0.06097561 | G27: 0.061728395 | H27: 0.058139535 | I27: 0.061728395 | J27: 0.067567568 | K27: 0.058139535 | L27: 0.056818182 | M27: 0.053763441 | N27: 0.058139535 | O27: 0.056818182 | P27: 0.06097561 | Q27: 0.056179775 | R27: 0.053763441 | S27: 0.056818182 | T27: 0.056179775 | U27: 0.052631579 | V27: 0.052631579 | W27: 0.053191489 | X27: 0.053763441 | Y27: 0.053191489 | Z27: 0.06097561 | AA27: 0.056818182 | AB27: 0.053763441 | AC27: 0.05 | AE27: El vendedor/a cerró la venta | AF27: 1 | AG27: 1 | AH27: n/a | AI27: 1 | AJ27: n/a | AK27: n/a | AL27: 1 | AM27: 1 | AN27: n/a | AO27: 1 | AP27: n/a | AQ27: 1 | AR27: 1 | AS27: 1 | AT27: 1 | AU27: 1 | AV27: 1 | AW27: n/a | AX27: 1 | AY27: 1 | AZ27: 1 | BA27: 1 | BB27: n/a | BC27: n/a | BD27: n/a | BE27: 1 | BF27: n/a | BG27: 1 | BH27: 1 | BI27: 1 | BJ27: n/a | BK27: n/a | BL27: 1 | BM27: 1 | BN27: 1 | BO27: 1 | BP27: 1 | BQ27: n/a | BR27: n/a | BS27: n/a | BT27: n/a | BU27: n/a | BW27: 1 | BX27: 1 | BY27: 1 | BZ27: 1
A28: 0.08045977 | B28: 0.0875 | C28: n/a | D28: n/a | E28: 0.093333333 | F28: 0.085365854 | G28: n/a | H28: n/a | I28: 0.086419753 | J28: n/a | K28: 0.081395349 | L28: 0.079545455 | M28: 0.075268817 | N28: n/a | O28: 0.079545455 | P28: 0.085365854 | Q28: 0.078651685 | R28: 0.075268817 | S28: 0.079545455 | T28: 0.078651685 | U28: 0.073684211 | V28: 0.073684211 | W28: 0.074468085 | X28: 0.075268817 | Y28: 0.074468085 | Z28: 0.085365854 | AA28: 0.079545455 | AB28: 0.075268817 | AC28: 0.07 | AE28: El vendedor/a ofreció y explicó los beneficios del servicio de entrega gratuita, tiempo de entrega, áreas de cobertura. | AF28: 1 | AG28: 0 | AH28: n/a | AI28: 1 | AJ28: n/a | AK28: n/a | AL28: 1 | AM28: 0 | AN28: n/a | AO28: 1 | AP28: n/a | AQ28: 0 | AR28: 1 | AS28: 1 | AT28: 0 | AU28: 1 | AV28: 1 | AW28: n/a | AX28: 1 | AY28: 1 | AZ28: 1 | BA28: 1 | BB28: n/a | BC28: n/a | BD28: n/a | BE28: 1 | BF28: n/a | BG28: 1 | BH28: 1 | BI28: 1 | BJ28: n/a | BK28: n/a | BL28: 1 | BM28: 0.5 | BN28: 0 | BO28: 1 | BP28: 1 | BQ28: n/a | BR28: n/a | BS28: n/a | BT28: n/a | BU28: n/a | BW28: 0.69230769 | BX28: 1 | BY28: 0.5 | BZ28: 0.73076923
A29: 0.08045977 | B29: n/a | C29: 0.079545455 | D29: n/a | E29: n/a | F29: 0.085365854 | G29: n/a | H29: n/a | I29: n/a | J29: n/a | K29: n/a | L29: 0.079545455 | M29: 0.075268817 | N29: n/a | O29: 0.079545455 | P29: n/a | Q29: 0.078651685 | R29: 0.075268817 | S29: 0.079545455 | T29: 0.078651685 | U29: 0.073684211 | V29: 0.073684211 | W29: 0.074468085 | X29: 0.075268817 | Y29: 0.074468085 | Z29: n/a | AA29: n/a | AB29: n/a | AC29: 0.07 | AE29: El vendedor/a ofreció y explicó los beneficios del servicio de instalación garantizada. | AF29: 1 | AG29: n/a | AH29: n/a | AI29: n/a | AJ29: n/a | AK29: n/a | AL29: 1 | AM29: 0 | AN29: n/a | AO29: 1 | AP29: n/a | AQ29: 0 | AR29: n/a | AS29: 1 | AT29: 0 | AU29: 1 | AV29: 1 | AW29: n/a | AX29: n/a | AY29: 1 | AZ29: 1 | BA29: 1 | BB29: n/a | BC29: n/a | BD29: n/a | BE29: 1 | BF29: n/a | BG29: 1 | BH29: 0 | BI29: 1 | BJ29: n/a | BK29: n/a | BL29: 1 | BM29: 1 | BN29: 0 | BO29: n/a | BP29: n/a | BQ29: n/a | BR29: n/a | BS29: n/a | BT29: n/a | BU29: n/a | BW29: 0.66666667 | BX29: 0.85714286 | BY29: 0.66666667 | BZ29: 0.73015873
A30: 0.08045977 | B30: 0.0875 | C30: 0.079545455 | D30: 0.088607595 | E30: 0.093333333 | F30: 0.085365854 | G30: 0.086419753 | H30: 0.081395349 | I30: 0.086419753 | J30: 0.094594595 | K30: 0.081395349 | L30: 0.079545455 | M30: 0.075268817 | N30: 0.081395349 | O30: 0.079545455 | P30: 0.085365854 | Q30: 0.078651685 | R30: 0.075268817 | S30: 0.079545455 | T30: 0.078651685 | U30: 0.073684211 | V30: 0.073684211 | W30: 0.074468085 | X30: 0.075268817 | Y30: 0.074468085 | Z30: 0.085365854 | AA30: 0.079545455 | AB30: 0.075268817 | AC30: 0.07 | AE30: El vendedor/a explicó los beneficios de la política de cambios y devoluciones. | AF30: 0.5 | AG30: 0.5 | AH30: n/a | AI30: 0.5 | AJ30: n/a | AK30: n/a | AL30: 1 | AM30: 0.5 | AN30: n/a | AO30: 1 | AP30: n/a | AQ30: 0 | AR30: 0.5 | AS30: 1 | AT30: 0.5 | AU30: 1 | AV30: 1 | AW30: n/a | AX30: 1 | AY30: 0 | AZ30: 0 | BA30: 0.5 | BB30: n/a | BC30: n/a | BD30: n/a | BE30: 0 | BF30: n/a | BG30: 1 | BH30: 0.5 | BI30: 0.5 | BJ30: n/a | BK30: n/a | BL30: 0 | BM30: 0.5 | BN30: 0.5 | BO30: 0 | BP30: 1 | BQ30: n/a | BR30: n/a | BS30: n/a | BT30: n/a | BU30: n/a | BW30: 0.69230769 | BX30: 0.35714286 | BY30: 0.33333333 | BZ30: 0.46092796
A31: n/a | B31: n/a | C31: 0.068181818 | D31: 0.075949367 | E31: n/a | F31: n/a | G31: 0.074074074 | H31: 0.069767442 | I31: 0.074074074 | J31: 0.081081081 | K31: 0.069767442 | L31: 0.068181818 | M31: 0.064516129 | N31: 0.069767442 | O31: n/a | P31: 0.073170732 | Q31: n/a | R31: 0.064516129 | S31: 0.068181818 | T31: 0.06741573 | U31: 0.063157895 | V31: 0.063157895 | W31: n/a | X31: 0.064516129 | Y31: 0.063829787 | Z31: n/a | AA31: 0.068181818 | AB31: 0.064516129 | AC31: 0.06 | AE31: El vendedor/a preguntó, si necesitaba algo más, o tuvo la capacidad/ habilidad de ofrecer productos ADICIONALES diferentes al que solicitó | AF31: 1 | AG31: 0.5 | AH31: n/a | AI31: 0 | AJ31: n/a | AK31: n/a | AL31: 0.5 | AM31: 0.5 | AN31: n/a | AO31: 1 | AP31: n/a | AQ31: 0 | AR31: 1 | AS31: 1 | AT31: 0.5 | AU31: 1 | AV31: 0.5 | AW31: n/a | AX31: 0.5 | AY31: 0 | AZ31: 0 | BA31: 1 | BB31: n/a | BC31: n/a | BD31: n/a | BE31: n/a | BF31: n/a | BG31: 0 | BH31: 1 | BI31: 1 | BJ31: n/a | BK31: n/a | BL31: 0.5 | BM31: 0.5 | BN31: 1 | BO31: 1 | BP31: 1 | BQ31: n/a | BR31: n/a | BS31: n/a | BT31: n/a | BU31: n/a | BW31: 0.61538462 | BX31: 0.5 | BY31: 0.66666667 | BZ31: 0.59401709
A32: 0.08045977 | B32: 0.0875 | C32: 0.079545455 | D32: 0.088607595 | E32: 0.093333333 | F32: 0.085365854 | G32: 0.086419753 | H32: 0.081395349 | I32: 0.086419753 | J32: 0.094594595 | K32: 0.081395349 | L32: 0.079545455 | M32: 0.075268817 | N32: 0.081395349 | O32: 0.079545455 | P32: 0.085365854 | Q32: 0.078651685 | R32: n/a | S32: n/a | T32: 0.078651685 | U32: 0.073684211 | V32: 0.073684211 | W32: 0.074468085 | X32: 0.075268817 | Y32: 0.074468085 | Z32: 0.085365854 | AA32: 0.079545455 | AB32: 0.075268817 | AC32: 0.07 | AE32: El vendedor/a consultó el método de pago y ofreció MINICUOTAS | AF32: 1 | AG32: 0.5 | AH32: n/a | AI32: 0.5 | AJ32: n/a | AK32: n/a | AL32: 1 | AM32: 0.5 | AN32: n/a | AO32: 1 | AP32: n/a | AQ32: 0 | AR32: 1 | AS32: 1 | AT32: 0.5 | AU32: 1 | AV32: 1 | AW32: n/a | AX32: 1 | AY32: 0 | AZ32: 0 | BA32: 0.5 | BB32: n/a | BC32: n/a | BD32: n/a | BE32: 0.5 | BF32: n/a | BG32: 0.5 | BH32: 0.5 | BI32: 0.5 | BJ32: n/a | BK32: n/a | BL32: 0.5 | BM32: 0.5 | BN32: 1 | BO32: 0.5 | BP32: 0.5 | BQ32: n/a | BR32: n/a | BS32: n/a | BT32: n/a | BU32: n/a | BW32: 0.76923077 | BX32: 0.35714286 | BY32: 0.66666667 | BZ32: 0.5976801
A33: 0.057471264 | B33: 0.0625 | C33: 0.056818182 | D33: 0.063291139 | E33: 0.066666667 | F33: 0.06097561 | G33: 0.061728395 | H33: 0.058139535 | I33: 0.061728395 | J33: 0.067567568 | K33: 0.058139535 | L33: 0.056818182 | M33: 0.053763441 | N33: 0.058139535 | O33: 0.056818182 | P33: 0.06097561 | Q33: 0.056179775 | R33: 0.053763441 | S33: 0.056818182 | T33: 0.056179775 | U33: 0.052631579 | V33: n/a | W33: 0.053191489 | X33: 0.053763441 | Y33: 0.053191489 | Z33: 0.06097561 | AA33: 0.056818182 | AB33: 0.053763441 | AC33: 0.05 | AE33: El vendedor/a demostró actitud de servicio, amabilidad y cortesía en el trato | AF33: 1 | AG33: 1 | AH33: n/a | AI33: 1 | AJ33: n/a | AK33: n/a | AL33: 1 | AM33: 0.5 | AN33: n/a | AO33: 1 | AP33: n/a | AQ33: 1 | AR33: 1 | AS33: 1 | AT33: 1 | AU33: 1 | AV33: 1 | AW33: n/a | AX33: 1 | AY33: 1 | AZ33: 1 | BA33: 1 | BB33: n/a | BC33: n/a | BD33: n/a | BE33: 1 | BF33: n/a | BG33: 1 | BH33: 1 | BI33: 1 | BJ33: n/a | BK33: n/a | BL33: 0.5 | BM33: 1 | BN33: 1 | BO33: 1 | BP33: 1 | BQ33: n/a | BR33: n/a | BS33: n/a | BT33: n/a | BU33: n/a | BW33: 0.96153846 | BX33: 1 | BY33: 0.83333333 | BZ33: 0.93162393
A34: 0.057471264 | B34: 0.0625 | C34: n/a | D34: 0.063291139 | E34: n/a | F34: n/a | G34: n/a | H34: 0.058139535 | I34: n/a | J34: n/a | K34: 0.058139535 | L34: n/a | M34: 0.053763441 | N34: 0.058139535 | O34: 0.056818182 | P34: n/a | Q34: n/a | R34: 0.053763441 | S34: n/a | T34: n/a | U34: n/a | V34: 0.052631579 | W34: 0.053191489 | X34: 0.053763441 | Y34: 0.053191489 | Z34: n/a | AA34: n/a | AB34: 0.053763441 | AC34: 0.05 | AE34: En caso de interrupción durante la visita, el vendedor le pidió disculpas por la interrupción. | AF34: 1 | AG34: n/a | AH34: n/a | AI34: n/a | AJ34: n/a | AK34: n/a | AL34: 0 | AM34: 1 | AN34: n/a | AO34: 1 | AP34: n/a | AQ34: 0 | AR34: n/a | AS34: 1 | AT34: 1 | AU34: n/a | AV34: 0.5 | AW34: n/a | AX34: 1 | AY34: 0 | AZ34: 0.5 | BA34: n/a | BB34: n/a | BC34: n/a | BD34: n/a | BE34: 1 | BF34: n/a | BG34: n/a | BH34: 1 | BI34: 1 | BJ34: n/a | BK34: n/a | BL34: 1 | BM34: n/a | BN34: n/a | BO34: 1 | BP34: n/a | BQ34: n/a | BR34: n/a | BS34: n/a | BT34: n/a | BU34: n/a | BW34: 0.72222222 | BX34: 0.7 | BY34: 1 | BZ34: 0.80740741
AC35: n/a | AE35: DISMAC CLUB - El vendedor/a explicó de qué trata el Dismaclub | AF35: n/a | AG35: n/a | AH35: n/a | AI35: n/a | AJ35: n/a | AK35: n/a | AL35: n/a | AM35: n/a | AN35: n/a | AO35: n/a | AP35: n/a | AQ35: n/a | AR35: n/a | AS35: n/a | AT35: n/a | AU35: n/a | AV35: n/a | AW35: n/a | AX35: n/a | AY35: n/a | AZ35: n/a | BA35: n/a | BB35: n/a | BC35: n/a | BD35: n/a | BE35: n/a | BF35: n/a | BG35: n/a | BH35: n/a | BI35: n/a | BJ35: n/a | BK35: n/a | BL35: n/a | BM35: n/a | BN35: n/a | BO35: n/a | BP35: n/a | BQ35: n/a | BR35: n/a | BS35: n/a | BT35: n/a | BU35: n/a | BW35: n/a | BX35: n/a | BY35: n/a | BZ35: n/a
A36: 1 | B36: 1 | C36: 1 | D36: 1 | E36: 1 | F36: 1 | G36: 1 | H36: 1 | I36: 1 | J36: 1 | K36: 1 | L36: 1 | M36: 1 | N36: 1 | O36: 1 | P36: 1 | Q36: 1 | R36: 1 | S36: 1 | T36: 1 | U36: 1 | V36: 1 | W36: 1 | X36: 1 | Y36: 1 | Z36: 1 | AA36: 1 | AB36: 1 | AC36: 0.15 | AE36: INFORMACIÓN SOBRE LA INSTALACIÓN | AF36: 1 | AG36: n/a | AH36: n/a | AI36: n/a | AJ36: n/a | AK36: n/a | AL36: n/a | AM36: n/a | AN36: n/a | AO36: n/a | AP36: n/a | AQ36: n/a | AR36: n/a | AS36: n/a | AT36: n/a | AU36: 1 | AV36: n/a | AW36: n/a | AX36: n/a | AY36: 1 | AZ36: n/a | BA36: 1 | BB36: n/a | BC36: n/a | BD36: n/a | BE36: n/a | BF36: n/a | BG36: n/a | BH36: n/a | BI36: n/a | BJ36: n/a | BK36: n/a | BL36: n/a | BM36: 1 | BN36: n/a | BO36: n/a | BP36: n/a | BQ36: n/a | BR36: n/a | BS36: n/a | BT36: n/a | BU36: n/a | BW36: 1 | BX36: 1 | BY36: 1 | BZ36: 1
AC37: 0.3333 | AE37: El vendedor/a coordinó y programó la entrega a domicilio del producto | AF37: 1 | AG37: n/a | AH37: n/a | AI37: n/a | AJ37: n/a | AK37: n/a | AL37: n/a | AM37: n/a | AN37: n/a | AO37: n/a | AP37: n/a | AQ37: n/a | AR37: n/a | AS37: n/a | AT37: n/a | AU37: 1 | AV37: n/a | AW37: n/a | AX37: n/a | AY37: 1 | AZ37: n/a | BA37: 1 | BB37: n/a | BC37: n/a | BD37: n/a | BE37: n/a | BF37: n/a | BG37: n/a | BH37: n/a | BI37: n/a | BJ37: n/a | BK37: n/a | BL37: n/a | BM37: 1 | BN37: n/a | BO37: n/a | BP37: n/a | BQ37: n/a | BR37: n/a | BS37: n/a | BT37: n/a | BU37: n/a | BW37: 1 | BX37: 1 | BY37: 1 | BZ37: 1
AC38: 0.3333 | AE38: El vendedor/a coordinó y programó la instalación del producto | AF38: 1 | AG38: n/a | AH38: n/a | AI38: n/a | AJ38: n/a | AK38: n/a | AL38: n/a | AM38: n/a | AN38: n/a | AO38: n/a | AP38: n/a | AQ38: n/a | AR38: n/a | AS38: n/a | AT38: n/a | AU38: 1 | AV38: n/a | AW38: n/a | AX38: n/a | AY38: n/a | AZ38: n/a | BA38: 1 | BB38: n/a | BC38: n/a | BD38: n/a | BE38: n/a | BF38: n/a | BG38: n/a | BH38: n/a | BI38: n/a | BJ38: n/a | BK38: n/a | BL38: n/a | BM38: n/a | BN38: n/a | BO38: n/a | BP38: n/a | BQ38: n/a | BR38: n/a | BS38: n/a | BT38: n/a | BU38: n/a | BW38: 1 | BX38: 1 | BY38: n/a | BZ38: 1
AC39: 0.3333 | AE39: El vendedor/a informó y explicó los requisitos previos de instalación del producto | AF39: 1 | AG39: n/a | AH39: n/a | AI39: n/a | AJ39: n/a | AK39: n/a | AL39: n/a | AM39: n/a | AN39: n/a | AO39: n/a | AP39: n/a | AQ39: n/a | AR39: n/a | AS39: n/a | AT39: n/a | AU39: 1 | AV39: n/a | AW39: n/a | AX39: n/a | AY39: n/a | AZ39: n/a | BA39: 1 | BB39: n/a | BC39: n/a | BD39: n/a | BE39: n/a | BF39: n/a | BG39: n/a | BH39: n/a | BI39: n/a | BJ39: n/a | BK39: n/a | BL39: n/a | BM39: 1 | BN39: n/a | BO39: n/a | BP39: n/a | BQ39: n/a | BR39: n/a | BS39: n/a | BT39: n/a | BU39: n/a | BW39: 1 | BX39: 1 | BY39: 1 | BZ39: 1
AC40: 0.1 | AE40: DESPEDIDA | AF40: 0.83333333 | AG40: 0.66666667 | AH40: n/a | AI40: 0.66666667 | AJ40: n/a | AK40: n/a | AL40: 1 | AM40: 0.83333333 | AN40: n/a | AO40: 0.83333333 | AP40: n/a | AQ40: 0.66666667 | AR40: 0.83333333 | AS40: 0.83333333 | AT40: 0.66666667 | AU40: 0.83333333 | AV40: 1 | AW40: n/a | AX40: 1 | AY40: 0.33333333 | AZ40: 0.83333333 | BA40: 0.83333333 | BB40: n/a | BC40: n/a | BD40: n/a | BE40: 0.83333333 | BF40: n/a | BG40: 0.83333333 | BH40: 0.66666667 | BI40: 1 | BJ40: n/a | BK40: n/a | BL40: 0.83333333 | BM40: 0.66666667 | BN40: 0.83333333 | BO40: 1 | BP40: 0.83333333 | BQ40: n/a | BR40: n/a | BS40: n/a | BT40: n/a | BU40: n/a | BW40: 0.82051282 | BX40: 0.76190476 | BY40: 0.77777778 | BZ40: 0.78673179
AC41: 0.3333 | AE41: El vendedor/a le solicitó sus datos personales y en caso de no estar registrado en su sistema, lo registró | AF41: 0.5 | AG41: 0.5 | AH41: n/a | AI41: 0.5 | AJ41: n/a | AK41: n/a | AL41: 1 | AM41: 0.5 | AN41: n/a | AO41: 0.5 | AP41: n/a | AQ41: 0.5 | AR41: 0.5 | AS41: 0.5 | AT41: 0.5 | AU41: 0.5 | AV41: 1 | AW41: n/a | AX41: 1 | AY41: 0.5 | AZ41: 0.5 | BA41: 0.5 | BB41: n/a | BC41: n/a | BD41: n/a | BE41: 0.5 | BF41: n/a | BG41: 0.5 | BH41: 0.5 | BI41: 1 | BJ41: n/a | BK41: n/a | BL41: 1 | BM41: 0.5 | BN41: 0.5 | BO41: 1 | BP41: 0.5 | BQ41: n/a | BR41: n/a | BS41: n/a | BT41: n/a | BU41: n/a | BW41: 0.61538462 | BX41: 0.57142857 | BY41: 0.66666667 | BZ41: 0.61782662
AC42: 0.3333 | AE42: El vendedor/a lo dirigió a caja para efectuar el pago. | AF42: 1 | AG42: 1 | AH42: n/a | AI42: 1 | AJ42: n/a | AK42: n/a | AL42: 1 | AM42: 1 | AN42: n/a | AO42: 1 | AP42: n/a | AQ42: 1 | AR42: 1 | AS42: 1 | AT42: 1 | AU42: 1 | AV42: 1 | AW42: n/a | AX42: 1 | AY42: 0 | AZ42: 1 | BA42: 1 | BB42: n/a | BC42: n/a | BD42: n/a | BE42: 1 | BF42: n/a | BG42: 1 | BH42: 1 | BI42: 1 | BJ42: n/a | BK42: n/a | BL42: 1 | BM42: 1 | BN42: 1 | BO42: 1 | BP42: 1 | BQ42: n/a | BR42: n/a | BS42: n/a | BT42: n/a | BU42: n/a | BW42: 1 | BX42: 0.85714286 | BY42: 1 | BZ42: 0.95238095
AC43: 0.3333 | AE43: El vendedor/a se despidió amablemente y lo invito a visitar nuevamente la tienda | AF43: 1 | AG43: 0.5 | AH43: n/a | AI43: 0.5 | AJ43: n/a | AK43: n/a | AL43: 1 | AM43: 1 | AN43: n/a | AO43: 1 | AP43: n/a | AQ43: 0.5 | AR43: 1 | AS43: 1 | AT43: 0.5 | AU43: 1 | AV43: 1 | AW43: n/a | AX43: 1 | AY43: 0.5 | AZ43: 1 | BA43: 1 | BB43: n/a | BC43: n/a | BD43: n/a | BE43: 1 | BF43: n/a | BG43: 1 | BH43: 0.5 | BI43: 1 | BJ43: n/a | BK43: n/a | BL43: 0.5 | BM43: 0.5 | BN43: 1 | BO43: 1 | BP43: 1 | BQ43: n/a | BR43: n/a | BS43: n/a | BT43: n/a | BU43: n/a | BW43: 0.84615385 | BX43: 0.85714286 | BY43: 0.66666667 | BZ43: 0.78998779
AC44: 0.1 | AE44: PRESENTACIÓN PERSONAL DEL VENDEDOR/A | AF44: 1 | AG44: 1 | AH44: n/a | AI44: 1 | AJ44: n/a | AK44: n/a | AL44: 1 | AM44: 1 | AN44: n/a | AO44: 1 | AP44: n/a | AQ44: 1 | AR44: 1 | AS44: 1 | AT44: 1 | AU44: 1 | AV44: 1 | AW44: n/a | AX44: 1 | AY44: 1 | AZ44: 1 | BA44: 1 | BB44: n/a | BC44: n/a | BD44: n/a | BE44: 0.75 | BF44: n/a | BG44: 0.75 | BH44: 1 | BI44: 1 | BJ44: n/a | BK44: n/a | BL44: 1 | BM44: 1 | BN44: 1 | BO44: 1 | BP44: 0.75 | BQ44: 0 | BR44: 0 | BS44: 0 | BT44: 0 | BU44: 0 | BW44: 1 | BX44: 0.92857143 | BY44: 1 | BZ44: 0.97619048
AC45: 0.5 | AE45: El vendedor/a se encontraba con el uniforme de la empresa. | AF45: 1 | AG45: 1 | AH45: n/a | AI45: 1 | AJ45: n/a | AK45: n/a | AL45: 1 | AM45: 1 | AN45: n/a | AO45: 1 | AP45: n/a | AQ45: 1 | AR45: 1 | AS45: 1 | AT45: 1 | AU45: 1 | AV45: 1 | AW45: n/a | AX45: 1 | AY45: 1 | AZ45: 1 | BA45: 1 | BB45: n/a | BC45: n/a | BD45: n/a | BE45: 1 | BF45: n/a | BG45: 1 | BH45: 1 | BI45: 1 | BJ45: n/a | BK45: n/a | BL45: 1 | BM45: 1 | BN45: 1 | BO45: 1 | BP45: 0.5 | BQ45: n/a | BR45: n/a | BS45: n/a | BT45: n/a | BU45: n/a | BW45: 1 | BX45: 1 | BY45: 1 | BZ45: 1
AC46: 0.5 | AE46: El vendedor/a tenía buena presencia (El cabello no está en su rostro, está limpio y prolijo) | AF46: 1 | AG46: 1 | AH46: n/a | AI46: 1 | AJ46: n/a | AK46: n/a | AL46: 1 | AM46: 1 | AN46: n/a | AO46: 1 | AP46: n/a | AQ46: 1 | AR46: 1 | AS46: 1 | AT46: 1 | AU46: 1 | AV46: 1 | AW46: n/a | AX46: 1 | AY46: 1 | AZ46: 1 | BA46: 1 | BB46: n/a | BC46: n/a | BD46: n/a | BE46: 0.5 | BF46: n/a | BG46: 0.5 | BH46: 1 | BI46: 1 | BJ46: n/a | BK46: n/a | BL46: 1 | BM46: 1 | BN46: 1 | BO46: 1 | BP46: 1 | BQ46: n/a | BR46: n/a | BS46: n/a | BT46: n/a | BU46: n/a | BW46: 1 | BX46: 0.85714286 | BY46: 1 | BZ46: 0.95238095
AB48: 0.29411765 | AC48: 0.25 | AD48: 0 | AE48: PRIMER CONTACTO | AF48: 1 | AG48: 1 | AH48: n/a | AI48: 1 | AJ48: n/a | AK48: n/a | AL48: 1 | AM48: 1 | AN48: n/a | AO48: 1 | AP48: n/a | AQ48: 0.85 | AR48: 1 | AS48: 1 | AT48: 0.85 | AU48: 1 | AV48: 1 | AW48: n/a | AX48: 1 | AY48: 0.55 | AZ48: 0.7 | BA48: 0.7 | BB48: n/a | BC48: n/a | BD48: n/a | BE48: 0.7 | BF48: n/a | BG48: 0.6 | BH48: 1 | BI48: 0.85 | BJ48: n/a | BK48: n/a | BL48: 1 | BM48: 1 | BN48: 1 | BO48: 1 | BP48: 1 | BQ48: n/a | BR48: n/a | BS48: n/a | BT48: n/a | BU48: n/a
AB49: 0.47058824 | AC49: 0.4 | AD49: 0 | AE49: GESTION DE VENTA | AF49: 0.92473118 | AG49: 0.69318182 | AH49: n/a | AI49: 0.75308642 | AJ49: n/a | AK49: n/a | AL49: 0.88172043 | AM49: 0.54301075 | AN49: n/a | AO49: 1 | AP49: n/a | AQ49: 0.44 | AR49: 0.88636364 | AS49: 0.97 | AT49: 0.63 | AU49: 1 | AV49: 0.91 | AW49: n/a | AX49: 0.96511628 | AY49: 0.62365591 | AZ49: 0.61 | BA49: 0.75263158 | BB49: n/a | BC49: n/a | BD49: n/a | BE49: 0.78723404 | BF49: n/a | BG49: 0.58421053 | BH49: 0.69 | BI49: 0.795 | BJ49: n/a | BK49: n/a | BL49: 0.69354839 | BM49: 0.80681818 | BN49: 0.74210526 | BO49: 0.74193548 | BP49: 0.92045455 | BQ49: 0 | BR49: 0 | BS49: 0 | BT49: 0 | BU49: 0
AB50: n/a | AC50: 0.15 | AD50: 0 | AE50: INFORMACIÓN SOBRE LA INSTALACIÓN | AF50: 1 | AG50: n/a | AH50: n/a | AI50: n/a | AJ50: n/a | AK50: n/a | AL50: n/a | AM50: n/a | AN50: n/a | AO50: n/a | AP50: n/a | AQ50: n/a | AR50: n/a | AS50: n/a | AT50: n/a | AU50: 1 | AV50: n/a | AW50: n/a | AX50: n/a | AY50: 1 | AZ50: n/a | BA50: 1 | BB50: n/a | BC50: n/a | BD50: n/a | BE50: n/a | BF50: n/a | BG50: n/a | BH50: n/a | BI50: n/a | BJ50: n/a | BK50: n/a | BL50: n/a | BM50: 1 | BN50: n/a | BO50: n/a | BP50: n/a
AB51: 0.11764706 | AC51: 0.1 | AD51: 0 | AE51: DESPEDIDA | AF51: 0.83333333 | AG51: 0.66666667 | AH51: n/a | AI51: 0.66666667 | AJ51: n/a | AK51: n/a | AL51: 1 | AM51: 0.83333333 | AN51: n/a | AO51: 0.83333333 | AP51: n/a | AQ51: 0.66666667 | AR51: 0.83333333 | AS51: 0.83333333 | AT51: 0.66666667 | AU51: 0.83333333 | AV51: 1 | AW51: n/a | AX51: 1 | AY51: 0.33333333 | AZ51: 0.83333333 | BA51: 0.83333333 | BB51: n/a | BC51: n/a | BD51: n/a | BE51: 0.83333333 | BF51: n/a | BG51: 0.83333333 | BH51: 0.66666667 | BI51: 1 | BJ51: n/a | BK51: n/a | BL51: 0.83333333 | BM51: 0.66666667 | BN51: 0.83333333 | BO51: 1 | BP51: 0.83333333 | BQ51: n/a | BR51: n/a | BS51: n/a | BT51: n/a | BU51: n/a
AB52: 0.11764706 | AC52: 0.1 | AD52: 0 | AE52: PRESENTACIÓN PERSONAL DEL VENDEDOR/A | AF52: 1 | AG52: 1 | AH52: n/a | AI52: 1 | AJ52: n/a | AK52: n/a | AL52: 1 | AM52: 1 | AN52: n/a | AO52: 1 | AP52: n/a | AQ52: 1 | AR52: 1 | AS52: 1 | AT52: 1 | AU52: 1 | AV52: 1 | AW52: n/a | AX52: 1 | AY52: 1 | AZ52: 1 | BA52: 1 | BB52: n/a | BC52: n/a | BD52: n/a | BE52: 0.75 | BF52: n/a | BG52: 0.75 | BH52: 1 | BI52: 1 | BJ52: n/a | BK52: n/a | BL52: 1 | BM52: 1 | BN52: 1 | BO52: 1 | BP52: 0.75 | BQ52: 0 | BR52: 0 | BS52: 0 | BT52: 0 | BU52: 0
AC54: 0.22 | AE54: ATENCIÓN EN CAJA | AF54: 1 | AG54: 1 | AH54: n/a | AI54: 1 | AJ54: n/a | AK54: n/a | AL54: 1 | AM54: 1 | AN54: n/a | AO54: 1 | AP54: n/a | AQ54: 0.75 | AR54: 0.60714286 | AS54: 1 | AT54: 1 | AU54: 0.74285714 | AV54: 0.75 | AW54: n/a | AX54: 1 | AY54: 0.8 | AZ54: 0.75 | BA54: 1 | BB54: n/a | BC54: n/a | BD54: n/a | BE54: 0.75 | BF54: n/a | BG54: 0.75 | BH54: 1 | BI54: 0.75 | BJ54: n/a | BK54: n/a | BL54: 1 | BM54: 0.8 | BN54: 1 | BO54: 1 | BP54: 1 | BQ54: n/a | BR54: n/a | BS54: n/a | BT54: n/a | BU54: n/a | BW54: 0.91153846 | BX54: 0.82857143 | BY54: 0.93333333 | BZ54: 0.89114774
AC55: 0.4 | AE55: ATENCIÓN EN CAJA | AF55: 1 | AG55: 1 | AH55: n/a | AI55: 1 | AJ55: n/a | AK55: n/a | AL55: 1 | AM55: 1 | AN55: n/a | AO55: 1 | AP55: n/a | AQ55: 1 | AR55: 0.71428571 | AS55: 1 | AT55: 1 | AU55: 0.85714286 | AV55: 1 | AW55: n/a | AX55: 1 | AY55: 1 | AZ55: 1 | BA55: 1 | BB55: n/a | BC55: n/a | BD55: n/a | BE55: 1 | BF55: n/a | BG55: 1 | BH55: 1 | BI55: 1 | BJ55: n/a | BK55: n/a | BL55: 1 | BM55: 1 | BN55: 1 | BO55: 1 | BP55: 1 | BQ55: n/a | BR55: n/a | BS55: n/a | BT55: n/a | BU55: n/a | BW55: 0.96703297 | BX55: 1 | BY55: 1 | BZ55: 0.98901099
AC56: 0.1429 | AE56: El cajero/a saludó amablemente. | AF56: 1 | AG56: 1 | AH56: n/a | AI56: 1 | AJ56: n/a | AK56: n/a | AL56: 1 | AM56: 1 | AN56: n/a | AO56: 1 | AP56: n/a | AQ56: 1 | AR56: 0 | AS56: 1 | AT56: 1 | AU56: 1 | AV56: 1 | AW56: n/a | AX56: 1 | AY56: 1 | AZ56: n/a | BA56: 1 | BB56: n/a | BC56: n/a | BD56: n/a | BE56: 1 | BF56: n/a | BG56: 1 | BH56: 1 | BI56: n/a | BJ56: n/a | BK56: n/a | BL56: 1 | BM56: 1 | BN56: 1 | BO56: 1 | BP56: 1 | BQ56: n/a | BR56: n/a | BS56: n/a | BT56: n/a | BU56: n/a | BW56: 0.92307692 | BX56: 1 | BY56: 1 | BZ56: 0.97435897
AC57: 0.1429 | AE57: El cajero/a respetó el orden de llegada. | AF57: 1 | AG57: 1 | AH57: n/a | AI57: 1 | AJ57: n/a | AK57: n/a | AL57: 1 | AM57: 1 | AN57: n/a | AO57: 1 | AP57: n/a | AQ57: 1 | AR57: 1 | AS57: 1 | AT57: 1 | AU57: 1 | AV57: 1 | AW57: n/a | AX57: 1 | AY57: 1 | AZ57: n/a | BA57: 1 | BB57: n/a | BC57: n/a | BD57: n/a | BE57: 1 | BF57: n/a | BG57: n/a | BH57: 1 | BI57: 1 | BJ57: n/a | BK57: n/a | BL57: 1 | BM57: 1 | BN57: 1 | BO57: 1 | BP57: 1 | BQ57: n/a | BR57: n/a | BS57: n/a | BT57: n/a | BU57: n/a | BW57: 1 | BX57: 1 | BY57: 1 | BZ57: 1
AC58: 0.1429 | AE58: El cajero/a le comunicó sobre el monto a pagar y realizó el proceso de facturación (Pide NIT y explica la implementación de la facturación electrónica, es decir pide los datos al cliente, explica que la factura le llegará por correo o a su teléfono (opcional) y efectivamente la factura le llegó por uno de estos medios). | AF58: 1 | AG58: 1 | AH58: n/a | AI58: 1 | AJ58: n/a | AK58: n/a | AL58: 1 | AM58: 1 | AN58: n/a | AO58: 1 | AP58: n/a | AQ58: 1 | AR58: 1 | AS58: 1 | AT58: 1 | AU58: 1 | AV58: 1 | AW58: n/a | AX58: 1 | AY58: 1 | AZ58: 1 | BA58: 1 | BB58: n/a | BC58: n/a | BD58: n/a | BE58: 1 | BF58: n/a | BG58: 1 | BH58: 1 | BI58: 1 | BJ58: n/a | BK58: n/a | BL58: 1 | BM58: 1 | BN58: 1 | BO58: 1 | BP58: 1 | BQ58: n/a | BR58: n/a | BS58: n/a | BT58: n/a | BU58: n/a | BW58: 1 | BX58: 1 | BY58: 1 | BZ58: 1
AC59: 0.1429 | AE59: El cajero/a entregó la garantía del producto o indicó que esta venía dentro de la caja del producto. (Aplica solo en caso de refrigeradores, cocinas, freezers, lavadoras, microondas y Aires Acondicionados) | AF59: 1 | AG59: 1 | AH59: n/a | AI59: 1 | AJ59: n/a | AK59: n/a | AL59: 1 | AM59: 1 | AN59: n/a | AO59: 1 | AP59: n/a | AQ59: 1 | AR59: 1 | AS59: 1 | AT59: 1 | AU59: 1 | AV59: 1 | AW59: n/a | AX59: 1 | AY59: 1 | AZ59: 1 | BA59: 1 | BB59: n/a | BC59: n/a | BD59: n/a | BE59: 1 | BF59: n/a | BG59: 1 | BH59: 1 | BI59: 1 | BJ59: n/a | BK59: n/a | BL59: 1 | BM59: 1 | BN59: 1 | BO59: 1 | BP59: 1 | BQ59: n/a | BR59: n/a | BS59: n/a | BT59: n/a | BU59: n/a | BW59: 1 | BX59: 1 | BY59: 1 | BZ59: 1
AC60: 0.1429 | AE60: El cajero/a lo dirigió o le indicó quien es el encargado de hacer la entrega | AF60: 1 | AG60: 1 | AH60: n/a | AI60: 1 | AJ60: n/a | AK60: n/a | AL60: 1 | AM60: 1 | AN60: n/a | AO60: 1 | AP60: n/a | AQ60: 1 | AR60: 1 | AS60: 1 | AT60: 1 | AU60: 1 | AV60: 1 | AW60: n/a | AX60: 1 | AY60: 1 | AZ60: n/a | BA60: 1 | BB60: n/a | BC60: n/a | BD60: n/a | BE60: 1 | BF60: n/a | BG60: 1 | BH60: 1 | BI60: 1 | BJ60: n/a | BK60: n/a | BL60: 1 | BM60: 1 | BN60: 1 | BO60: 1 | BP60: 1 | BQ60: n/a | BR60: n/a | BS60: n/a | BT60: n/a | BU60: n/a | BW60: 1 | BX60: 1 | BY60: 1 | BZ60: 1
AC61: 0.1429 | AE61: El cajero/a lo atendió con rapidez en el cobro, facturación. | AF61: 1 | AG61: 1 | AH61: n/a | AI61: 1 | AJ61: n/a | AK61: n/a | AL61: 1 | AM61: 1 | AN61: n/a | AO61: 1 | AP61: n/a | AQ61: 1 | AR61: 1 | AS61: 1 | AT61: 1 | AU61: 1 | AV61: 1 | AW61: n/a | AX61: 1 | AY61: 1 | AZ61: 1 | BA61: 1 | BB61: n/a | BC61: n/a | BD61: n/a | BE61: 1 | BF61: n/a | BG61: 1 | BH61: 1 | BI61: 1 | BJ61: n/a | BK61: n/a | BL61: 1 | BM61: 1 | BN61: 1 | BO61: 1 | BP61: 1 | BQ61: n/a | BR61: n/a | BS61: n/a | BT61: n/a | BU61: n/a | BW61: 1 | BX61: 1 | BY61: 1 | BZ61: 1
AC62: 0.1429 | AE62: El cajero agradecio la compra, se despidió amablemente "Hasta luego" "Que tenga un buen día" "Que le vaya bien" y lo invitó a visitar la tienda nuevamente | AF62: 1 | AG62: 1 | AH62: n/a | AI62: 1 | AJ62: n/a | AK62: n/a | AL62: 1 | AM62: 1 | AN62: n/a | AO62: 1 | AP62: n/a | AQ62: 1 | AR62: 0 | AS62: 1 | AT62: 1 | AU62: 0 | AV62: 1 | AW62: n/a | AX62: 1 | AY62: 1 | AZ62: 1 | BA62: 1 | BB62: n/a | BC62: n/a | BD62: n/a | BE62: 1 | BF62: n/a | BG62: 1 | BH62: 1 | BI62: 1 | BJ62: n/a | BK62: n/a | BL62: 1 | BM62: 1 | BN62: 1 | BO62: 1 | BP62: 1 | BQ62: n/a | BR62: n/a | BS62: n/a | BT62: n/a | BU62: n/a | BW62: 0.84615385 | BX62: 1 | BY62: 1 | BZ62: 0.94871795
AC63: 0.2 | AE63: INFORMACIÓN SOBRE LA ENTREGA E INSTALACIÓN DE PRODUCTOS | AF63: 1 | AG63: n/a | AH63: n/a | AI63: n/a | AJ63: n/a | AK63: n/a | AL63: n/a | AM63: n/a | AN63: n/a | AO63: n/a | AP63: n/a | AQ63: n/a | AR63: n/a | AS63: n/a | AT63: n/a | AU63: 0 | AV63: n/a | AW63: n/a | AX63: n/a | AY63: 0 | AZ63: n/a | BA63: 1 | BB63: n/a | BC63: n/a | BD63: n/a | BE63: n/a | BF63: n/a | BG63: n/a | BH63: n/a | BI63: n/a | BJ63: n/a | BK63: n/a | BL63: n/a | BM63: 1 | BN63: n/a | BO63: n/a | BP63: n/a | BQ63: n/a | BR63: n/a | BS63: n/a | BT63: n/a | BU63: n/a | BW63: 0.5 | BX63: 0.5 | BY63: 1 | BZ63: 0.66666667
AC64: 0.25 | AE64: El cajero/a validó la fecha de entrega a domicilio del producto | AF64: 1 | AG64: n/a | AH64: n/a | AI64: n/a | AJ64: n/a | AK64: n/a | AL64: n/a | AM64: n/a | AN64: n/a | AO64: n/a | AP64: n/a | AQ64: n/a | AR64: n/a | AS64: n/a | AT64: n/a | AU64: 0 | AV64: n/a | AW64: n/a | AX64: n/a | AY64: 0 | AZ64: n/a | BA64: 1 | BB64: n/a | BC64: n/a | BD64: n/a | BE64: n/a | BF64: n/a | BG64: n/a | BH64: n/a | BI64: n/a | BJ64: n/a | BK64: n/a | BL64: n/a | BM64: 1 | BN64: n/a | BO64: n/a | BP64: n/a | BQ64: n/a | BR64: n/a | BS64: n/a | BT64: n/a | BU64: n/a | BW64: 0.5 | BX64: 0.5 | BY64: 1 | BZ64: 0.66666667
AC65: 0.25 | AE65: El cajero/a validó la fecha de instalación del producto | AF65: 1 | AG65: n/a | AH65: n/a | AI65: n/a | AJ65: n/a | AK65: n/a | AL65: n/a | AM65: n/a | AN65: n/a | AO65: n/a | AP65: n/a | AQ65: n/a | AR65: n/a | AS65: n/a | AT65: n/a | AU65: n/a | AV65: n/a | AW65: n/a | AX65: n/a | AY65: n/a | AZ65: n/a | BA65: 1 | BB65: n/a | BC65: n/a | BD65: n/a | BE65: n/a | BF65: n/a | BG65: n/a | BH65: n/a | BI65: n/a | BJ65: n/a | BK65: n/a | BL65: n/a | BM65: n/a | BN65: n/a | BO65: n/a | BP65: n/a | BQ65: n/a | BR65: n/a | BS65: n/a | BT65: n/a | BU65: n/a | BW65: 1 | BX65: 1 | BY65: n/a | BZ65: 1
AC66: 0.25 | AE66: El cajero/a validó que el vendedor explicó los requisitos previos de instalacion del producto, que el cliente entiende estos requisitos, y el cajero entregó los requisitos impresos al cliente. | AF66: 1 | AG66: n/a | AH66: n/a | AI66: n/a | AJ66: n/a | AK66: n/a | AL66: n/a | AM66: n/a | AN66: n/a | AO66: n/a | AP66: n/a | AQ66: n/a | AR66: n/a | AS66: n/a | AT66: n/a | AU66: 0 | AV66: n/a | AW66: n/a | AX66: n/a | AY66: 0 | AZ66: n/a | BA66: 1 | BB66: n/a | BC66: n/a | BD66: n/a | BE66: n/a | BF66: n/a | BG66: n/a | BH66: n/a | BI66: n/a | BJ66: n/a | BK66: n/a | BL66: n/a | BM66: n/a | BN66: n/a | BO66: n/a | BP66: n/a | BQ66: n/a | BR66: n/a | BS66: n/a | BT66: n/a | BU66: n/a | BW66: 0.5 | BX66: 0.5 | BY66: n/a | BZ66: 0.5
AC67: 0.25 | AE67: El cajero informó y explicó al cliente que para cualquier cambio de horario que quiera realizar en la programación de la entrega o instalación debe llamar al número 800 10 2000 | AF67: 1 | AG67: n/a | AH67: n/a | AI67: n/a | AJ67: n/a | AK67: n/a | AL67: n/a | AM67: n/a | AN67: n/a | AO67: n/a | AP67: n/a | AQ67: n/a | AR67: n/a | AS67: n/a | AT67: n/a | AU67: 0 | AV67: n/a | AW67: n/a | AX67: n/a | AY67: 0 | AZ67: n/a | BA67: 1 | BB67: n/a | BC67: n/a | BD67: n/a | BE67: n/a | BF67: n/a | BG67: n/a | BH67: n/a | BI67: n/a | BJ67: n/a | BK67: n/a | BL67: n/a | BM67: 1 | BN67: n/a | BO67: n/a | BP67: n/a | BQ67: n/a | BR67: n/a | BS67: n/a | BT67: n/a | BU67: n/a | BW67: 0.5 | BX67: 0.5 | BY67: 1 | BZ67: 0.66666667
AC68: 0.2 | AE68: MINI CUOTAS - El cajero/a consultó el método de pago y ofreció MINICUOTAS | AF68: 1 | AG68: 1 | AH68: n/a | AI68: 1 | AJ68: n/a | AK68: n/a | AL68: 1 | AM68: 1 | AN68: n/a | AO68: 1 | AP68: n/a | AQ68: 0 | AR68: 0 | AS68: 1 | AT68: 1 | AU68: 1 | AV68: 0 | AW68: n/a | AX68: 1 | AY68: 1 | AZ68: 0 | BA68: 1 | BB68: n/a | BC68: n/a | BD68: n/a | BE68: 0 | BF68: n/a | BG68: 0 | BH68: 1 | BI68: 0 | BJ68: n/a | BK68: n/a | BL68: 1 | BM68: 0 | BN68: 1 | BO68: 1 | BP68: 1 | BQ68: n/a | BR68: n/a | BS68: n/a | BT68: n/a | BU68: n/a | BW68: 0.76923077 | BX68: 0.42857143 | BY68: 0.66666667 | BZ68: 0.62148962
AC69: 0.2 | AE69: PRESENTACIÓN PERSONAL DEL CAJERO | AF69: 1 | AG69: 1 | AH69: n/a | AI69: 1 | AJ69: n/a | AK69: n/a | AL69: 1 | AM69: 1 | AN69: n/a | AO69: 1 | AP69: n/a | AQ69: 1 | AR69: 1 | AS69: 1 | AT69: 1 | AU69: 1 | AV69: 1 | AW69: n/a | AX69: 1 | AY69: 1 | AZ69: 1 | BA69: 1 | BB69: n/a | BC69: n/a | BD69: n/a | BE69: 1 | BF69: n/a | BG69: 1 | BH69: 1 | BI69: 1 | BJ69: n/a | BK69: n/a | BL69: 1 | BM69: 1 | BN69: 1 | BO69: 1 | BP69: 1 | BQ69: n/a | BR69: n/a | BS69: n/a | BT69: n/a | BU69: n/a | BW69: 1 | BX69: 1 | BY69: 1 | BZ69: 1
AC70: 0.5 | AE70: El cajero/a se encontraba con el uniforme de la empresa. | AF70: 1 | AG70: 1 | AH70: n/a | AI70: 1 | AJ70: n/a | AK70: n/a | AL70: 1 | AM70: 1 | AN70: n/a | AO70: 1 | AP70: n/a | AQ70: 1 | AR70: 1 | AS70: 1 | AT70: 1 | AU70: 1 | AV70: 1 | AW70: n/a | AX70: 1 | AY70: 1 | AZ70: 1 | BA70: 1 | BB70: n/a | BC70: n/a | BD70: n/a | BE70: 1 | BF70: n/a | BG70: 1 | BH70: 1 | BI70: 1 | BJ70: n/a | BK70: n/a | BL70: 1 | BM70: 1 | BN70: 1 | BO70: 1 | BP70: 1 | BQ70: n/a | BR70: n/a | BS70: n/a | BT70: n/a | BU70: n/a | BW70: 1 | BX70: 1 | BY70: 1 | BZ70: 1
AC71: 0.5 | AE71: El cajero/a tenía buena presencia (El cabello no está en su rostro, está limpio y prolijo) | AF71: 1 | AG71: 1 | AH71: n/a | AI71: 1 | AJ71: n/a | AK71: n/a | AL71: 1 | AM71: 1 | AN71: n/a | AO71: 1 | AP71: n/a | AQ71: 1 | AR71: 1 | AS71: 1 | AT71: 1 | AU71: 1 | AV71: 1 | AW71: n/a | AX71: 1 | AY71: 1 | AZ71: 1 | BA71: 1 | BB71: n/a | BC71: n/a | BD71: n/a | BE71: 1 | BF71: n/a | BG71: 1 | BH71: 1 | BI71: 1 | BJ71: n/a | BK71: n/a | BL71: 1 | BM71: 1 | BN71: 1 | BO71: 1 | BP71: 1 | BQ71: n/a | BR71: n/a | BS71: n/a | BT71: n/a | BU71: n/a | BW71: 1 | BX71: 1 | BY71: 1 | BZ71: 1
AA73: 0.66666667 | AB73: 0.5 | AC73: 0.4 | AD73: 0 | AE73: ATENCIÓN EN CAJA | AF73: 1 | AG73: 1 | AH73: n/a | AI73: 1 | AJ73: n/a | AK73: n/a | AL73: 1 | AM73: 1 | AN73: n/a | AO73: 1 | AP73: n/a | AQ73: 1 | AR73: 0.71428571 | AS73: 1 | AT73: 1 | AU73: 0.85714286 | AV73: 1 | AW73: n/a | AX73: 1 | AY73: 1 | AZ73: 1 | BA73: 1 | BB73: n/a | BC73: n/a | BD73: n/a | BE73: 1 | BF73: n/a | BG73: 1 | BH73: 1 | BI73: 1 | BJ73: n/a | BK73: n/a | BL73: 1 | BM73: 1 | BN73: 1 | BO73: 1 | BP73: 1 | BQ73: n/a | BR73: n/a | BS73: n/a | BT73: n/a | BU73: n/a
AA74: n/a | AB74: n/a | AC74: 0.2 | AD74: 0 | AE74: INFORMACIÓN SOBRE LA ENTREGA E INSTALACIÓN DE PRODUCTOS | AF74: 1 | AG74: n/a | AH74: n/a | AI74: n/a | AJ74: n/a | AK74: n/a | AL74: n/a | AM74: n/a | AN74: n/a | AO74: n/a | AP74: n/a | AQ74: n/a | AR74: n/a | AS74: n/a | AT74: n/a | AU74: 0 | AV74: n/a | AW74: n/a | AX74: n/a | AY74: 0 | AZ74: n/a | BA74: 1 | BB74: n/a | BC74: n/a | BD74: n/a | BE74: n/a | BF74: n/a | BG74: n/a | BH74: n/a | BI74: n/a | BJ74: n/a | BK74: n/a | BL74: n/a | BM74: 1 | BN74: n/a | BO74: n/a | BP74: n/a | BQ74: n/a | BR74: n/a | BS74: n/a | BT74: n/a | BU74: n/a
AA75: n/a | AB75: 0.25 | AC75: 0.2 | AD75: 0 | AE75: MINI CUOTAS - El cajero/a consultó el método de pago y ofreció MINICUOTAS | AF75: 1 | AG75: 1 | AH75: n/a | AI75: 1 | AJ75: n/a | AK75: n/a | AL75: 1 | AM75: 1 | AN75: n/a | AO75: 1 | AP75: n/a | AQ75: 0 | AR75: 0 | AS75: 1 | AT75: 1 | AU75: 1 | AV75: 0 | AW75: n/a | AX75: 1 | AY75: 1 | AZ75: 0 | BA75: 1 | BB75: n/a | BC75: n/a | BD75: n/a | BE75: 0 | BF75: n/a | BG75: 0 | BH75: 1 | BI75: 0 | BJ75: n/a | BK75: n/a | BL75: 1 | BM75: 0 | BN75: 1 | BO75: 1 | BP75: 1 | BQ75: n/a | BR75: n/a | BS75: n/a | BT75: n/a | BU75: n/a
AA76: 0.33333333 | AB76: 0.25 | AC76: 0.2 | AD76: 0 | AE76: PRESENTACIÓN PERSONAL DEL CAJERO | AF76: 1 | AG76: 1 | AH76: n/a | AI76: 1 | AJ76: n/a | AK76: n/a | AL76: 1 | AM76: 1 | AN76: n/a | AO76: 1 | AP76: n/a | AQ76: 1 | AR76: 1 | AS76: 1 | AT76: 1 | AU76: 1 | AV76: 1 | AW76: n/a | AX76: 1 | AY76: 1 | AZ76: 1 | BA76: 1 | BB76: n/a | BC76: n/a | BD76: n/a | BE76: 1 | BF76: n/a | BG76: 1 | BH76: 1 | BI76: 1 | BJ76: n/a | BK76: n/a | BL76: 1 | BM76: 1 | BN76: 1 | BO76: 1 | BP76: 1 | BQ76: n/a | BR76: n/a | BS76: n/a | BT76: n/a | BU76: n/a
AH77: #REF!
AC78: 0.11 | AE78: ATENCIÓN POSTPAGO | AF78: n/a | AG78: 0.9999 | AH78: n/a | AI78: 0.9999 | AJ78: n/a | AK78: n/a | AL78: 0.9999 | AM78: 0.9999 | AN78: n/a | AO78: 0.9999 | AP78: n/a | AQ78: 0.5 | AR78: 0.9999 | AS78: 0.9999 | AT78: 0.9999 | AU78: n/a | AV78: 0.9999 | AW78: n/a | AX78: 0.9999 | AY78: n/a | AZ78: 1 | BA78: n/a | BB78: n/a | BC78: n/a | BD78: n/a | BE78: 0.9999 | BF78: n/a | BG78: 0.6666 | BH78: 0.9999 | BI78: 0.9999 | BJ78: n/a | BK78: n/a | BL78: 0.5 | BM78: n/a | BN78: 0.9999 | BO78: 1 | BP78: 1 | BQ78: #REF! | BR78: #REF! | BS78: #REF! | BT78: #REF! | BU78: #REF! | BW78: 0.95445455 | BX78: 0.93326 | BY78: 0.74995 | BZ78: 0.87922152
AC79: 1 | AE79: ENTREGA EN TIENDA | AF79: n/a | AG79: 0.9999 | AH79: n/a | AI79: 0.9999 | AJ79: n/a | AK79: n/a | AL79: 0.9999 | AM79: 0.9999 | AN79: n/a | AO79: 0.9999 | AP79: n/a | AQ79: 0.5 | AR79: 0.9999 | AS79: 0.9999 | AT79: 0.9999 | AU79: n/a | AV79: 0.9999 | AW79: n/a | AX79: 0.9999 | AY79: n/a | AZ79: 1 | BA79: n/a | BB79: n/a | BC79: n/a | BD79: n/a | BE79: 0.9999 | BF79: n/a | BG79: 0.6666 | BH79: 0.9999 | BI79: 0.9999 | BJ79: n/a | BK79: n/a | BL79: 0.5 | BM79: n/a | BN79: 0.9999 | BO79: 1 | BP79: 1 | BQ79: n/a | BR79: n/a | BS79: n/a | BT79: n/a | BU79: n/a | BW79: 0.95445455 | BX79: 0.93326 | BY79: 0.74995 | BZ79: 0.87922152
Z80: 0.5 | AA80: n/a | AB80: n/a | AC80: 0.3333 | AE80: El vendedor/a mostró los accesorios con los que viene el producto | AF80: n/a | AG80: 1 | AH80: n/a | AI80: 1 | AJ80: n/a | AK80: n/a | AL80: 1 | AM80: 1 | AN80: n/a | AO80: 1 | AP80: n/a | AQ80: n/a | AR80: 1 | AS80: 1 | AT80: 1 | AU80: n/a | AV80: 1 | AW80: n/a | AX80: 1 | AY80: n/a | AZ80: n/a | BA80: n/a | BB80: n/a | BC80: n/a | BD80: n/a | BE80: 1 | BF80: n/a | BG80: 0 | BH80: 1 | BI80: 1 | BJ80: n/a | BK80: n/a | BL80: n/a | BM80: n/a | BN80: 1 | BO80: n/a | BP80: n/a | BQ80: n/a | BR80: n/a | BS80: n/a | BT80: n/a | BU80: n/a | BW80: 1 | BX80: 0.75 | BY80: 1 | BZ80: 0.91666667
Z81: n/a | AA81: 0.5 | AB81: n/a | AC81: 0.3333 | AE81: El vendedor/a probó el producto | AF81: n/a | AG81: 1 | AH81: n/a | AI81: 1 | AJ81: n/a | AK81: n/a | AL81: 1 | AM81: 1 | AN81: n/a | AO81: 1 | AP81: n/a | AQ81: 1 | AR81: 1 | AS81: 1 | AT81: 1 | AU81: n/a | AV81: 1 | AW81: n/a | AX81: 1 | AY81: n/a | AZ81: 1 | BA81: n/a | BB81: n/a | BC81: n/a | BD81: n/a | BE81: 1 | BF81: n/a | BG81: 1 | BH81: 1 | BI81: 1 | BJ81: n/a | BK81: n/a | BL81: 1 | BM81: n/a | BN81: 1 | BO81: 1 | BP81: 1 | BQ81: n/a | BR81: n/a | BS81: n/a | BT81: n/a | BU81: n/a | BW81: 1 | BX81: 1 | BY81: 1 | BZ81: 1
Z82: 0.5 | AA82: 0.5 | AB82: 1 | AC82: 0.3333 | AE82: El vendedor/a se despidió amablemente y lo invito a visitar nuevamente la tienda | AF82: n/a | AG82: 1 | AH82: n/a | AI82: 1 | AJ82: n/a | AK82: n/a | AL82: 1 | AM82: 1 | AN82: n/a | AO82: 1 | AP82: n/a | AQ82: 0 | AR82: 1 | AS82: 1 | AT82: 1 | AU82: n/a | AV82: 1 | AW82: n/a | AX82: 1 | AY82: n/a | AZ82: 1 | BA82: n/a | BB82: n/a | BC82: n/a | BD82: n/a | BE82: 1 | BF82: n/a | BG82: 1 | BH82: 1 | BI82: 1 | BJ82: n/a | BK82: n/a | BL82: 0 | BM82: n/a | BN82: 1 | BO82: 1 | BP82: 1 | BQ82: n/a | BR82: n/a | BS82: n/a | BT82: n/a | BU82: n/a | BW82: 0.90909091 | BX82: 1 | BY82: 0.5 | BZ82: 0.8030303
AC84: 0.15 | AE84: AMBIENTE DE LA TIENDA | AF84: 1 | AG84: 1 | AH84: n/a | AI84: 1 | AJ84: n/a | AK84: n/a | AL84: 1 | AM84: 1 | AN84: n/a | AO84: 1 | AP84: n/a | AQ84: 1 | AR84: 1 | AS84: 0.91666667 | AT84: 1 | AU84: 1 | AV84: 1 | AW84: n/a | AX84: 1 | AY84: 0.75 | AZ84: 0.625 | BA84: 0.75 | BB84: n/a | BC84: n/a | BD84: n/a | BE84: 0.83333333 | BF84: n/a | BG84: 0.83333333 | BH84: 0.79166667 | BI84: 0.75 | BJ84: n/a | BK84: n/a | BL84: 1 | BM84: 1 | BN84: 1 | BO84: 1 | BP84: 1 | BQ84: n/a | BR84: n/a | BS84: 0 | BT84: 0 | BU84: n/a | BW84: 0.99358974 | BX84: 0.76190476 | BY84: 1 | BZ84: 0.91849817
AC85: 0.5 | AE85: LIMPIEZA Y ORDEN | AF85: 1 | AG85: 1 | AH85: n/a | AI85: 1 | AJ85: n/a | AK85: n/a | AL85: 1 | AM85: 1 | AN85: n/a | AO85: 1 | AP85: n/a | AQ85: 1 | AR85: 1 | AS85: 0.83333333 | AT85: 1 | AU85: 1 | AV85: 1 | AW85: n/a | AX85: 1 | AY85: 0.5 | AZ85: 0.5 | BA85: 0.5 | BB85: n/a | BC85: n/a | BD85: n/a | BE85: 0.66666667 | BF85: n/a | BG85: 0.66666667 | BH85: 0.83333333 | BI85: 0.5 | BJ85: n/a | BK85: n/a | BL85: 1 | BM85: 1 | BN85: 1 | BO85: 1 | BP85: 1 | BQ85: n/a | BR85: n/a | BS85: n/a | BT85: n/a | BU85: n/a | BW85: 0.98717949 | BX85: 0.5952381 | BY85: 1 | BZ85: 0.86080586
AC86: 0.3333 | AE86: El interior de la tienda se encontraba limpio y en buenas condiciones (pisos, paredes y techo) | AF86: 1 | AG86: 1 | AH86: n/a | AI86: 1 | AJ86: n/a | AK86: n/a | AL86: 1 | AM86: 1 | AN86: n/a | AO86: 1 | AP86: n/a | AQ86: 1 | AR86: 1 | AS86: 1 | AT86: 1 | AU86: 1 | AV86: 1 | AW86: n/a | AX86: 1 | AY86: 0 | AZ86: 0 | BA86: 0.5 | BB86: n/a | BC86: n/a | BD86: n/a | BE86: 0.5 | BF86: n/a | BG86: 1 | BH86: 0.5 | BI86: 0.5 | BJ86: n/a | BK86: n/a | BL86: 1 | BM86: 1 | BN86: 1 | BO86: 1 | BP86: 1 | BQ86: n/a | BR86: n/a | BS86: n/a | BT86: n/a | BU86: n/a | BW86: 1 | BX86: 0.42857143 | BY86: 1 | BZ86: 0.80952381
AC87: 0.3333 | AE87: Los pasillos se encontraban libres y permitían la libre circulación | AF87: 1 | AG87: 1 | AH87: n/a | AI87: 1 | AJ87: n/a | AK87: n/a | AL87: 1 | AM87: 1 | AN87: n/a | AO87: 1 | AP87: n/a | AQ87: 1 | AR87: 1 | AS87: 1 | AT87: 1 | AU87: 1 | AV87: 1 | AW87: n/a | AX87: 1 | AY87: 1 | AZ87: 0.5 | BA87: 0.5 | BB87: n/a | BC87: n/a | BD87: n/a | BE87: 1 | BF87: n/a | BG87: 0.5 | BH87: 1 | BI87: 0.5 | BJ87: n/a | BK87: n/a | BL87: 1 | BM87: 1 | BN87: 1 | BO87: 1 | BP87: 1 | BQ87: n/a | BR87: n/a | BS87: n/a | BT87: n/a | BU87: n/a | BW87: 1 | BX87: 0.71428571 | BY87: 1 | BZ87: 0.9047619
AC88: 0.3333 | AE88: Los productos se encontraban ordenados y limpios | AF88: 1 | AG88: 1 | AH88: n/a | AI88: 1 | AJ88: n/a | AK88: n/a | AL88: 1 | AM88: 1 | AN88: n/a | AO88: 1 | AP88: n/a | AQ88: 1 | AR88: 1 | AS88: 0.5 | AT88: 1 | AU88: 1 | AV88: 1 | AW88: n/a | AX88: 1 | AY88: 0.5 | AZ88: 1 | BA88: 0.5 | BB88: n/a | BC88: n/a | BD88: n/a | BE88: 0.5 | BF88: n/a | BG88: 0.5 | BH88: 1 | BI88: 0.5 | BJ88: n/a | BK88: n/a | BL88: 1 | BM88: 1 | BN88: 1 | BO88: 1 | BP88: 1 | BQ88: n/a | BR88: n/a | BS88: n/a | BT88: n/a | BU88: n/a | BW88: 0.96153846 | BX88: 0.64285714 | BY88: 1 | BZ88: 0.86813187
AC89: 0.5 | AE89: LETREROS Y SEÑALETICA | AF89: 1 | AG89: 1 | AH89: n/a | AI89: 1 | AJ89: n/a | AK89: n/a | AL89: 1 | AM89: 1 | AN89: n/a | AO89: 1 | AP89: n/a | AQ89: 1 | AR89: 1 | AS89: 1 | AT89: 1 | AU89: 1 | AV89: 1 | AW89: n/a | AX89: 1 | AY89: 1 | AZ89: 0.75 | BA89: 1 | BB89: n/a | BC89: n/a | BD89: n/a | BE89: 1 | BF89: n/a | BG89: 1 | BH89: 0.75 | BI89: 1 | BJ89: n/a | BK89: n/a | BL89: 1 | BM89: 1 | BN89: 1 | BO89: 1 | BP89: 1 | BQ89: n/a | BR89: n/a | BS89: n/a | BT89: n/a | BU89: n/a | BW89: 1 | BX89: 0.92857143 | BY89: 1 | BZ89: 0.97619048
AC90: 0.5 | AE90: Los productos cuentan con la cartelería o letreros que indican sus precios | AF90: 1 | AG90: 1 | AH90: n/a | AI90: 1 | AJ90: n/a | AK90: n/a | AL90: 1 | AM90: 1 | AN90: n/a | AO90: 1 | AP90: n/a | AQ90: 1 | AR90: 1 | AS90: 1 | AT90: 1 | AU90: 1 | AV90: 1 | AW90: n/a | AX90: 1 | AY90: 1 | AZ90: 0.5 | BA90: 1 | BB90: n/a | BC90: n/a | BD90: n/a | BE90: 1 | BF90: n/a | BG90: 1 | BH90: 0.5 | BI90: 1 | BJ90: n/a | BK90: n/a | BL90: 1 | BM90: 1 | BN90: 1 | BO90: 1 | BP90: 1 | BQ90: n/a | BR90: n/a | BS90: n/a | BT90: n/a | BU90: n/a | BW90: 1 | BX90: 0.85714286 | BY90: 1 | BZ90: 0.95238095
AC91: 0.5 | AE91: Los letreros de promociones y la señalética eran visibles | AF91: 1 | AG91: 1 | AH91: n/a | AI91: 1 | AJ91: n/a | AK91: n/a | AL91: 1 | AM91: 1 | AN91: n/a | AO91: 1 | AP91: n/a | AQ91: 1 | AR91: 1 | AS91: 1 | AT91: 1 | AU91: 1 | AV91: 1 | AW91: n/a | AX91: 1 | AY91: 1 | AZ91: 1 | BA91: 1 | BB91: n/a | BC91: n/a | BD91: n/a | BE91: 1 | BF91: n/a | BG91: 1 | BH91: 1 | BI91: 1 | BJ91: n/a | BK91: n/a | BL91: 1 | BM91: 1 | BN91: 1 | BO91: 1 | BP91: 1 | BQ91: n/a | BR91: n/a | BS91: n/a | BT91: n/a | BU91: n/a | BW91: 1 | BX91: 1 | BY91: 1 | BZ91: 1
AC93: 0.5 | AD93: 0 | AE93: LIMPIEZA Y ORDEN | AF93: 1 | AG93: 1 | AH93: n/a | AI93: 1 | AJ93: n/a | AK93: n/a | AL93: 1 | AM93: 1 | AN93: n/a | AO93: 1 | AP93: n/a | AQ93: 1 | AR93: 1 | AS93: 0.83333333 | AT93: 1 | AU93: 1 | AV93: 1 | AW93: n/a | AX93: 1 | AY93: 0.5 | AZ93: 0.5 | BA93: 0.5 | BB93: n/a | BC93: n/a | BD93: n/a | BE93: 0.66666667 | BF93: n/a | BG93: 0.66666667 | BH93: 0.83333333 | BI93: 0.5 | BJ93: n/a | BK93: n/a | BL93: 1 | BM93: 1 | BN93: 1 | BO93: 1 | BP93: 1 | BQ93: n/a | BR93: n/a | BS93: n/a | BT93: n/a | BU93: n/a
AC94: 0.5 | AD94: 0 | AE94: LETREROS Y SEÑALETICA | AF94: 1 | AG94: 1 | AH94: n/a | AI94: 1 | AJ94: n/a | AK94: n/a | AL94: 1 | AM94: 1 | AN94: n/a | AO94: 1 | AP94: n/a | AQ94: 1 | AR94: 1 | AS94: 1 | AT94: 1 | AU94: 1 | AV94: 1 | AW94: n/a | AX94: 1 | AY94: 1 | AZ94: 0.75 | BA94: 1 | BB94: n/a | BC94: n/a | BD94: n/a | BE94: 1 | BF94: n/a | BG94: 1 | BH94: 0.75 | BI94: 1 | BJ94: n/a | BK94: n/a | BL94: 1 | BM94: 1 | BN94: 1 | BO94: 1 | BP94: 1 | BQ94: n/a | BR94: n/a | BS94: n/a | BT94: n/a | BU94: n/a
AC96: 0 | AE96: DELIVERY | AF96: 1 | AG96: n/a | AH96: n/a | AI96: n/a | AJ96: n/a | AK96: n/a | AL96: n/a | AM96: n/a | AN96: n/a | AO96: n/a | AP96: n/a | AQ96: n/a | AR96: n/a | AS96: n/a | AT96: n/a | AU96: 1 | AV96: n/a | AW96: n/a | AX96: n/a | AY96: 1 | AZ96: n/a | BA96: 1 | BB96: n/a | BC96: n/a | BD96: n/a | BE96: n/a | BF96: n/a | BG96: n/a | BH96: n/a | BI96: n/a | BJ96: n/a | BK96: n/a | BL96: n/a | BM96: 1 | BN96: n/a | BO96: n/a | BP96: n/a | BQ96: #REF! | BR96: #REF! | BS96: #REF! | BT96: #REF! | BU96: #REF! | BW96: 1 | BX96: 1 | BY96: 1 | BZ96: 1
AC97: 1 | AE97: ENTREGA A DOMICILIO | AF97: 1 | AG97: n/a | AH97: n/a | AI97: n/a | AJ97: n/a | AK97: n/a | AL97: n/a | AM97: n/a | AN97: n/a | AO97: n/a | AP97: n/a | AQ97: n/a | AR97: n/a | AS97: n/a | AT97: n/a | AU97: 1 | AV97: n/a | AW97: n/a | AX97: n/a | AY97: 1 | AZ97: n/a | BA97: 1 | BB97: n/a | BC97: n/a | BD97: n/a | BE97: n/a | BF97: n/a | BG97: n/a | BH97: n/a | BI97: n/a | BJ97: n/a | BK97: n/a | BL97: n/a | BM97: 1 | BN97: n/a | BO97: n/a | BP97: n/a | BQ97: n/a | BR97: n/a | BS97: n/a | BT97: n/a | BU97: n/a | BW97: 1 | BX97: 1 | BY97: 1 | BZ97: 1
AA98: 0.5 | AB98: 0.33333333 | AC98: 0.25 | AE98: El chofer se comunicó con el cliente por lo menos 30 minutos antes para confirmar la entrega | AF98: 1 | AG98: n/a | AH98: n/a | AI98: n/a | AJ98: n/a | AK98: n/a | AL98: n/a | AM98: n/a | AN98: n/a | AO98: n/a | AP98: n/a | AQ98: n/a | AR98: n/a | AS98: n/a | AT98: n/a | AU98: 1 | AV98: n/a | AW98: n/a | AX98: n/a | AY98: 1 | AZ98: n/a | BA98: 1 | BB98: n/a | BC98: n/a | BD98: n/a | BE98: n/a | BF98: n/a | BG98: n/a | BH98: n/a | BI98: n/a | BJ98: n/a | BK98: n/a | BL98: n/a | BM98: 1 | BN98: n/a | BO98: n/a | BP98: n/a | BQ98: n/a | BR98: n/a | BS98: n/a | BT98: n/a | BU98: n/a | BW98: 1 | BX98: 1 | BY98: 1 | BZ98: 1
AA99: 0.5 | AB99: 0.33333333 | AC99: 0.25 | AE99: El producto llegó a su casa en el rango de tiempo indicado (No más de 24 Hr) | AF99: 1 | AG99: n/a | AH99: n/a | AI99: n/a | AJ99: n/a | AK99: n/a | AL99: n/a | AM99: n/a | AN99: n/a | AO99: n/a | AP99: n/a | AQ99: n/a | AR99: n/a | AS99: n/a | AT99: n/a | AU99: 1 | AV99: n/a | AW99: n/a | AX99: n/a | AY99: 1 | AZ99: n/a | BA99: 1 | BB99: n/a | BC99: n/a | BD99: n/a | BE99: n/a | BF99: n/a | BG99: n/a | BH99: n/a | BI99: n/a | BJ99: n/a | BK99: n/a | BL99: n/a | BM99: 1 | BN99: n/a | BO99: n/a | BP99: n/a | BQ99: n/a | BR99: n/a | BS99: n/a | BT99: n/a | BU99: n/a | BW99: 1 | BX99: 1 | BY99: 1 | BZ99: 1
AA100: n/a | AB100: 0.33333333 | AC100: 0.25 | AE100: El chofer dejó el producto dentro del inmueble y en el lugar solicitado por el cliente | AF100: 1 | AG100: n/a | AH100: n/a | AI100: n/a | AJ100: n/a | AK100: n/a | AL100: n/a | AM100: n/a | AN100: n/a | AO100: n/a | AP100: n/a | AQ100: n/a | AR100: n/a | AS100: n/a | AT100: n/a | AU100: 1 | AV100: n/a | AW100: n/a | AX100: n/a | AY100: 1 | AZ100: n/a | BA100: 1 | BB100: n/a | BC100: n/a | BD100: n/a | BE100: n/a | BF100: n/a | BG100: n/a | BH100: n/a | BI100: n/a | BJ100: n/a | BK100: n/a | BL100: n/a | BM100: 1 | BN100: n/a | BO100: n/a | BP100: n/a | BQ100: n/a | BR100: n/a | BS100: n/a | BT100: n/a | BU100: n/a | BW100: 1 | BX100: 1 | BY100: 1 | BZ100: 1
AA101: n/a | AB101: n/a | AC101: 0.25 | AE101: El producto llegó en perfecto estatodo sin daños estéticos | AF101: 1 | AG101: n/a | AH101: n/a | AI101: n/a | AJ101: n/a | AK101: n/a | AL101: n/a | AM101: n/a | AN101: n/a | AO101: n/a | AP101: n/a | AQ101: n/a | AR101: n/a | AS101: n/a | AT101: n/a | AU101: 1 | AV101: n/a | AW101: n/a | AX101: n/a | AY101: 1 | AZ101: n/a | BA101: 1 | BB101: n/a | BC101: n/a | BD101: n/a | BE101: n/a | BF101: n/a | BG101: n/a | BH101: n/a | BI101: n/a | BJ101: n/a | BK101: n/a | BL101: n/a | BM101: 1 | BN101: n/a | BO101: n/a | BP101: n/a | BQ101: n/a | BR101: n/a | BS101: n/a | BT101: n/a | BU101: n/a | BW101: 1 | BX101: 1 | BY101: 1 | BZ101: 1
AC102: 0.1 | AE102: DEVOLUCIÓN | AF102: 1 | AG102: 1 | AH102: n/a | AI102: 1 | AJ102: n/a | AK102: n/a | AL102: 1 | AM102: 1 | AN102: n/a | AO102: 1 | AP102: n/a | AQ102: 1 | AR102: 1 | AS102: 1 | AT102: 1 | AU102: 1 | AV102: 1 | AW102: n/a | AX102: 1 | AY102: 0.83333333 | AZ102: 1 | BA102: 1 | BB102: n/a | BC102: n/a | BD102: n/a | BE102: 1 | BF102: n/a | BG102: 1 | BH102: 1 | BI102: 1 | BJ102: n/a | BK102: n/a | BL102: 1 | BM102: 1 | BN102: 1 | BO102: 1 | BP102: 1 | BQ102: n/a | BR102: n/a | BS102: n/a | BT102: n/a | BU102: n/a | BW102: 1 | BX102: 0.97619048 | BY102: 1 | BZ102: 0.99206349
AC103: 1 | AE103: DEVOLUCIÓN EN TIENDA | AF103: 1 | AG103: 1 | AH103: n/a | AI103: 1 | AJ103: n/a | AK103: n/a | AL103: 1 | AM103: 1 | AN103: n/a | AO103: 1 | AP103: n/a | AQ103: 1 | AR103: 1 | AS103: 1 | AT103: 1 | AU103: 1 | AV103: 1 | AW103: n/a | AX103: 1 | AY103: 0.83333333 | AZ103: 1 | BA103: 1 | BB103: n/a | BC103: n/a | BD103: n/a | BE103: 1 | BF103: n/a | BG103: 1 | BH103: 1 | BI103: 1 | BJ103: n/a | BK103: n/a | BL103: 1 | BM103: 1 | BN103: 1 | BO103: 1 | BP103: 1 | BQ103: n/a | BR103: n/a | BS103: n/a | BT103: n/a | BU103: n/a | BW103: 1 | BX103: 0.97619048 | BY103: 1 | BZ103: 0.99206349
AC104: 0.1667 | AE104: El encargado/a lo saludó amablemente | AF104: 1 | AG104: 1 | AH104: n/a | AI104: 1 | AJ104: n/a | AK104: n/a | AL104: 1 | AM104: 1 | AN104: n/a | AO104: 1 | AP104: n/a | AQ104: 1 | AR104: 1 | AS104: 1 | AT104: 1 | AU104: 1 | AV104: 1 | AW104: n/a | AX104: 1 | AY104: 1 | AZ104: 1 | BA104: 1 | BB104: n/a | BC104: n/a | BD104: n/a | BE104: 1 | BF104: n/a | BG104: 1 | BH104: 1 | BI104: 1 | BJ104: n/a | BK104: n/a | BL104: 1 | BM104: 1 | BN104: 1 | BO104: 1 | BP104: 1 | BQ104: n/a | BR104: n/a | BS104: n/a | BT104: n/a | BU104: n/a | BW104: 1 | BX104: 1 | BY104: 1 | BZ104: 1
AC105: 0.1667 | AE105: El encargado/a escuchó atentamente, con paciencia y con interés | AF105: 1 | AG105: 1 | AH105: n/a | AI105: 1 | AJ105: n/a | AK105: n/a | AL105: 1 | AM105: 1 | AN105: n/a | AO105: 1 | AP105: n/a | AQ105: 1 | AR105: 1 | AS105: 1 | AT105: 1 | AU105: 1 | AV105: 1 | AW105: n/a | AX105: 1 | AY105: 1 | AZ105: 1 | BA105: 1 | BB105: n/a | BC105: n/a | BD105: n/a | BE105: 1 | BF105: n/a | BG105: 1 | BH105: 1 | BI105: 1 | BJ105: n/a | BK105: n/a | BL105: 1 | BM105: 1 | BN105: 1 | BO105: 1 | BP105: 1 | BQ105: n/a | BR105: n/a | BS105: n/a | BT105: n/a | BU105: n/a | BW105: 1 | BX105: 1 | BY105: 1 | BZ105: 1
AC106: 0.1667 | AE106: El encargado/a demostró una buena actitud ante su solicitud | AF106: 1 | AG106: 1 | AH106: n/a | AI106: 1 | AJ106: n/a | AK106: n/a | AL106: 1 | AM106: 1 | AN106: n/a | AO106: 1 | AP106: n/a | AQ106: 1 | AR106: 1 | AS106: 1 | AT106: 1 | AU106: 1 | AV106: 1 | AW106: n/a | AX106: 1 | AY106: 1 | AZ106: 1 | BA106: 1 | BB106: n/a | BC106: n/a | BD106: n/a | BE106: 1 | BF106: n/a | BG106: 1 | BH106: 1 | BI106: 1 | BJ106: n/a | BK106: n/a | BL106: 1 | BM106: 1 | BN106: 1 | BO106: 1 | BP106: 1 | BQ106: n/a | BR106: n/a | BS106: n/a | BT106: n/a | BU106: n/a | BW106: 1 | BX106: 1 | BY106: 1 | BZ106: 1
AC107: 0.1667 | AE107: El encargado/a verificó el estado del producto, y determinó si cumple con la política de cambios y devoluciones | AF107: 1 | AG107: 1 | AH107: n/a | AI107: 1 | AJ107: n/a | AK107: n/a | AL107: 1 | AM107: 1 | AN107: n/a | AO107: 1 | AP107: n/a | AQ107: 1 | AR107: 1 | AS107: 1 | AT107: 1 | AU107: 1 | AV107: 1 | AW107: n/a | AX107: 1 | AY107: 0 | AZ107: 1 | BA107: 1 | BB107: n/a | BC107: n/a | BD107: n/a | BE107: 1 | BF107: n/a | BG107: 1 | BH107: 1 | BI107: 1 | BJ107: n/a | BK107: n/a | BL107: 1 | BM107: 1 | BN107: 1 | BO107: 1 | BP107: 1 | BQ107: n/a | BR107: n/a | BS107: n/a | BT107: n/a | BU107: n/a | BW107: 1 | BX107: 0.85714286 | BY107: 1 | BZ107: 0.95238095
AC108: 0.1667 | AE108: El encargado/a hizo efectiva la devolución | AF108: 1 | AG108: 1 | AH108: n/a | AI108: 1 | AJ108: n/a | AK108: n/a | AL108: 1 | AM108: 1 | AN108: n/a | AO108: 1 | AP108: n/a | AQ108: 1 | AR108: 1 | AS108: 1 | AT108: 1 | AU108: 1 | AV108: 1 | AW108: n/a | AX108: 1 | AY108: 1 | AZ108: 1 | BA108: 1 | BB108: n/a | BC108: n/a | BD108: n/a | BE108: 1 | BF108: n/a | BG108: 1 | BH108: 1 | BI108: 1 | BJ108: n/a | BK108: n/a | BL108: 1 | BM108: 1 | BN108: 1 | BO108: 1 | BP108: 1 | BQ108: n/a | BR108: n/a | BS108: n/a | BT108: n/a | BU108: n/a | BW108: 1 | BX108: 1 | BY108: 1 | BZ108: 1
AC109: 0.1667 | AE109: La atención por parte del encargado/a fue ágil y rápida. | AF109: 1 | AG109: 1 | AH109: n/a | AI109: 1 | AJ109: n/a | AK109: n/a | AL109: 1 | AM109: 1 | AN109: n/a | AO109: 1 | AP109: n/a | AQ109: 1 | AR109: 1 | AS109: 1 | AT109: 1 | AU109: 1 | AV109: 1 | AW109: n/a | AX109: 1 | AY109: 1 | AZ109: 1 | BA109: 1 | BB109: n/a | BC109: n/a | BD109: n/a | BE109: 1 | BF109: n/a | BG109: 1 | BH109: 1 | BI109: 1 | BJ109: n/a | BK109: n/a | BL109: 1 | BM109: 1 | BN109: 1 | BO109: 1 | BP109: 1 | BQ109: n/a | BR109: n/a | BS109: n/a | BT109: n/a | BU109: n/a | BW109: 1 | BX109: 1 | BY109: 1 | BZ109: 1
AE110: El encargado le brindó toda la información necesaria con respecto a la devolución (sólo en caso de demora) | AF110: n/a | AG110: n/a | AH110: n/a | AI110: n/a | AJ110: n/a | AK110: n/a | AL110: n/a | AM110: n/a | AN110: n/a | AO110: n/a | AP110: n/a | AQ110: n/a | AR110: n/a | AS110: n/a | AT110: n/a | AU110: n/a | AV110: n/a | AW110: n/a | AX110: n/a | AY110: n/a | AZ110: n/a | BA110: n/a | BB110: n/a | BC110: n/a | BD110: n/a | BE110: n/a | BF110: n/a | BG110: n/a | BH110: n/a | BI110: n/a | BJ110: n/a | BK110: n/a | BL110: n/a | BM110: n/a | BN110: n/a | BO110: n/a | BP110: n/a | BQ110: n/a | BR110: n/a | BS110: n/a | BT110: n/a | BU110: n/a | BW110: n/a | BX110: n/a | BY110: n/a | BZ110: n/a
AC112: 0 | AE112: MEDIDAS DE BIOSEGURIDAD | AF112: n/a | AG112: n/a | AH112: n/a | AI112: n/a | AJ112: n/a | AK112: n/a | AL112: n/a | AM112: n/a | AN112: n/a | AO112: n/a | AP112: n/a | AQ112: n/a | AR112: n/a | AS112: n/a | AT112: n/a | AU112: n/a | AV112: n/a | AW112: n/a | AX112: n/a | AY112: n/a | AZ112: n/a | BA112: n/a | BB112: n/a | BC112: n/a | BD112: n/a | BE112: n/a | BF112: n/a | BG112: n/a | BH112: n/a | BI112: n/a | BJ112: n/a | BK112: n/a | BL112: n/a | BM112: n/a | BN112: n/a | BO112: n/a | BP112: n/a | BW112: n/a | BX112: n/a | BY112: n/a | BZ112: n/a
...

Sheet Santa Cruz
B3: Reporte Diciembre 2025 - Visitas encubiertas DISMAC
B4: Santa Cruz - Comentarios Relevantes
C5: SANTA CRUZ
B7: DIMENSIONES EVALUADAS | C7: Cristobal de Mendoza #1055 | E7: Doble Vía entre 5to y 6to anillo | G7: Isabel 1 | I7: Montero | K7: Pampa de la Isla | M7: Show Room (P.I.) | O7: Villa 1ero de Mayo | Q7: 4to anillo e Isuto | S7: Plan 3000 | U7: Omar Chávez | W7: Av. Cristo Redentor | Y7: Av. Santos Dumont | AA7: Isabel 2
C8: Consulta | D8: Compra | E8: Consulta | F8: Compra | G8: Consulta | H8: Compra | I8: Consulta | J8: Compra | K8: Consulta | L8: Compra | M8: Consulta | N8: Compra | O8: Consulta | P8: Compra | Q8: Consulta | R8: Compra | S8: Consulta | T8: Compra | U8: Consulta | V8: Compra | W8: Consulta | X8: Compra | Y8: Consulta | Z8: Compra | AA8: Consulta | AB8: Compra
B9: FECHA DE LA VISITA | C9: 09-FEB-2026 | D9: 13-FEB-2026 | E9: 09-FEB-2026 | F9: 13-FEB-2026 | G9: 09-FEB-2026 | H9: 14-FEB-2026 | I9: 13-FEB-2026 | J9: 10-FEB-2026 | K9: 10-FEB-2026 | L9: 14-FEB-2026 | M9: 13-FEB-2026 | N9: 11-FEB-2026 | O9: 13-FEB-2026 | P9: 10-FEB-2026 | Q9: 13-FEB-2026 | R9: 11-FEB-2026 | S9: 13-FEB-2026 | T9: 10-FEB-2026 | U9: 10-FEB-2026 | V9: 11-FEB-2026 | W9: 11-FEB-2026 | X9: 13-FEB-2026 | Y9: 14-FEB-2026 | Z9: 12-FEB-2026 | AA9: 14-FEB-2026 | AB9: 10-FEB-2026
B10: TURNO | C10: Tarde | D10: Tarde | E10: Tarde | F10: Tarde | G10: Tarde | H10: Tarde | I10: Tarde | J10: Tarde | K10: Tarde | L10: Tarde | M10: Tarde | N10: Tarde | O10: Tarde | P10: Tarde | Q10: Tarde | R10: Mañana | S10: Tarde | T10: Medio día | U10: Tarde | V10: Tarde | W10: Tarde | X10: Tarde | Y10: Tarde | Z10: Tarde | AA10: Tarde | AB10: Tarde
B11: PRODUCTO | C11: Lavadora | D11: Cocina de 4 hornallas | E11: Aire acondicionado | F11: Plancha en seco | G11: Heladera | H11: Horno eléctrico Briara 550w | I11: Lavadora | J11: Secadora de cabello | K11: Lavadora y frezer | L11: Plancha de cabello Mallory Red Diamond | M11: Lavadoras | N11: Plancha en seco | O11: Lavadora | P11: Plancha a vapor Arno | Q11: Frezeer | R11: Plancha de cabello | S11: Aire acondicionado y hidrolavadora | T11: Plancha de cabello | U11: Lavadora y aire acondicionado | V11: Licuadora Arno 550W | W11: Lavadora | X11: Cocina Clásica Kerning | Y11: Aire acondicionado | Z11: Tostadora Philips | AA11: Televisor | AB11: Plancha a vapor arno essential 1100W de potencia
B13: ATENCIÓN DEL VENDEDOR
B14: PRIMER CONTACTO
B15: El vendedor/a se percató de la presencia del cliente y se aproximó para atenderlo | M15: No aplica, los vendedores estaba ocupados, había uno atendiendo a una familia y habían otros metiendo y sacando cosas del depósito | O15: No aplica, el vendedor se encontraba con otro cliente | Q15: No aplica, los vendedores se encontraban con otros clientes por lo cual esperé 5 minutos | T15: No aplica, esperé 8 minutos para ser atendida, ya que el vendedor se encontraba con otra cliente | U15: No aplica, esperé 6 minutos y había clientes en ese horario, todos estaban ocupados | X15: No aplica, los vendedores se encontraban ocupados, tuve que esperar que se desocupen para que me atiendan | Z15: No aplica, el vendedor me saludó, pero estaba ocupado haciendo una venta, esperé 5 minutos y fui y busqué un vendedor que pueda atenderme | AA15: No aplica, esperé 9 minutos, todos los vendedores se encontraban ocupado con otros clientes
B16: El vendedor/a lo saludó amablemente o pregunto en modo de bienvenida | G16: No aplica, yo saludé primero a la cual me devuelve el saludo | O16: Yo me acerqué y lo saludé no devolvió el saludo | T16: No aplica, yo me aproximé al vendedor y lo saludé primero, la cual me devuelve el saludo | U16: Yo me acerqué, saludé y pregunté por el producto, pero el no devolvió el saludo | Z16: No aplica, tuve que buscar un vendedor para que me atienda porque estaban ocupados trabajando, saludé primero y me devolvieron el saludo
B17: El vendedor/a pregunta al cliente lo que busca o sus preferencias. | E17: No aplica, yo fui directamente a preguntarle sobre el producto que estaba buscando | H17: No aplica, el vendedor estaba pendiente de mi porque me saludó y estaba cerca de mi esperando que le pregunté y ahí le consulte sobre el producto | J17: No aplica, yo le pregunté directamente sobre el producto ya que el vendedor solo me entregó un folleto de promociones y se pretendía ir | U17: No aplica, yo pregunté directamente sobre un producto | X17: No aplica, yo fui y lo busqué al vendedor porque estaban ocupados y le pregunté directamente sobre los productos que buscaba | Z17: No aplica, tuve que preguntarle yo donde estaba las tostadoras y el me indicó donde estaban, pero llegó se fue a la tv del ecomerce a ver otros productos y luego de un minuto el mismo me habló sobre el producto
B18: El vendedor/a dirige al cliente a donde debe, según su necesidad | C18: No aplica, ya me encontraba en la zona del producto que estaba buscando | H18: No aplica, ya estábamos en la zona de los productos que buscaba | J18: No aplica, ya me encontraba en la zona del producto | N18: No aplica, ya me encontraba en la zona | Q18: No aplica, ya me encontraba en la zona del producto | Z18: No aplica, ya estaba en la sección del producto | AA18: No aplica, ya me encontraba en la zona del producto
B19: GESTION DE VENTA
B20: El vendedor/a mostró el producto solicitado de forma rápida y sin hacer esperar mucho tiempo al cliente.
B21: El vendedor/a en caso de no disponer del producto en tienda, utilizó la página ecommerce de DISMAC para ofrecer otras opciones al cliente. | C21: No aplica, el producto estaba disponible en la tienda | D21: No aplica, el producto estaba disponible en tienda | E21: No aplica, el producto comsultado estaba disponible en la tienda | G21: No aplica, el producto estaba disponible en la tienda | H21: No aplica, los productos estaban disponibles en tienda | I21: No aplica, el producto estaba disponible en tienda | J21: No aplica, el producto estaba en la tienda, pero menciona que hay mas modelos en la página, sin embargo no me mostró la página | K21: No aplica, el producto se encontraba en la tienda | L21: No aplica, el producto estaba disponible en tienda | N21: No aplica, los productos se encontraban disponible en la tienda | P21: No aplica, no utilizó eso porque los productos estaban en tienda | R21: No aplica, el producto estaba disponible en la tienda | T21: No aplica, el producto se encontraba disponible | U21: No aplica, el producto estaba disponible en la tienda | W21: No aplica, el producto se encontraba en la tienda | X21: No aplica, los productos estaban en tienda disponible | Z21: No aplica, el producto estaba disponible en tienda | AA21: No aplica, el producto se encontraba en la tienda | AB21: No aplica, el producto estaba disponible en la tienda
B22: El vendedor/a demostró tener conocimiento del producto y proporcionó toda la información (garantía) y especificaciones del mismo.
B23: El vendedor/a mostró diferentes opciones de productos e hizo recomendaciones de acuerdo a sus necesidades. | J23: No me hizo otras recomendaciones al parecer su conocimiento era muy básico | K23: No mostró las diferentes opciones que tenían, tampoco hizo recomendaciones a lo que yo necesitaba y ni me preguntó, tenía que preguntarle para que el me hablara un poco del producto que estaba consultando
B24: El vendedor/a le comunicó los precios más bajos garantizados de Dismac. | E24: No me habló sobre que Dismac tenía los precios más bajos, siendo que le comenté que lo ví más barato el aire acondicionado en otro lado | G24: En ningún momento mencionó que Dismac tiene los precios más bajos del mercado | K24: No mencionó que tienen los precios más bajos, ni el descuento del 20%, con las justa me decía el precio de los productos que consulté | O24: No mencionó sobre los precios bajos garantizados | P24: No me habló de que cuentan con los precios más bajos garantizados | U24: No lo mencionó en ningún momento sobre los precios bajos garantizados
B25: El vendedor/a le comunicó sobre las promociones especiales, productos en combo, descuentos o lanzamientos. | E25: No me mencionó si había promociones especiales o productos en combos disponibles en tienda | K25: No mencionó ninguna promoción, descuentos o lanzamientos y tampoco combos | P25: No me habló de promociónes vigentes en la tienda | U25: En ningún momento mencionó alguna promoción o combos
B26: El vendedor/a explicó de qué trata la garantía extendida y sus beneficios | C26: No mencionó sobre la garantía extendida | E26: No mencionó sobre la garantía extendida | G26: No mencionó sobre la garantía extendida | K26: No me explicó sobre la garantía extendida ni sus beneficios | O26: No da ninguna información acerca de la garantía extendida | P26: No me habló de ningún tipo de garantía extendida de los productos | Q26: No mencionó ninguna de las garantías la extendida ni de la que cuenta el producto | U26: No proporcionó ninguna información sobre la garantía extendida | Z26: No me habló de las garantías extendidas que tenía la tienda
B27: El vendedor/a se esmeró en brindar argumentos para incentivar la compra del producto. | K27: El vendedor no se esmeró en dar buenos argumentos para poder incentivar la compra en todo mi recorrido lo tenía a el siguiendome, pero no me daba información a menos de que yo le preguntara algo sobre el producto | R27: Solo me dice las marcas y se aleja me dice que le consulte si tengo alguna duda | T27: El vendedor no se esmeró en darme detalles del producto que estaba buscando, tuve que preguntar para que el vendedor me diera más detalle del producto, no tenía mucho conocimiento del producto comprado | U27: Su explicación básica en cuanto a precios y tamaños, no me incentivaba a comprar solo se limitaba a responder lo que le consultaba
B28: El vendedor/a cerró la venta
B29: El vendedor/a ofreció y explicó los beneficios del servicio de entrega gratuita, tiempo de entrega, áreas de cobertura. | E29: No me habló si había entregas gratuitas o si llevaban el producto a domicilio | F29: No aplica, era compra pequeña | H29: No aplica, era compra pequeña | J29: No aplica, era compra pequeña, aunque si indicó el transporte | K29: No mencionó que tenían entrega gratuita | L29: No aplica, era compra pequeña | N29: No aplica, era compra pequeña, aunque si indicó el transporte | O29: No mencionó en ningún momento sobre la entrega gratuita | P29: No aplica, hicimos una compra pequeña de una plancha | R29: No aplica, era compra pequeña, aunque si indicó el transporte | T29: No aplica, era compra pequeña, aunque si indicó el transporte | U29: En ningún momento dijo que realizaban entrega a domicilio mayormente estaba con el celular ocupado | V29: No aplica, era compra pequeña | Z29: No aplica, era compra pequeña | AB29: No aplica, es un producto pequeño
B30: El vendedor/a ofreció y explicó los beneficios del servicio de instalación garantizada. | E30: No aplica, yo mencioné sobre la instalación ya el vendedor recién me explicó que tenía un costo aparte | F30: No aplica, se compró un producto pequeño | G30: No aplica, el producto no necesita instalación | H30: No aplica, estaba realizando la compra de un producto pequeño | J30: No aplica, era compra pequeña | K30: No mencionó que contaban con instalaciones garantizadas | L30: No aplica, se compró un producto pequeño | N30: No aplica, era compra pequeña | O30: No da esa información en ningún momento sobre la instalación garantizada | P30: No aplica, se compró un producto pequeño | Q30: el producto no requiere instalacion | R30: No aplica, era compra pequeña | T30: No aplica, era compra pequeña | U30: No me mencionó sobre este beneficio de la instalación | V30: No aplica, era compra pequeña | Z30: No aplica, era compra pequeña | AA30: No aplica, el producto no requiere instalación | AB30: No aplica, era compra pequeña
B31: El vendedor/a explicó los beneficios de la política de cambios y devoluciones. | C31: No explicó las políticas de cambios y devoluciones | E31: No me habló sobre devoluciones ni los cambios de los productos de Dismac | G31: En ningún momento mencionó la política de cambios y devoluciones | K31: No mencionó las políticas de cambios y devoluciones | O31: No da esa información de las políticas de cambio ni devoluciones | P31: No me habló de las políticas de devolución vigente en la tienda | Q31: No mencionó los beneficios de las politicas de cambios y devoluciones | U31: No mencionó nada sobre las políticas de cambio ni devoluciones
B32: El vendedor/a preguntó, si necesitaba algo más, o tuvo la capacidad/ habilidad de ofrecer productos ADICIONALES diferentes al que solicitó | C32: No aplica, solo consulté por un solo tipo de producto | E32: No indagó para preguntarme si buscaba algo más, porque después de que me explicó sobre los aires acondicionados me quedé viendo los aires para ver si el me decía algo, pero el agarró su celular y se puso a ver videos | G32: No preguntó en ningún momento si necesitaba algo más | H32: No me habló sobre otros productos adicionales que podía llevar en la tienda solo se dedicó a responder mis preguntas | J32: No preguntó si necesitaba algo más, ni ofreció | K32: No me ofreció otros productos diferente al que estaba buscando | O32: No aplica, solo consulté un producto | P32: solo me respondió las preguntas que yo le hacia, no me ofreció otros productos diferentes al que le consulté | U32: Solo mostró específicamente los productos por los cuales yo pregunté, no ofreció otras opciones | Z32: Solo se dedicaba a responder mis preguntas que le hacía, no me ofreció nada adiccional | AA32: No preguntaba si necesitaba algo mas ni ofreció otros productos
B33: El vendedor/a consultó el método de pago y ofreció MINICUOTAS | E33: No me mencionó de las mini cuotas de Dismac | G33: No explica ni menciona las mini cuotas | K33: No me consultó ni mencionó las mini cuotas | O33: No dio esa información de las mini cuotas | P33: No me ofrecieron mini cuotas ni créditos para comprar productos | U33: No preguntó ni mencionó las mini cuotas
B34: El vendedor/a demostró actitud de servicio, amabilidad y cortesía en el trato | K34: El vendedor se encontra serio y solo respondia los que yo le consultaba
B35: En caso de interrupción durante la visita, el vendedor le pidió disculpas por la interrupción. | D35: No aplica, no hubo interrupción | E35: No aplica, no hubo interrupción | F35: No aplica, no hubo interrupción | G35: No aplica, no hubo interrupción | H35: No aplica, no hubo interrupción | I35: No aplica, no hubo interrupción | J35: Si habían otros clientes que se acercaba y le consultaban por algunos productos, pero el no pedía disculpa por la interrupción | K35: No aplica, no hubo interrupción | M35: No aplica, no hubo interrupción | O35: No aplica, no hubo interrupción | P35: Hubo un vendedor que me atendío inicialmente, pero luego se fue sin decirme nada luego le volví a preguntar por lo que buscaba y solo me indicó dónde estaban los productos y se fue a hacer otras cosas al área de caja y luego no lo volví a ver más, tuve que efectuar mi compra con otra vendedora | Q35: No aplica, no hubo interrupción | R35: No aplica, no hubo interrupción | W35: No aplica, no hubo interrupción | X35: No aplica, no hubo interrupción | Z35: Hubo interrupciónes por la llamada de su celular, pero no me pidió disculpas solo se ausentó de mi lado y volvía solo y ya luego se volvió a ir y yo tuve que ir a buscarlo
B36: INFORMACIÓN SOBRE LA INSTALACIÓN
B37: El vendedor/a coordinó y programó la entrega a domicilio del producto
B38: El vendedor/a coordinó y programó la instalación del producto
B39: El vendedor/a informó y explicó los requisitos previos de instalación del producto
B40: DESPEDIDA
B41: El vendedor/a le solicitó sus datos personales y en caso de no estar registrado en su sistema, lo registró | C41: No solicitó mis datos ya que no realicé ninguna compra | E41: No me solicitó datos personales para ningún registro | G41: En ningún momento pide los datos personales ni nada | K41: No solicitó mis datos personales | M41: No me pidió datos personales porque estaba haciendo una consulta, pero si me habló de que podía registrarme en la página de Dismac para mini cuotas y ver más productos y pedidos desde la página | O41: No solicitó datos solo explicó lo que se le preguntó | Q41: No solicitó mis datos personales para el registro | S41: No me pidió mis datos personales, estaba realizando una consulta, pero si me dijo que podría registrarme en la tienda para solicitar créditos | U41: En ningún momento solicitó datos personales ni nada | W41: No solicitó los datos personales
B42: El vendedor/a lo dirigió a caja para efectuar el pago.
B43: El vendedor/a se despidió amablemente y lo invito a visitar nuevamente la tienda | E43: No sé despidió de mi yo le dije muchas gracias y el dijo de nada solo eso y no me invitó a volver a la tienda ni se despidió | G43: No se despidió y tampoco me invitó a volver a la tienda | P43: No se despidió de mi, ni me invitó a visitar la tienda otra vez, solo me entregó el producto y no hizo nada más | U43: Yo le dije gracias y el me dijo de nada solo eso
B44: PRESENTACIÓN PERSONAL DEL VENDEDOR/A
B45: El vendedor/a se encontraba con el uniforme de la empresa.
B46: El vendedor/a tenía buena presencia (El cabello no está en su rostro, está limpio y prolijo)
B47: ATENCIÓN EN CAJA
B48: ATENCIÓN EN CAJA
B49: El cajero/a saludó amablemente. "Buenos días" "Buen día, en qué puedo ayudarle" "Cómo está" | R49: La cajera no saludó y directo cobró el producto
B50: El cajero/a respetó el orden de llegada.
B51: El cajero/a le comunicó sobre el monto a pagar y realizó el proceso de facturación (Pide NIT y explica la implementación de la facturación electrónica, es decir pide los datos al cliente, explica que la factura le llegará por correo o a su teléfono (opcional) y efectivamente la factura le llegó por uno de estos medios).
B52: El cajero/a entregó la garantía del producto o indicó que esta venía dentro de la caja del producto. (Aplica solo en caso de refrigeradores, cocinas, freezers, lavadoras, microondas y Aires Acondicionados)
B53: El cajero/a lo dirigió o le indicó quien es el encargado de hacer la entrega
B54: El cajero/a lo atendió con rapidez en el cobro, facturación.
B55: El cajero agradecio la compra, se despidió amablemente "Hasta luego" "Que tenga un buen día" "Que le vaya bien" y lo invitó a visitar la tienda nuevamente | R55: Directo me dio la factura y me indicó dónde me entregarán el producto, no se despidió | X55: No sé despidió de mi ni me invitó a qué vuelva nuevamente, solo me dió mi factura y nada más
B56: INFORMACIÓN SOBRE LA ENTREGA E INSTALACIÓN DE PRODUCTOS
B57: El cajero/a validó la fecha de entrega a domicilio del producto | X57: No me dijo cuando me iba a llegar el producto, solo verificó mis datos se cobró y me dió mi factura, no hubo una interacción con el cajero
B58: El cajero/a validó la fecha de instalación del producto | X58: No aplica, solicité la compra sin instalación
B59: El cajero/a validó que el vendedor explicó los requisitos previos de instalacion del producto, que el cliente entiende estos requisitos, y el cajero entregó los requisitos impresos al cliente. | X59: No válido ninguno de estos detalles, no hubo mucha interacción con el cajero salvó mis datos y el cobro del dinero
B60: El cajero informó y explicó al cliente que para cualquier cambio de horario que quiera realizar en la programación de la entrega o instalación debe llamar al número 800 10 2000 | X60: No me habló nada de esto, la interacción con la cajera fue escasa
B61: MINI CUOTAS - El cajero/a consultó el método de pago y ofreció MINICUOTAS | P61: No me habló de mini cuotas | R61: No preguntó ni tampoco ofreció mini cuotas | Z61: No me habló de mini cuotas, solo me preguntó por el pago
B62: PRESENTACIÓN PERSONAL DEL CAJERO
B63: El cajero/a se encontraba con el uniforme de la empresa.
B64: El cajero/a tenía buena presencia (El cabello no está en su rostro, está limpio y prolijo)
B65: ATENCIÓN POSTPAGO
B66: ENTREGA EN TIENDA
B67: El vendedor/a mostró los accesorios con los que viene el producto | P67: No aplica, el producto no tenía accesorios
B68: El vendedor/a probó el producto
B69: El vendedor/a se despidió amablemente y lo invito a visitar nuevamente la tienda | P69: Solo me dió el producto, no uso una despedida que me invite a visitar la tienda nuevamente
B70: AMBIENTE DE LA TIENDA
B71: LIMPIEZA Y ORDEN
B72: El interior de la tienda se encontraba limpio y en buenas condiciones (pisos, paredes y techo)
B73: Los pasillos se encontraban libres y permitían la libre circulación
B74: Los productos se encontraban ordenados y limpios | T74: Habían productos que estaban emplovados, por ejemplo las planchas para cabellos, secadoras, computadoras, celulares, sandwicheras
B75: LETREROS Y SEÑALETICA
B76: Los productos cuentan con la cartelera o letreros que indican sus precios
B77: Los letreros de promociones y la señalética eran visibles
B78: DELIVERY
B79: ENTREGA A DOMICILIO
B80: El chofer se comunicó con el cliente por lo menos 30 minutos antes para confirmar la entrega
B81: El producto llegó a su casa en el rango de tiempo indicado (No más de 24 Hr)
B82: El chofer dejó el producto dentro del inmueble y en el lugar solicitado por el cliente
B83: El producto llegó en perfecto estatodo sin daños estéticos
B84: DEVOLUCIÓN
B85: DEVOLUCIÓN EN TIENDA
B86: El encargado/a lo saludó amablemente
... B98: EXPERIENCIA EN EL SERVICIO
B99: ¿Qué rescata de la visita que realizó? es decir, ¿qué acciones positivas observó durante su visita? | C99: La atención por parte de la vendedora fue muy amable y atenta; me explicó detalladamente la variedad de productos que tienen. Los ambientes de la tienda se encontraban limpios y organizados, y los letreros eran bien visibles. | D99: La atención personalizada fue muy amable. El vendedor y el cajero tenían amplio conocimiento. La sucursal estaba limpia, la atención fue rápida y la entrega a domicilio llegó bien pese a la lluvia. La devolución fue sencilla y rápida. | E99: El vendedor se percató inmediatamente de que llegué a la tienda, me interceptó y mostró predisposición para atender mi consulta. La tienda estaba limpia, los precios estaban a la vista y eran fáciles de entender. | F99: La atención del vendedor, la cajera y la persona encargada de la devolución fue muy buena: atentos y amables. La tienda era cómoda y amplia para caminar y ver los productos. | G99: Me atendieron rápido; la tienda estaba limpia y ordenada. Me mostraron el producto que buscaba y me explicaron sus características y las diferencias entre marcas. | H99: Fue una buena visita. Me atendieron de manera cordial y estuvieron atentos a los productos que observaba. Me dieron toda la información de la tienda durante la compra y fueron muy amables. En la devolución no pusieron trabas y el proceso fue ágil. | I99: La atención fue rápida, a pesar de que no había muchos vendedores. El lugar estaba limpio y la encargada explicó con facilidad. | J99: El orden que mantienen en la tienda y el proceso de devolución fueron bastante rápidos. | K99: El lugar era cómodo, limpio y bien organizado. | L99: Muy buena atención del vendedor y del cajero; sus explicaciones fueron amplias. El lugar estaba limpio y acomodado. La atención fue rápida, a pesar de que había muchos clientes. | M99: El vendedor mostró voluntad de atenderme, incluso cuando estaba ocupado con un carro de carga. Dejó lo que hacía para brindarme atención, mostró predisposición y buen ánimo. Me habló de todas las promociones vigentes y de otros productos disponibles. Nunca se mostró cansado ni aburrido. Excelente atención. | N99: El ambiente de la tienda es amplio y cómodo para caminar y observar los productos. La atención del vendedor fue cordial y amigable; además, me explicaron todos los beneficios de comprar en Dismac. | O99: La limpieza del lugar y el ambiente festivo fueron agradables. | P99: Los vendedores respondieron mis preguntas; la tienda estaba limpia y los precios y promociones se podían apreciar claramente. | Q99: La variedad de productos estaba ordenada y limpia. Por otro lado, la atención del jefe de tienda fue muy amable al darse el tiempo de atenderme. | R99: La variedad de productos, la limpieza de la tienda y el proceso de devolución fueron rápidos y sin complicaciones. | S99: La vendedora, apenas se desocupó de atender a otro cliente, vino a atenderme. Mostró mucha amabilidad y paciencia para responder todas mis preguntas. Fue muy atenta y me habló de todas las promociones de la tienda. Se notaba su interés en concretar la venta. Excelente atención. | T99: Destaco la variedad de productos que hay en la tienda y la atención por parte del vendedor y el cajero. | U99: La limpieza de la sucursal y el orden de la tienda fueron notables. | V99: Fue una visita muy interactiva. El vendedor se esmeró en atenderme y buscar el producto de acuerdo con mi necesidad. En ningún momento mostró aburrimiento ni desinterés; estuvo pendiente de brindarme toda la información y también me ofreció productos adicionales. Excelente atención. | W99: La atención por parte del vendedor fue muy buena; me explicó todos los beneficios y recomendaciones de los productos. El ambiente era amplio y ordenado. | X99: La visita fue muy interactiva. El vendedor se expresó bien y siempre tenía algo que decir. Me explicó todas las promociones y ventajas de comprar en Dismac de manera gradual y acorde con mis preguntas. Excelente atención. | Y99: La atención fue rápida y detallada; me dio amplias opciones y me explicó todos los beneficios de comprar en Dismac. La sucursal estaba limpia y ordenada. | Z99: Buena atención. Me habló sobre las promociones y devoluciones después de que ya había comprado el producto. Mientras me mostraba el producto, me explicó las diferentes promociones. La tienda estaba ordenada y limpia. | AA99: La atención por parte del vendedor fue muy atenta y cordial; la tienda se encontraba limpia y organizada. | AB99: El personal era numeroso; había bastantes vendedores, algunos con muy buen conocimiento sobre los productos y con explicaciones sencillas y entendibles. El cajero también mostró amabilidad y explicó las políticas de manera rápida y clara.
B100: ¿En qué debería mejorar esta sucursal de Dismac para brindar una mejor experiencia de compra a sus clientes? | C100: Se debería ampliar el ambiente de la tienda, ya que tienen variedad de productos. También conviene mencionar el beneficio de la garantía extendida y las políticas de cambios y devoluciones. | D100: No habría nada que mejorar; todo muy bien en la sucursal. | E100: La interacción con los clientes debería ser más activa; los vendedores deberían mostrarse más animados para ofrecer productos y brindar información que convenza de comprar en la tienda. No solo responder preguntas, sino dar más detalles que ayuden a tomar decisiones de compra. Además, no se mencionó la garantía al inicio de la explicación; recién al final, cuando pregunté, me comentó sobre las garantías de cada producto. Tampoco debería revisar el celular durante una consulta para ver videos en redes sociales; el vendedor debe enfocarse en atender y brindar satisfacción, mencionando promociones, beneficios de las minicuotas, cambios o devoluciones, entrega gratuita, precios bajos garantizados y garantía extendida. | F100: A mi criterio, todo está bien; nada que aportar para mejorar la sucursal. | G100: Se debería mejorar la atención en cuanto al nivel de convencimiento para vender y explicar las políticas de devoluciones, precios y beneficios. La manera de ofrecer productos es muy básica y forzada. Deben mejorar en la presentación de todos los beneficios de comprar en Dismac: minicuotas, garantía extendida, precios bajos garantizados, instalaciones garantizadas y promociones. Además, el volumen de la música es muy alto y dificulta conversar con el vendedor. | H100: El vendedor debería incentivar más a los clientes a comprar, brindando argumentos convincentes y explicando todos los beneficios de la tienda. | I100: Se debería mejorar la organización de los productos grandes, ya que da la impresión de estar muy lleno y estorboso, aunque no lo está. | J100: La tienda es muy pequeña para la cantidad de productos que tiene, lo que hace incómodo caminar cuando está llena. Además, los vendedores manejan información muy básica, prácticamente solo precios y marcas. Deberían conocer más sobre características, usos y beneficios de los productos. | K100: Se debería mejorar la atención al cliente, dar mejores argumentos y ampliar el conocimiento de los vendedores sobre los productos y beneficios de comprar en Dismac, ya que no se mencionó ninguno. También poner más entusiasmo. | L100: No habría nada que mejorar; la atención es muy buena. | M100: La atención fue excelente; no tengo quejas. Tuve una buena experiencia. | N100: Cumplen con todos los criterios; nada que indicar para mejorar. Una de las mejores sucursales. | O100: El personal debería aumentar en número y mejorar su nivel de atención, que actualmente es muy básico y no convence. Deberían mencionar a todos los clientes los beneficios de comprar en Dismac. | P100: El primer vendedor solo estuvo un rato conmigo y luego se fue. Cuando le pregunté por las planchas, solo señaló el sector sin interés en atenderme. Después lo vi ocupado en cajas y tuve que buscar otra vendedora, que estaba comiendo y no se percató de que necesitaba atención. Respondía de manera seca y sin ánimo, sin mencionar promociones ni beneficios de comprar en Dismac. | Q100: Se deberían dar más argumentos sobre los productos, mencionar instalaciones y no olvidar las políticas de cambios y devoluciones. | R100: El vendedor debería incentivar la compra y no dejar que uno solo observe el producto. Al momento de comprar, debería explicar beneficios y políticas de la tienda, no esperar hasta la devolución. En cuanto a la cajera, debería ser más amable y no limitarse a cobrar directamente. | S100: La atención fue muy buena; no hay quejas sobre la tienda ni la atención. | T100: Si bien el vendedor tenía buena actitud y era amable, podría mejorar sus conocimientos para incentivar la compra. Por otro lado, la tienda cuenta con varios productos, pero el ambiente es bastante pequeño; ampliar el lugar sería más cómodo. | U100: El personal debería ser más convincente al ofrecer productos y explicar beneficios y políticas de Dismac. La explicación fue muy básica y poco atractiva; los letreros daban más información que los vendedores. | V100: Todo estuvo acorde a lo que se espera en la atención a un cliente; deberían seguir atendiendo así de atentos. | W100: Tal vez podrían dar más a conocer su página web para que la gente explore y vea más productos. | X100: Por parte del vendedor, todo perfecto. Sin embargo, en el área de caja falta mayor interacción con el cliente: dar más información sobre la entrega del producto o ventajas de comprar en Dismac. Se limitó a pedir mis datos y cobrar, como en cualquier cajero convencional. | Y100: No habría nada que mejorar, salvo ampliar la sucursal, ya que los pasillos son angostos. | Z100: El vendedor debería dar prioridad a los clientes presentes en la tienda. Al llegar, saludé a un vendedor ocupado con otro cliente; otro estaba mostrando su celular a otro cliente. Finalmente me acerqué a uno sin clientes, pero estaba respondiendo mensajes y viendo productos en la pantalla de Dismac. Su atención no estaba enfocada en mí; respondía apurado. Debería dar prioridad a los clientes en físico dentro de la sucursal. | AA100: Los vendedores deberían ofrecer más productos y no centrarse solo en el que el cliente consulta, explicando beneficios de comprar en Dismac. | AB100: Sería mejor que un solo vendedor atienda de principio a fin la compra. En esta ocasión me atendieron tres vendedores, lo que generó pérdida de tiempo en los cambios de atención.
B102: n/a: No aplica.

Sheet La Paz
B2: Reporte Diciembre 2025 - Visitas encubiertas Dismac
B3: La Paz - Comentarios Relevantes
C5: LA PAZ
B7: DIMENSIONES EVALUADAS | C7: Calacoto Av. Ballivian 1305 | E7: E. Salmon 1053 | G7: El Alto 4 | I7: Socabaya | K7: Multicine Río Seco | M7: El Alto Satélite | O7: El Alto Cruce Villa Adela
C8: Consulta | D8: Compra | E8: Consulta | F8: Compra | G8: Consulta | H8: Compra | I8: Consulta | J8: Compra | K8: Consulta | L8: Compra | M8: Consulta | N8: Compra | O8: Consulta | P8: Compra
B9: FECHA DE LA VISITA | C9: 08-FEB-2026 | D9: 09-FEB-2026 | E9: 06-FEB-2026 | F9: 14-FEB-2026 | G9: 14-FEB-2026 | H9: 11-FEB-2026 | I9: 06-FEB-2026 | J9: 09-FEB-2026 | K9: 07-FEB-2026 | L9: 11-FEB-2026 | M9: 07-FEB-2026 | N9: 10-FEB-2026 | O9: 12-FEB-2026 | P9: 14-FEB-2026
B10: TURNO | C10: Tarde | D10: Tarde | E10: Tarde | F10: Tarde | G10: Tarde | H10: Tarde | I10: Tarde | J10: Tarde | K10: Mañana | L10: Tarde | M10: Tarde | N10: Tarde | O10: Tarde | P10: Medio día
B11: PRODUCTO | C11: Lavadora de 12 kilos | D11: Cocina clásica de 4h - Kerning Moderatto Q6 Plata | E11: Lavadora de más de 10 kilos | F11: Plancha alisadora de cabello connecto | G11: Cocina 5 hornallas | H11: Cocina Kerning de 4 h Negro | I11: Cocina o Lavadora | J11: Plancha a vapor Oster compacta 1400W de potencia | K11: Cocina de 6 hornillas | L11: Tenaza rizadora de cabello digital Connecto | M11: Cocina - Lavadora | N11: Licuadora enxuta 1.5 Lt. 500 W jarra de vidrio | O11: Lavadora | P11: Plancha a vapor básica Oster 1200W
B13: ATENCIÓN DEL VENDEDOR
B14: PRIMER CONTACTO
B15: El vendedor/a se percató de la presencia del cliente y se aproximó para atenderlo | C15: Esperé que se acercara como 10 minutos, me vio, es más se acercó y me saludó y se pasó directo, estaba con el celular manejando, seguí caminando pese a que estaba cerca no me atendió, después de 10 minutos yo tuve que llamarlo | D15: No aplica, habían 6 posibles clientes esperando en la tienda y solo 2 personas atendiendo, todos estaban atentos a que alguien se desocupe para hacerse atender... yo aproveché que un señor se fue a cajas para hacerme ver con la vendedora después de 9 minutos donde inicio la atención | E15: La vendedora se percató de mi presencia, pero atendió a una pareja que entró después de mi, se acercó primero a ellos y después a mí | F15: Habían 2 vendedores en la planta baja, uno de ellos solo veia su celular y la otra estaba con otro cliente aunque también caminaba por la tienda viendo su celular, en la planta alta solo estaba el cajero, no había vendedor, estuve caminando cerca del vendedor desocupado, pero no se me acercó | G15: Había vendedores caminando por la tienda, unos 4 y ninguno se me acercó, de igual manera había otros clientes y solo 1 estaba con vendedor, había igual otros vendedores en la zona de caja charlando en voz alta entre ellos | I15: Estuve caminando como 6 minutos, estaban detrás del mostrador todos, 2 cajeros, 1 persona en minicuotas y 2 vendedores caminaban, pero por el mismo sector viendo su celular todos. | L15: Estuve caminando como 6 minutos entre los pasillos, habia otra persona tambien viendo pero tampoco estaba siendo atendido los vendedores estaban cerca a las cajas con sus celulares y había 3 personas en los mostradores | P15: Me vieron, pero estaban hablando entre cuatro personas detrás de cajas, había 1 atendiendo, di vueltas por la agencia por 10 minutos y nadie venía, escuché murmullos de quien me atendería y se acercó un joven cuando pedi que me atiendan
B16: El vendedor/a lo saludó amablemente o pregunto en modo de bienvenida | D16: No me saludó, solo me dijo dígame que esta buscando? algo especifico? | G16: No me saludó, yo directamente le dije quisiera preguntar y me dijo que necesita? | I16: No me saludó, cuando pasaron los 6 minutos finalmente me acerqué al mostrador, le pregunté a la persona de minicuotas y salió una muchacha, solo me dijo en que me podía ayudar | L16: El vendedor no me saludó, pero se acercó cuando pregunté si alguien podía ayudarme, solo dijo claro que si
B17: El vendedor/a pregunta al cliente lo que busca o sus preferencias. | C17: No aplica, al momento de acercarme le consulté por el producto de mi interés | I17: No aplica, al momento de acercarme le consulté por el producto de mi interés | L17: No me preguntó sobre mis preferencias, pero empezó a mostrarme las opciones más caras principalmente
B18: El vendedor/a dirige al cliente a donde debe, según su necesidad | C18: No aplica, ya estaba en el área del producto | P18: No aplica, ya estaba en el área del producto
B19: GESTION DE VENTA
B20: El vendedor/a mostró el producto solicitado de forma rápida y sin hacer esperar mucho tiempo al cliente. | C20: No aplica, no fue necesario traer el producto de almacén | E20: No aplica, no fue necesario traer el producto de almacén | G20: No aplica, no fue necesario traer el producto de almacén | I20: No aplica, no fue necesario traer el producto de almacén | K20: No aplica, no fue necesario traer el producto de almacén | M20: No aplica, no fue necesario traer el producto de almacén | O20: No aplica, no fue necesario traer el producto de almacén
B21: El vendedor/a en caso de no disponer del producto en tienda, utilizó la página ecommerce de DISMAC para ofrecer otras opciones al cliente. | C21: No aplica, el producto se encontraba en tienda | D21: No aplica, el producto se encontraba en tienda | F21: No aplica, el producto se encontraba en tienda | G21: Me dijo que había una opción más de cocina Oster con spidera en la sucursal de calacoto y mencionó dos veces: "te puedo mostrar en la página web", pero no me llevó para mostrarme ni tampoco me preguntó si queria ir a ver | I21: No aplica, el producto se encontraba en tienda | K21: Mencionó la página, pero no mostró, ni ingresó porque el producto estaba en tienda | L21: Revisó la página de Dismac, pero desde su celular y no me mostró, eso hizo cuando le pregunté por el material de las planchas | M21: Cuando pregunté por una cocina de marca diferente Dako, miro en su celular la página de Dismac, pero no me mostró, leyó desde su celular las caracteristicas, yo pude ver de reojo. | N21: No aplica, el producto se encontraba en tienda | P21: No aplica, el producto se encontraba en tienda
B22: El vendedor/a demostró tener conocimiento del producto y proporcionó toda la información (garantía) y especificaciones del mismo. | G22: Me dijo que no estaba seguro de para que sirve el accesorio adicional que tienen las cocinas, tampoco me supo responder otro dato sobre material o medidas y decía si no me equivoco... se equivocó sobre la doble llama de la cocina oster porque en la puerta del horno decía otra cosa | K22: No sabía cuál tenía grill, estaba revisando uno por uno cuál tenía y cuál era eléctrica o a gas y estaba revisando precios y no recordó que había en la tienda de 6 hornillas | L22: El vendedor no sabía las características de los productos, mientras le preguntaba me dijo voy a revisar, entró a la página de Dismac y a google, miro la procedencia de las marcas, las busco en chat gpt y me dice debe ser chinita descartable porque es nueva.
B23: El vendedor/a mostró diferentes opciones de productos e hizo recomendaciones de acuerdo a sus necesidades.
B24: El vendedor/a le comunicó los precios más bajos garantizados de Dismac. | D24: No mencionó nada sobre que tienen los precios más bajos del mercado | E24: No mencionó nada sobre que tienen los precios más bajos del mercado | F24: No mencionó nada sobre que tienen los precios más bajos del mercado | G24: No mencionó nada sobre que tienen los precios más bajos del mercado | J24: No mencionó nada sobre que tienen los precios más bajos del mercado | K24: No mencionó nada sobre que tienen los precios más bajos del mercado | L24: No mencionó nada sobre que tienen los precios más bajos del mercado | M24: No mencionó nada sobre que tienen los precios más bajos del mercado | O24: No mencionó nada sobre que tienen los precios más bajos del mercado
B25: El vendedor/a le comunicó sobre las promociones especiales, productos en combo, descuentos o lanzamientos. | D25: No mencionó ninguna promoción o productos en combo | F25: No mencionó ninguna promoción o productos en combo | G25: No mencionó ninguna promoción o productos en combo | J25: No mencionó ninguna promoción o productos en combo | L25: No mencionó ninguna promoción o productos en combo | M25: No mencionó ningún tipo de promoción, menos bandeos o combos, se limitó a leer los productos y precios | P25: No mencionó ninguna promoción o productos en combo
B26: El vendedor/a explicó de qué trata la garantía extendida y sus beneficios | C26: No mencionó nada sobre la garantía extendida | E26: No mencionó nada sobre la garantía extendida | G26: No mencionó nada sobre la garantía extendida | K26: No mencionó nada sobre la garantía extendida | L26: No mencionó nada sobre la garantía extendida | M26: No mencionó nada sobre la garantía extendida | O26: No mencionó nada sobre la garantía extendida | P26: No mencionó nada sobre la garantía extendida
B27: El vendedor/a se esmeró en brindar argumentos para incentivar la compra del producto. | F27: No me incentivó a la compra del producto, solo respondía a mis consultas, no se esmeró en brindar argumentos para que realice la compra | I27: Sentí que se limitaba a responder las preguntas y las características básicas, tampoco me motivó y muchas veces habían silencios donde yo tenía que seguir indagando
B28: El vendedor/a cerró la venta
B29: El vendedor/a ofreció y explicó los beneficios del servicio de entrega gratuita, tiempo de entrega, áreas de cobertura. | F29: No aplica, se realizó una compra pequeña | J29: No aplica, se realizó una compra pequeña | L29: No aplica, se realizó una compra pequeña | N29: No aplica, se realizó una compra pequeña | P29: No aplica, se realizó una compra pequeña
B30: El vendedor/a ofreció y explicó los beneficios del servicio de instalación garantizada. | F30: No aplica, se realizó una compra pequeña, el producto no requiere instalación | J30: No aplica, se realizó una compra pequeña, el producto no requiere instalación | L30: No aplica, se realizó una compra pequeña, el producto no requiere instalación | M30: No dijo nada acerca de la instalación de la cocina ni lavadora | N30: No aplica, se realizó una compra pequeña, el producto no requiere instalación | P30: No aplica, se realizó una compra pequeña, el producto no requiere instalación
B31: El vendedor/a explicó los beneficios de la política de cambios y devoluciones. | C31: No mencionó la política de cambios ni devoluciones | D31: No mencionó la política de cambios ni devoluciones | E31: No mencionó la política de cambios ni devoluciones | F31: No mencionó la política de cambios ni devoluciones | G31: No mencionó la política de cambios ni devoluciones | I31: No mencionó la política de cambios ni devoluciones | J31: No mencionó la política de cambios ni devoluciones | M31: No mencionó la política de cambios ni devoluciones | P31: No mencionó la política de cambios ni devoluciones
B32: El vendedor/a preguntó, si necesitaba algo más, o tuvo la capacidad/ habilidad de ofrecer productos ADICIONALES diferentes al que solicitó | C32: No aplica, al momento de acercarme le consulté por un tipo de producto | D32: Estaba bastante apurada al terminar de llenar un formulario en su celular solo me dijo es todo por favor pase a caja | E32: No aplica, le consulté por un producto en específico | F32: No ofreció ningún producto adicional | G32: No aplica, yo le consulté por un tipo de producto | I32: No aplica, yo le consulté por un tipo de producto | J32: No aplica, yo le consulté por un tipo de producto | K32: No aplica, le consulté por un producto en específico | L32: No hizo ninguna pregunta que incentive a realizar más compras | M32: No aplica, yo le consulté por un tipo de producto
B33: El vendedor/a consultó el método de pago y ofreció MINICUOTAS | C33: No mencionó nada de las mini cuotas | D33: No mencionó nada de las mini cuotas | E33: No mencionó nada de las mini cuotas | F33: No mencionó nada de las mini cuotas | G33: No mencionó nada de las mini cuotas | J33: No mencionó nada de las mini cuotas | L33: No mencionó nada de las mini cuotas | M33: No mencionó nada de las mini cuotas | P33: No mencionó nada de las mini cuotas
B34: El vendedor/a demostró actitud de servicio, amabilidad y cortesía en el trato
B35: En caso de interrupción durante la visita, el vendedor le pidió disculpas por la interrupción. | C35: No aplica, no hubo ninguna interrupción durante nuestra interacción | D35: Tuvimos una interrupción cuando un cliente anterior estaba en caja y al terminar de pagar la fue a buscar, nuevamente solo me dijo por favor espereme unos minutos siga viendo y al volver solo me dijo ya decidió? | E35: Cuando al finalizar(a los 15 min aprox) le preguntaron por un producto ella dirigió al lugar al otro cliente y me dejó viendo el producto y solo miraba que estaba haciendo | G35: No aplica, no hubo ninguna interrupción durante nuestra interacción | H35: No aplica, no hubo ninguna interrupción durante nuestra interacción | I35: No aplica, no hubo ninguna interrupción durante nuestra interacción | K35: No aplica, no hubo ninguna interrupción durante nuestra interacción | L35: No aplica, no hubo ninguna interrupción durante nuestra interacción | M35: No aplica, no hubo ninguna interrupción durante nuestra interacción | O35: No aplica, no hubo ninguna interrupción durante nuestra interacción
B36: INFORMACIÓN SOBRE LA INSTALACIÓN
B37: El vendedor/a coordinó y programó la entrega a domicilio del producto
B38: El vendedor/a coordinó y programó la instalación del producto | D38: No aplica, no solicite la instalación
B39: El vendedor/a informó y explicó los requisitos previos de instalación del producto | D39: No aplica, no solicité la instalación
B40: DESPEDIDA
B41: El vendedor/a le solicitó sus datos personales y en caso de no estar registrado en su sistema, lo registró | C41: No me pidió mis datos, ni registró en su sistema | E41: No me pidió mis datos, ni registró en su sistema | G41: No me pidió mis datos, ni registró en su sistema | I41: No me pidió mis datos, ni registró en su sistema | K41: No me pidió mis datos, ni registró en su sistema | M41: No me pidió mis datos, ni registró en su sistema
B42: El vendedor/a lo dirigió a caja para efectuar el pago. | D42: Solo me dijo pase por cajas, no me dijo donde ni nada, a eso le pregunté y solo se me acercó y me dijo sí solo vaya a cajas
B43: El vendedor/a se despidió amablemente y lo invito a visitar nuevamente la tienda | D43: Solo me dijo es todo pase a cajas, no se despidió | M43: No se despidió de mi cuando terminó la interacción, solo me dijo que lo busque si me animaba a comprar
B44: PRESENTACIÓN PERSONAL DEL VENDEDOR/A
B45: El vendedor/a se encontraba con el uniforme de la empresa.
B46: El vendedor/a tenía buena presencia (El cabello no está en su rostro, está limpio y prolijo) | I46: Estaba despeinada y con el cabello sucio, estaba con barbijo muy resfriada no se veía su cara muy bien | L46: El cabello estaba largo y el muchacho cubria parte de su cara con su cabello
B47: ATENCIÓN EN CAJA
B48: ATENCIÓN EN CAJA
B49: El cajero/a saludó amablemente. "Buenos días" "Buen día, en qué puedo ayudarle" "Cómo está" | F49: No aplica, me cobró el mismo vendedor | P49: No aplica, me cobró el mismo vendedor
B50: El cajero/a respetó el orden de llegada. | F50: No aplica, era la única persona para ser atendida | L50: No aplica, era la única persona para ser atendida
B51: El cajero/a le comunicó sobre el monto a pagar y realizó el proceso de facturación (Pide NIT y explica la implementación de la facturación electrónica, es decir pide los datos al cliente, explica que la factura le llegará por correo o a su teléfono (opcional) y efectivamente la factura le llegó por uno de estos medios).
B52: El cajero/a entregó la garantía del producto o indicó que esta venía dentro de la caja del producto. (Aplica solo en caso de refrigeradores, cocinas, freezers, lavadoras, microondas y Aires Acondicionados)
B53: El cajero/a lo dirigió o le indicó quien es el encargado de hacer la entrega | F53: No aplica, el mismo cajero me entregó el producto
B54: El cajero/a lo atendió con rapidez en el cobro, facturación.
B55: El cajero agradecio la compra, se despidió amablemente "Hasta luego" "Que tenga un buen día" "Que le vaya bien" y lo invitó a visitar la tienda nuevamente
B56: INFORMACIÓN SOBRE LA ENTREGA E INSTALACIÓN DE PRODUCTOS
B57: El cajero/a validó la fecha de entrega a domicilio del producto | D57: No corroboró que la entrega la programé con el vendedor para el martes entre las 18 y las 21
B58: El cajero/a validó la fecha de instalación del producto | D58: No aplica, no solicité instalación
B59: El cajero/a validó que el vendedor explicó los requisitos previos de instalacion del producto, que el cliente entiende estos requisitos, y el cajero entregó los requisitos impresos al cliente. | D59: No validó que el vendedor me haya hablado de los requisitos específicos o especiales para la instalación de la cocina
B60: El cajero informó y explicó al cliente que para cualquier cambio de horario que quiera realizar en la programación de la entrega o instalación debe llamar al número 800 10 2000 | D60: No me dijo nada acerca de la entrega ni sobre realizar algún cambio en el horario
B61: MINI CUOTAS - El cajero/a consultó el método de pago y ofreció MINICUOTAS | F61: No mencionó nada sobre mini cuotas | J61: Si me preguntó el método de pago, pero no ofreció mini cuotas | L61: No mencionó nada sobre mini cuotas | P61: No mencionó nada sobre mini cuotas
B62: PRESENTACIÓN PERSONAL DEL CAJERO
B63: El cajero/a se encontraba con el uniforme de la empresa.
B64: El cajero/a tenía buena presencia (El cabello no está en su rostro, está limpio y prolijo)
B65: ATENCIÓN POSTPAGO
B66: ENTREGA EN TIENDA
B67: El vendedor/a mostró los accesorios con los que viene el producto | F67: No aplica, la plancha no venía con ningún accesorio adicional | L67: No mostró ningún accesorio, ni manual, ni nada, solo la enchufó y la probó, estaba nervioso tratando de explicarme
B68: El vendedor/a probó el producto
B69: El vendedor/a se despidió amablemente y lo invito a visitar nuevamente la tienda
B70: AMBIENTE DE LA TIENDA
B71: LIMPIEZA Y ORDEN
B72: El interior de la tienda se encontraba limpio y en buenas condiciones (pisos, paredes y techo) | C72: En el piso se encontró serpentina con globos rotos y polvo, más que todo en el área de cocinas | D72: Estaba en buenas condiciones, pero imagino que estan decorando para carnavales porque había globos y serpentina en algunos lugares en el piso además que había una botella de agua detrás de uno de los televisores al inicio me imagino de algún vendedor o del seguridad | E72: En el piso había restos de una bolsa rota como en pedazos y en la entrada había manchas de polvo | F72: Estaba bastante sucio, tenía basuras por todas partes, restos de serpentina y globos, papeles y tambien tanto abajo como en la parte superior tenía manchas en el piso, de igual manera la señaletica amarilla y negra estaba desgastada y tenía partes desportilladas, es decir que la ultima grada al subir a la planta alta le faltaba un pedazo | G72: Habían papeles de serpentina en el piso y además manchas de zapatos especialmente al ingreso, también desgaste en la cinta amarilla y negra en el piso | J72: Había globos, serpentina en el piso, bolsas rotas y cables para asegurar los cables delgados | M72: El piso estaba bastante sucio en el área de cocinas | O72: El piso estaba sucio y tenía basuras en el área de lavadoras
B73: Los pasillos se encontraban libres y permitían la libre circulación | F73: Tenía cajas de televisores a lado de las gradas y ahí mismo tenía basura | G73: Cerca de la puerta que divide la tienda, habían cajas de varios productos apilados de igual manera cerca a cajas estaba sucio y desordenado | L73: Había un montacargas cerca, junto a las planchas de cabello que hacía angosto e incomodo el paso y también cajas de televisores pegados al vidrio del último pasillo que también dificultaba el libre tránsito de clientes | O73: Tenía cajas en medio de los pasillos que interrumpian el paso
B74: Los productos se encontraban ordenados y limpios | C74: Estaba con polvo los electrodomésticos como ser, cocinas, parlantes, licuadoras. | H74: Algunas secciones tenían polvo en los artefactos como ser: las cocinas, parlantes y tv | I74: Había productos chuecos en la entrada y una cinta adhesiva gruesa cerca de unos productos al ingreso | K74: En el área de las cocinas se notaba el polvo encima, no estaba limpio | O74: Los productos estaban muy apretos por el poco espacio y daba la sensación de no estar expuestos para el público sino más bien apilados, no se entendían las etiquetas con relación a los productos
B75: LETREROS Y SEÑALETICA
B76: Los productos cuentan con la cartelera o letreros que indican sus precios | F76: No todos los productos tenían letreros, ni todos los letreros tenían productos como una plancha de pelo | M76: Aparentemente no había desorden en la tienda pero sí había etiquetas que no correspondian al producto o etiquetas con espacio vacío
B77: Los letreros de promociones y la señalética eran visibles
B78: DELIVERY
B79: ENTREGA A DOMICILIO
B80: El chofer se comunicó con el cliente por lo menos 30 minutos antes para confirmar la entrega
B81: El producto llegó a su casa en el rango de tiempo indicado (No más de 24 Hr)
B82: El chofer dejó el producto dentro del inmueble y en el lugar solicitado por el cliente
B83: El producto llegó en perfecto estatodo sin daños estéticos
B84: DEVOLUCIÓN
B85: DEVOLUCIÓN EN TIENDA
B86: El encargado/a lo saludó amablemente
B87: El encargado/a escuchó atentamente, con paciencia y con interés
B88: El encargado/a demostró una buena actitud ante su solicitud
B89: El encargado/a verificó el estado del producto, y determinó si cumple con la política de cambios y devoluciones | D89: Solo me recibió la cocina y me dirigió a cajas, me pidió mi ci y mi factura para escanear, no verificó el producto
B90: El encargado/a hizo efectiva la devolución
B91: La atención por parte del encargado/a fue ágil y rápida.
B92: El encargado le brindó toda la información necesaria con respecto a la devolución (en caso de demora)
B93: MEDIDAS DE BIOSEGURIDAD
B94: Midieron su temperatura y proporcionaron alcohol líquido o en gel al ingresar a la sucursal
B95: Al ingresar la persona que controla verificó que el cliente tenga barbijo
B96: El personal de tienda, ¿estuvo con el barbijo puesto todo el tiempo
B97: En el sector de caja, contaban con alcohol líquido o en gel
B98: EXPERIENCIA EN EL SERVICIO
B99: ¿Qué rescata de la visita que realizó? es decir, ¿qué acciones positivas observó durante su visita? | C99: Esta agencia sí contaba con varios empleados; es amplia, tiene variedad de productos expuestos y la atención del vendedor fue muy amable y cordial. | D99: La tienda es grande y limpia en general. Esta vez tenía algunos elementos de decoración (globos de carnaval) en el piso, pero la atención fue buena. Cuando fui hacía demasiado calor; tal vez sería bueno implementar algún sistema de aire para refrescar el ambiente. Todo el personal fue amable. | E99: Podría destacar la variedad de productos que se tiene en esta sucursal; todos los empleados estaban uniformados y fueron amables. | F99: La atención de la muchacha que me atendió cuando volví a hacer la devolución fue muy buena y amable. | G99: La tienda era grande y con los productos bien distribuidos. Vi artículos que no encontré en otras sucursales y mayor variedad. Había más personal disponible para atender. No había música en la tienda; luego intentaron ponerla con un volumen adecuado. | H99: La atención fue cordial y ágil. | I99: Fue una visita bastante tranquila. La vendedora respondió a todas mis preguntas con claridad y amabilidad. El ambiente era agradable. | J99: La atención del personal fue amable y cordial. | K99: La vendedora fue cordial, pese a que no tenía pleno dominio de la información del producto, y trató de incentivar la compra. | L99: La tienda estaba limpia en general, con un ambiente agradable. Los productos estaban al alcance y todo bien iluminado. | M99: La actitud del personal fue amable. Aunque estaban desocupados al momento de mi visita —porque justo entré y era la única persona— todos estaban trabajando en tareas como engrapar folletos con sus datos de vendedor y requisitos de mini cuotas. No se veía gente sin hacer nada. Mientras recorría la tienda, otro vendedor me preguntó si necesitaba algo; al decirle que ya me atendieron, me regaló una revista e incentivó la compra, hablándome de campañas de venta, descuentos y opciones de pago al crédito y al contado. | N99: La atención fue muy cordial; la vendedora se esmeró en atenderme y el cajero fue muy atento, incluso con la agencia relativamente llena. | O99: La muchacha fue muy amable en todo momento y dedicada a responder mis preguntas. | P99: El vendedor fue amable. La sucursal tiene variedad de productos y está ubicada en un lugar estratégico. | Q99: La sucursal estaba bien ordenada. Aunque de afuera parecía pequeña, al entrar uno se lleva una grata sorpresa por lo fácil que es caminar por sus pasillos. Los vendedores estaban siempre atentos a las necesidades de los clientes. | R99: En términos generales, la tienda Dismac de la Ayacucho es grande, con ambientes cómodos y limpios. Cabe recordar que es de reciente apertura; es espaciosa y se puede encontrar variedad de productos para el hogar. | S99: Una tienda muy grande, con gran variedad de productos, ordenada y limpia, en buena ubicación. | T99: La sucursal América es amplia y ofrece una visión adecuada de los productos en general. La atención en caja, de la vendedora y de los encargados de la devolución fue excelente. | U99: La tienda estaba bien organizada; se podían ver todos los productos, desde pequeños hasta grandes, de manera cómoda. El vendedor saludó con un apretón de manos, muy formal y adecuado, lo que genera mayor confianza en sus explicaciones. | V99: Excelente atención al cliente. Todos los asesores de ventas están atentos a cualquier persona que ingrese, con buena actitud y una sonrisa. Todos los productos tienen precios visibles. Explican los beneficios de comprar en Dismac, incentivan a adquirir más productos, muestran ofertas y combos, y explican las garantías (algo que no hacen en las sucursales América y Ayacucho). Esta tienda está más limpia que las otras, todo ordenado y cuidado. | W99: El personal fue muy amable; me explicó muchas cosas, estuvo atento y me enseñó a usar su página con paciencia. | X99: El ambiente y la infraestructura son muy buenos; la tienda es muy linda. | Y99: Buen ambiente; la tienda es hermosa. | Z99: La atención fue buena y rápida.
B100: ¿En qué debería mejorar esta sucursal de Dismac para brindar una mejor experiencia de compra a sus clientes? | C100: Los vendedores estaban reunidos en un solo lugar, aunque había varios clientes. Al entrar, ninguno atendía; el único que vi estaba entretenido con el celular y no pudo atenderme. Además, los adornos de carnaval no deberían estar al alcance de los niños, ya que jalaban las serpentinas al piso. | D100: La tienda es espaciosa y ordenada, pero hace falta más personal. Cuando fui en la noche solo había una persona atendiendo a todos. Como la tienda es grande, no era fácil ubicar a un vendedor. En cuanto a la entrega a domicilio, el chofer me llamó al día siguiente a las 14:12 por WhatsApp y dijo que tardaría 40 minutos. Preguntó si podía entregar en ese momento en lugar de la noche y acepté. Llegó a las 15:10, más de 40 minutos después. El horario programado con la vendedora era entre las 18:00 y las 21:00. | E100: Al ingresar al ambiente observé a un vendedor atendiendo a unos clientes. Caminé viendo los productos hasta que terminó con ellos; luego encendió su radio a alto volumen, se acercó y pasó de largo revisando el celular hacia la puerta. Después de unos minutos entraron otros clientes y, tres minutos más tarde, llegó la vendedora. Aunque me vio primero, giró para atender a la pareja de clientes y recién después se dirigió a mí. Se debería mejorar la limpieza del lugar y bajar el volumen de la música ambiente, que es muy fuerte. | F100: La tienda estaba sucia y desordenada. Al volver para la devolución había aún más cajas en los pasillos, lo que impedía pasar. Había productos sin etiqueta, como celulares o máquinas de coser, y etiquetas sin productos en la sección de planchas para el pelo. Los vendedores tampoco estaban atentos. | G100: Se debería limpiar con más frecuencia, ya que las manchas en el piso dan mal aspecto. Además, había personal charlando entre sí en lugar de atender a los clientes u ordenar las cajas apiladas. | H100: Debería haber espacio en la puerta para estacionar autos al llevar o devolver productos, ya que los vendedores en la calle bloqueaban el paso a los vehículos. | I100: Los vendedores tendrían que estar más atentos a los clientes, ya que no había nadie fuera de los mostradores. Todos estaban en sus celulares, incluso los cajeros. Los dos vendedores estaban cerca del área de cajas: uno entraba y salía del almacén sin llevar nada, y la otra estaba parada mirando su celular. | J100: El espacio es pequeño. Fui alrededor de las 5 de la tarde y estaba lleno; la gente se chocaba en los pasillos para poder pasar. | K100: Se necesita más personal para atender; solo había dos personas, la vendedora y el cajero, y había que esperar a que se desocupen de otros clientes. | L100: Los pasillos son muy angostos, peor aún si colocan cajas de lavadoras y televisores. Los vendedores no están atentos a los clientes y no explican con claridad los productos; desconocen incluso la procedencia de las marcas. Me dijeron que Enxuta era china, pero en otra tienda me dieron otra información. | M100: Se debería capacitar al personal para que hable de los aspectos más técnicos y relevantes de los productos y sus diferencias. Cuando pregunté por lavadoras, el vendedor solo mencionó el tipo de carga y leyó los precios. En el caso de las cocinas, al decir que no conocía las marcas, en lugar de explicarlas o incentivar la compra por calidad o beneficios, buscó en su celular. | N100: La música ambiente es muy alta y la agencia cuenta con un espacio reducido, lo que dificulta ver los productos y decidir qué comprar. | O100: La vendedora no conocía algunos detalles de la lavadora y se inventaba respuestas. Al mostrarme la página web en la pantalla más grande, se contradijo con lo que había dicho antes: me aseguró que la lavadora Kering no ahorraba electricidad, pero ahí figuraba que sí. El ambiente es muy pequeño y la música muy fuerte, lo que incomodaba. | P100: El volumen de la música durante la devolución era muy fuerte y, junto con el ruido de los carnavales afuera, dificultaba escuchar. | Q100: Se necesitan letreros que guíen a los clientes hacia la parte superior del negocio, ya que parece de difícil acceso o no se nota al entrar. | R100: El personal de ventas no fue atento ni cordial. En caja la atención fue buena, pero el vendedor estaba más pendiente de su celular. Se necesita capacitación para mejorar el trato y explicar procesos como la devolución. | S100: Los vendedores deberían estar más atentos a los clientes. Si hay gran demanda, deben buscar formas de atender a todos. | T100: Tener una rampa para discapacitados o para subir y bajar productos grandes sería una buena idea, considerando el peso de las compras. | U100: Tal vez sería conveniente mover el “tótem” al centro de la tienda, ya que su ubicación actual al ingreso hace que se ignore fácilmente. | V100: Solo mejorar la exposición de productos nuevos en el mercado. | W100: Renovar algunos carteles para resaltar más los detalles en el área de celulares. | X100: Los vendedores deberían tener un poco más de conocimiento sobre todos los productos. | Y100: No me pidieron mis datos personales; deberían ampliar esta parte de la interacción. | Z100: La música estaba muy fuerte en la tienda al momento de la compra; en la devolución ya no era tan estruendosa. Deberían regular el volumen.
B102: n/a: No aplica.

Sheet Cochabamba
E2: Reporte Diciembre 2025 - Visitas encubiertas DISMAC
E3: Cochabamba - Comentarios Relevantes
B7: Pesos | E7: DIMENSIONES EVALUADAS | F7: Ayacucho 309 | H7: Av. América #459 | J7: Quillacollo
F8: Consulta | G8: Compra | H8: Consulta | I8: Compra | J8: Consulta | K8: Compra
E9: FECHA DE LA VISITA | F9: 07-FEB-2026 | G9: 09-FEB-2026 | H9: 13-FEB-2026 | I9: 09-FEB-2026 | J9: 09-FEB-2026 | K9: 19-FEB-2026
E10: TURNO | F10: Tarde | G10: Tarde | H10: Tarde | I10: Medio día | J10: Mañana | K10: Tarde
E11: PRODUCTO | F11: Refrigerador LG y oster | G11: Mixer Mallory | H11: Regrigerador Cónsul | I11: Lavadora Enxuta carga superior 7kgs blanca | J11: Lavadora LG | K11: Mixer Enxuta
B13: 0.3 | E13: ATENCIÓN DEL VENDEDOR
B14: 0.2 | E14: PRIMER CONTACTO
E15: El vendedor/a se percató de la presencia del cliente y se aproximó para atenderlo
E16: El vendedor/a lo saludó amablemente o pregunto en modo de bienvenida
E17: El vendedor/a pregunta al cliente lo que busca o sus preferencias.
E18: El vendedor/a dirige al cliente a donde debe, según su necesidad | G18: No aplica, yo tuve que acercarme a él ya que estaba viendo su celular, estaba cerca al producto de mi interés
B19: 0.3 | E19: GESTION DE VENTA
E20: El vendedor/a mostró el producto solicitado de forma rápida y sin hacer esperar mucho tiempo al cliente.
E21: El vendedor/a en caso de no disponer del producto en tienda, utilizó la página ecommerce de DISMAC para ofrecer otras opciones al cliente. | F21: No aplica, el producto se encontraba disponible en la tienda | G21: No aplica, el producto se encontraba disponible en la tienda | H21: No aplica, el producto se encontraba disponible en la tienda | I21: No aplica, el producto se encontraba disponible en la tienda | J21: No aplica, el producto se encontraba disponible en la tienda
E22: El vendedor/a demostró tener conocimiento del producto y proporcionó toda la información (garantía) y especificaciones del mismo.
E23: El vendedor/a mostró diferentes opciones de productos e hizo recomendaciones de acuerdo a sus necesidades. | G23: El vendedor estaba atento a su celular y solo respondía a mis preguntas, no mostró interés en la venta
E24: El vendedor/a le comunicó los precios más bajos garantizados de Dismac. | G24: No explicó nada, tampoco mostró interés en la venta, ni en atender, ni en cumplír con mis necesidades. | H24: No me indicó nada sobre el descuento del 20% si encontraba un producto con precio más bajo en otro lugar | J24: El vendedor no mencionó los precios más bajo a pesar de que se indicó haber visto el producto algo más barato en tienda amiga, solo pasó a explicar las características de otro producto
E25: El vendedor/a le comunicó sobre las promociones especiales, productos en combo, descuentos o lanzamientos. | G25: No explicó nada, ni de promociones ni de productos. Todo el tiempo de atención estuvo pendiente de su celular
E26: El vendedor/a explicó de qué trata la garantía extendida y sus beneficios | J26: El vendedor no me dió explicaciones sobre la garantía extendida de Dismac o los plazos
E27: El vendedor/a se esmeró en brindar argumentos para incentivar la compra del producto. | G27: En ningún momento durante la visita el vendedor mostró interés en atender, ni explicar nada, fui yo quien realizó las preguntas para comprar un electrodoméstico.
E28: El vendedor/a cerró la venta
E29: El vendedor/a ofreció y explicó los beneficios del servicio de entrega gratuita, tiempo de entrega, áreas de cobertura. | G29: No aplica, era compra pequeña | H29: No me indicó nada sobre la entrega a domicilio o si era gratuito | J29: Se preguntó por una lavadora, no se mencionó las ventajas de la entrega a domicilio e instalación de Dismac durante la consulta | K29: No aplica, era compra pequeña
E30: El vendedor/a ofreció y explicó los beneficios del servicio de instalación garantizada. | G30: No aplica, era compra pequeña | H30: No aplica, el producto no requería instalación | J30: El vendedor no me explicó los beneficios de la instalación gratuita cuando estaba preguntando por lavadoras a pesar de que explicó muy bien el ahorro de agua y ventajas del producto | K30: No aplica, era compra pequeña
E31: El vendedor/a explicó los beneficios de la política de cambios y devoluciones. | F31: No se explicó las políticas de cambios o devoluciones durante la visita | G31: No explicó nada de cambios y devoluciones | H31: No me explicó nada sobre las devoluciones | J31: El vendedor no explicó los beneficios de las políticas de cambios y devoluciones durante la visita, se concentró en las ventajas del producto en sí
B32: 0.2 | E32: El vendedor/a preguntó, si necesitaba algo más, o tuvo la capacidad/ habilidad de ofrecer productos ADICIONALES diferentes al que solicitó | G32: No mostró ningún producto adicional, yo le pregunté sobre una jarra eléctrica Oster y no detalló las características ni precios, solo dijo que si había | I32: La vendedora al momento de terminar la interacción de compra me mandó directamente a caja para hacer el pago
E33: El vendedor/a consultó el método de pago y ofreció MINICUOTAS | G33: No indicó nada de las mini cuotas, solo me dijo que me aproxime a las cajas | H33: No me indicó nada sobre los tipos de pago o mini cuotas, solo me habló de descuentos y el producto
E34: El vendedor/a demostró actitud de servicio, amabilidad y cortesía en el trato | G34: No demostró actitud de servicio, ni enseñar ningún producto durante mi visita. Estaba distraído con su celular.
E35: En caso de interrupción durante la visita, el vendedor le pidió disculpas por la interrupción. | G35: No aplica, no hubo interrupción | H35: No aplica, no hubo interrupción | I35: No aplica, no hubo interrupción | J35: No aplica, no hubo interrupción | K35: No aplica, no hubo interrupción
E36: INFORMACIÓN SOBRE LA INSTALACIÓN
E37: El vendedor/a coordinó y programó la entrega a domicilio del producto
E38: El vendedor/a coordinó y programó la instalación del producto | I38: No aplica, no correspondía hacer la instalación
E39: El vendedor/a informó y explicó los requisitos previos de instalación del producto
E40: DESPEDIDA
B41: 0.2 | E41: El vendedor/a le solicitó sus datos personales y en caso de no estar registrado en su sistema, lo registró | H41: No me pidió ningun dato personal | J41: El vendedor no solicitó mis datos durante la visita aunque si me enseño a usar el "totem" que está presente en la tienda y como contactar y ver precios desde la página
E42: El vendedor/a lo dirigió a caja para efectuar el pago.
E43: El vendedor/a se despidió amablemente y lo invito a visitar nuevamente la tienda | G43: No se despidió, tampoco me invitó a visitar la tienda nuevamente. En general ambos asesores de ventas estaban con uniformes, pero no fueron amables ni atentos con las personas, atienden a las personas viendo sus ropas y caras. | I43: La vendedora solo indicó donde se encontraban las cajas y se mantuvo llenando los datos de la entrega, al salir ella estaba ocupada con otro cliente y algo lejos de la puerta asi que no tuvimos más contacto
E44: PRESENTACIÓN PERSONAL DEL VENDEDOR/A
B45: 0.1 | E45: El vendedor/a se encontraba con el uniforme de la empresa.
E46: El vendedor/a tenía buena presencia (El cabello no está en su rostro, está limpio y prolijo)
E47: ATENCIÓN EN CAJA
E48: ATENCIÓN EN CAJA
B49: 0.2 | E49: El cajero/a saludó amablemente. "Buenos días" "Buen día, en qué puedo ayudarle" "Cómo está"
B50: 0.4 | E50: El cajero/a respetó el orden de llegada.
E51: El cajero/a le comunicó sobre el monto a pagar y realizó el proceso de facturación (Pide NIT y explica la implementación de la facturación electrónica, es decir pide los datos al cliente, explica que la factura le llegará por correo o a su teléfono (opcional) y efectivamente la factura le llegó por uno de estos medios).
E52: El cajero/a entregó la garantía del producto o indicó que esta venía dentro de la caja del producto. (Aplica solo en caso de refrigeradores, cocinas, freezers, lavadoras, microondas y Aires Acondicionados)
B53: 0.2 | E53: El cajero/a lo dirigió o le indicó quien es el encargado de hacer la entrega
E54: El cajero/a lo atendió con rapidez en el cobro, facturación.
E55: El cajero agradecio la compra, se despidió amablemente "Hasta luego" "Que tenga un buen día" "Que le vaya bien" y lo invitó a visitar la tienda nuevamente
E56: INFORMACIÓN SOBRE LA ENTREGA E INSTALACIÓN DE PRODUCTOS
E57: El cajero/a validó la fecha de entrega a domicilio del producto
E58: El cajero/a validó la fecha de instalación del producto | I58: No aplica, no se requiere la instalación
E59: El cajero/a validó que el vendedor explicó los requisitos previos de instalacion del producto, que el cliente entiende estos requisitos, y el cajero entregó los requisitos impresos al cliente. | I59: No aplica, no se requiere la instalación
E60: El cajero informó y explicó al cliente que para cualquier cambio de horario que quiera realizar en la programación de la entrega o instalación debe llamar al número 800 10 2000
B61: 0.4 | E61: MINI CUOTAS - El cajero/a consultó el método de pago y ofreció MINICUOTAS | I61: El pago se hizo por QR y anteriormente la vendedora confirmó que era pago al contado, por lo que creo que la cajera tenía esa impresión y no vio necesario el ofrecer las mini cuotas
E62: PRESENTACIÓN PERSONAL DEL CAJERO
E63: El cajero/a se encontraba con el uniforme de la empresa.
E64: El cajero/a tenía buena presencia (El cabello no está en su rostro, está limpio y prolijo)
E65: ATENCIÓN POSTPAGO
E66: ENTREGA EN TIENDA
B67: 0.15 | E67: El vendedor/a mostró los accesorios con los que viene el producto | G67: No aplica, al ser una compra pequeña, el producto estaba sellado. El vendedor me quería mostrar los accesorios le dije que estaba apurada.
E68: El vendedor/a probó el producto
E69: El vendedor/a se despidió amablemente y lo invito a visitar nuevamente la tienda | G69: No se despidió, tampoco invitó a visitar nuevamente las tiendas de Dismac
E70: AMBIENTE DE LA TIENDA
E71: LIMPIEZA Y ORDEN
B72: 0.2 | E72: El interior de la tienda se encontraba limpio y en buenas condiciones (pisos, paredes y techo)
B73: 0.75 | E73: Los pasillos se encontraban libres y permitían la libre circulación
E74: Los productos se encontraban ordenados y limpios
E75: LETREROS Y SEÑALETICA
E76: Los productos cuentan con la cartelera o letreros que indican sus precios
B77: 0.25 | E77: Los letreros de promociones y la señalética eran visibles
E78: DELIVERY
E79: ENTREGA A DOMICILIO
B80: 0.05 | E80: El chofer se comunicó con el cliente por lo menos 30 minutos antes para confirmar la entrega
B81: 0.7 | E81: El producto llegó a su casa en el rango de tiempo indicado (No más de 24 Hr)
E82: El chofer dejó el producto dentro del inmueble y en el lugar solicitado por el cliente
E83: El producto llegó en perfecto estatodo sin daños estéticos
E84: DEVOLUCIÓN
E85: DEVOLUCIÓN EN TIENDA
B86: 0.3 | E86: El encargado/a lo saludó amablemente
B87: 0.1 | E87: El encargado/a escuchó atentamente, con paciencia y con interés
B88: 0.3 | E88: El encargado/a demostró una buena actitud ante su solicitud
E89: El encargado/a verificó el estado del producto, y determinó si cumple con la política de cambios y devoluciones
E90: El encargado/a hizo efectiva la devolución
E91: La atención por parte del encargado/a fue ágil y rápida.
E92: El encargado le brindó toda la información necesaria con respecto a la devolución (en caso de demora)
E93: MEDIDAS DE BIOSEGURIDAD
E94: Midieron su temperatura y proporcionaron alcohol líquido o en gel al ingresar a la sucursal
E95: Al ingresar la persona que controla verificó que el cliente tenga barbijo
E96: El personal de tienda, ¿estuvo con el barbijo puesto todo el tiempo
E97: En el sector de caja, contaban con alcohol líquido o en gel
E98: EXPERIENCIA EN EL SERVICIO
E99: ¿Qué rescata de la visita que realizó? es decir, ¿qué acciones positivas observó durante su visita? | F99: La sucursal estaba bien ordenada. Aunque de afuera parecía pequeña, al entrar uno se lleva una grata sorpresa por lo fácil que es caminar por sus pasillos. Los vendedores estaban siempre atentos a las necesidades de los clientes. | G99: En términos generales, la tienda Dismac de la Ayacucho es grande, con ambientes cómodos y limpios. Cabe recordar que es de reciente apertura; es espaciosa y se puede encontrar variedad de productos para el hogar. | H99: Una tienda muy grande, con gran variedad de productos, ordenada y limpia, en buena ubicación. | I99: La sucursal América es amplia y ofrece una visión adecuada de los productos en general. La atención en caja, de la vendedora y de los encargados de la devolución fue excelente. | J99: La tienda estaba bien organizada; se podían ver todos los productos, desde pequeños hasta grandes, de manera cómoda. El vendedor saludó con un apretón de manos, muy formal y adecuado, lo que genera mayor confianza en sus explicaciones. | K99: Excelente atención al cliente. Todos los asesores de ventas están atentos a cualquier persona que ingrese, con buena actitud y una sonrisa. Todos los productos tienen precios visibles. Explican los beneficios de comprar en Dismac, incentivan a adquirir más productos, muestran ofertas y combos, y explican las garantías (algo que no hacen en las sucursales América y Ayacucho). Esta tienda está más limpia que las otras, todo ordenado y cuidado.
E100: ¿En qué debería mejorar esta sucursal de Dismac para brindar una mejor experiencia de compra a sus clientes? | F100: Se necesitan letreros que guíen a los clientes hacia la parte superior del negocio, ya que parece de difícil acceso o no se nota al entrar. | G100: El personal de ventas no fue atento ni cordial. En caja la atención fue buena, pero el vendedor estaba más pendiente de su celular. Se necesita capacitación para mejorar el trato y explicar procesos como la devolución. | H100: Los vendedores deberían estar más atentos a los clientes. Si hay gran demanda, deben buscar formas de atender a todos. | I100: Tener una rampa para discapacitados o para subir y bajar productos grandes sería una buena idea, considerando el peso de las compras. | J100: Tal vez sería conveniente mover el “tótem” al centro de la tienda, ya que su ubicación actual al ingreso hace que se ignore fácilmente. | K100: Solo mejorar la exposición de productos nuevos en el mercado.

Sheet Sucre-Tarija
E2: Reporte Diciembre 2025 - Visitas encubiertas DISMAC
E3: Sucre - Tarija - Comentarios Relevantes
F5: SUCRE - TARIJA
B7: Pesos | E7: DIMENSIONES EVALUADAS | F7: Sucre | H7: Tarija
F8: Consulta | G8: Compra | H8: Consulta | I8: Compra
E9: FECHA DE LA VISITA | F9: 13-FEB-2026 | G9: 10-FEB-2026 | H9: 19-FEB-2026 | I9: 12-FEB-2026
E10: TURNO | F10: Medio día | G10: Tarde | H10: Tarde | I10: Tarde
E11: PRODUCTO | F11: Refrigerador | G11: Plancha de cabello | H11: Heladera | I11: Plancha
B13: 0.3 | E13: ATENCIÓN DEL VENDEDOR
B14: 0.2 | E14: PRIMER CONTACTO
E15: El vendedor/a se percató de la presencia del cliente y se aproximó para atenderlo
E16: El vendedor/a lo saludó amablemente o pregunto en modo de bienvenida
E17: El vendedor/a pregunta al cliente lo que busca o sus preferencias.
E18: El vendedor/a dirige al cliente a donde debe, según su necesidad
B19: 0.3 | E19: GESTION DE VENTA
E20: El vendedor/a mostró el producto solicitado de forma rápida y sin hacer esperar mucho tiempo al cliente.
E21: El vendedor/a en caso de no disponer del producto en tienda, utilizó la página ecommerce de DISMAC para ofrecer otras opciones al cliente.
E22: El vendedor/a demostró tener conocimiento del producto y proporcionó toda la información (garantía) y especificaciones del mismo.
E23: El vendedor/a mostró diferentes opciones de productos e hizo recomendaciones de acuerdo a sus necesidades.
E24: El vendedor/a le comunicó los precios más bajos garantizados de Dismac. | F24: No explicó de los precios bajos, pero si que tienen todo tipo de productos y me indicó cuales | G24: No me dijo absolutamente nada sobre los precios más bajos del mercado | I24: Me dijo en la devolución, pero no en la compra
E25: El vendedor/a le comunicó sobre las promociones especiales, productos en combo, descuentos o lanzamientos. | G25: No me mencionaron nada sobre productos en oferta
E26: El vendedor/a explicó de qué trata la garantía extendida y sus beneficios | F26: No me explicó nada de la garantía extendida
E27: El vendedor/a se esmeró en brindar argumentos para incentivar la compra del producto.
E28: El vendedor/a cerró la venta
E29: El vendedor/a ofreció y explicó los beneficios del servicio de entrega gratuita, tiempo de entrega, áreas de cobertura. | G29: No aplica, es un producto pequeño | I29: No aplica, es un producto pequeño
E30: El vendedor/a ofreció y explicó los beneficios del servicio de instalación garantizada. | F30: No aplica, no cuenta con instalación pero el vendedor si me explicó el proceso | G30: No aplica, es un producto pequeño | H30: No aplica, no tiene instalación, el producto es una heladera | I30: No aplica, es un producto pequeño
E31: El vendedor/a explicó los beneficios de la política de cambios y devoluciones. | F31: No habló de la política de cambios y devoluciones | G31: No me explicó nada sobre los cambios y devoluciones
B32: 0.2 | E32: El vendedor/a preguntó, si necesitaba algo más, o tuvo la capacidad/ habilidad de ofrecer productos ADICIONALES diferentes al que solicitó
E33: El vendedor/a consultó el método de pago y ofreció MINICUOTAS | G33: No me ofreció mini cuotas | I33: No me ofreció las mini cuotas
E34: El vendedor/a demostró actitud de servicio, amabilidad y cortesía en el trato
E35: En caso de interrupción durante la visita, el vendedor le pidió disculpas por la interrupción. | F35: No aplica, no hubo interrupción | H35: No aplica, no hubo interrupción | I35: No aplica, no hubo interrupción
E36: INFORMACIÓN SOBRE LA INSTALACIÓN
E37: El vendedor/a coordinó y programó la entrega a domicilio del producto
E38: El vendedor/a coordinó y programó la instalación del producto
E39: El vendedor/a informó y explicó los requisitos previos de instalación del producto
E40: DESPEDIDA
B41: 0.2 | E41: El vendedor/a le solicitó sus datos personales y en caso de no estar registrado en su sistema, lo registró | H41: No me pidieron mis datos para registrarme
E42: El vendedor/a lo dirigió a caja para efectuar el pago.
E43: El vendedor/a se despidió amablemente y lo invito a visitar nuevamente la tienda
E44: PRESENTACIÓN PERSONAL DEL VENDEDOR/A
B45: 0.1 | E45: El vendedor/a se encontraba con el uniforme de la empresa. | I45: Tenía una polera color beige y los demás vendedores camisa chapaca, no tenía ningún distintivo de Dismac. Los cajeros estaban uniformados, creo que era por el jueves de comadres
E46: El vendedor/a tenía buena presencia (El cabello no está en su rostro, está limpio y prolijo)
E47: ATENCIÓN EN CAJA
E48: ATENCIÓN EN CAJA
B49: 0.2 | E49: El cajero/a saludó amablemente. "Buenos días" "Buen día, en qué puedo ayudarle" "Cómo está"
B50: 0.4 | E50: El cajero/a respetó el orden de llegada.
E51: El cajero/a le comunicó sobre el monto a pagar y realizó el proceso de facturación (Pide NIT y explica la implementación de la facturación electrónica, es decir pide los datos al cliente, explica que la factura le llegará por correo o a su teléfono (opcional) y efectivamente la factura le llegó por uno de estos medios).
E52: El cajero/a entregó la garantía del producto o indicó que esta venía dentro de la caja del producto. (Aplica solo en caso de refrigeradores, cocinas, freezers, lavadoras, microondas y Aires Acondicionados)
B53: 0.2 | E53: El cajero/a lo dirigió o le indicó quien es el encargado de hacer la entrega
E54: El cajero/a lo atendió con rapidez en el cobro, facturación.
E55: El cajero agradecio la compra, se despidió amablemente "Hasta luego" "Que tenga un buen día" "Que le vaya bien" y lo invitó a visitar la tienda nuevamente
E56: INFORMACIÓN SOBRE LA ENTREGA E INSTALACIÓN DE PRODUCTOS
E57: El cajero/a validó la fecha de entrega a domicilio del producto
E58: El cajero/a validó la fecha de instalación del producto
E59: El cajero/a validó que el vendedor explicó los requisitos previos de instalacion del producto, que el cliente entiende estos requisitos, y el cajero entregó los requisitos impresos al cliente.
E60: El cajero informó y explicó al cliente que para cualquier cambio de horario que quiera realizar en la programación de la entrega o instalación debe llamar al número 800 10 2000
B61: 0.4 | E61: MINI CUOTAS - El cajero/a consultó el método de pago y ofreció MINICUOTAS
E62: PRESENTACIÓN PERSONAL DEL CAJERO
E63: El cajero/a se encontraba con el uniforme de la empresa.
E64: El cajero/a tenía buena presencia (El cabello no está en su rostro, está limpio y prolijo)
E65: ATENCIÓN POSTPAGO
E66: ENTREGA EN TIENDA
B67: 0.15 | E67: El vendedor/a mostró los accesorios con los que viene el producto | G67: No aplica, no cuenta con accesorios | I67: No aplica, no cuenta con accesorios
E68: El vendedor/a probó el producto
E69: El vendedor/a se despidió amablemente y lo invito a visitar nuevamente la tienda
E70: AMBIENTE DE LA TIENDA
E71: LIMPIEZA Y ORDEN
B72: 0.2 | E72: El interior de la tienda se encontraba limpio y en buenas condiciones (pisos, paredes y techo)
B73: 0.75 | E73: Los pasillos se encontraban libres y permitían la libre circulación
E74: Los productos se encontraban ordenados y limpios
E75: LETREROS Y SEÑALETICA
E76: Los productos cuentan con la cartelera o letreros que indican sus precios
B77: 0.25 | E77: Los letreros de promociones y la señalética eran visibles
E78: DELIVERY
E79: ENTREGA A DOMICILIO
B80: 0.05 | E80: El chofer se comunicó con el cliente por lo menos 30 minutos antes para confirmar la entrega
B81: 0.7 | E81: El producto llegó a su casa en el rango de tiempo indicado (No más de 24 Hr)
E82: El chofer dejó el producto dentro del inmueble y en el lugar solicitado por el cliente
E83: El producto llegó en perfecto estatodo sin daños estéticos
E84: DEVOLUCIÓN
E85: DEVOLUCIÓN EN TIENDA
B86: 0.3 | E86: El encargado/a lo saludó amablemente
B87: 0.1 | E87: El encargado/a escuchó atentamente, con paciencia y con interés
B88: 0.3 | E88: El encargado/a demostró una buena actitud ante su solicitud
E89: El encargado/a verificó el estado del producto, y determinó si cumple con la política de cambios y devoluciones
E90: El encargado/a hizo efectiva la devolución
E91: La atención por parte del encargado/a fue ágil y rápida.
E92: El encargado le brindó toda la información necesaria con respecto a la devolución (en caso de demora)
E93: MEDIDAS DE BIOSEGURIDAD
E94: Midieron su temperatura y proporcionaron alcohol líquido o en gel al ingresar a la sucursal
E95: Al ingresar la persona que controla verificó que el cliente tenga barbijo
E96: El personal de tienda, ¿estuvo con el barbijo puesto todo el tiempo
E97: En el sector de caja, contaban con alcohol líquido o en gel
E98: EXPERIENCIA EN EL SERVICIO
E99: ¿Qué rescata de la visita que realizó? es decir, ¿qué acciones positivas observó durante su visita? | F99: El personal fue muy amable; me explicó muchas cosas, estuvo atento y me enseñó a usar su página con paciencia. | G99: El ambiente y la infraestructura son muy buenos; la tienda es muy linda. | H99: Buen ambiente; la tienda es hermosa. | I99: La atención fue buena y rápida.
E100: ¿En qué debería mejorar esta sucursal de Dismac para brindar una mejor experiencia de compra a sus clientes? | F100: Renovar algunos carteles para resaltar más los detalles en el área de celulares. | G100: Los vendedores deberían tener un poco más de conocimiento sobre todos los productos. | H100: No me pidieron mis datos personales; deberían ampliar esta parte de la interacción. | I100: La música estaba muy fuerte en la tienda al momento de la compra; en la devolución ya no era tan estruendosa. Deberían regular el volumen.

Sheet Cumplimiento de objetivos
G2: Reporte Diciembre 2025 - Visitas encubiertas DISMAC
G3: Cumplimiento de objetivos mínimos
D6: INDICES GENERALES
AB8: Santa Cruz | AC8: La Paz | AD8: Cochabamba | AE8: DISMAC
AA9: Enero/ 2024 | AB9: ='Datos comparativos'!BA90 -> 0.96131998 | AC9: ='Datos comparativos'!BB90 -> 0.91131509 | AD9: ='Datos comparativos'!BC90 -> 0.9364321 | AE9: ='Datos comparativos'!BD90 -> 0.93635573
AA10: Febrero/ 2024 | AB10: ='Datos comparativos'!BA91 -> 0.9817448 | AC10: ='Datos comparativos'!BB91 -> 0.87008593 | AD10: ='Datos comparativos'!BC91 -> 0.93162102 | AE10: ='Datos comparativos'!BD91 -> 0.92781725
AA11: Marzo/ 2024 | AB11: ='Datos comparativos'!BA92 -> 0.92260335 | AC11: ='Datos comparativos'!BB92 -> 0.89537224 | AD11: ='Datos comparativos'!BC92 -> 0.89458492 | AE11: ='Datos comparativos'!BD92 -> 0.90418684
AA12: Abril/ 2024 | AB12: ='Datos comparativos'!BA93 -> 0.93813119 | AC12: ='Datos comparativos'!BB93 -> 0.87661982 | AD12: ='Datos comparativos'!BC93 -> 0.93077354 | AE12: ='Datos comparativos'!BD93 -> 0.91517485
AA13: Mayo/ 2024 | AB13: ='Datos comparativos'!BA94 -> 0.92699049 | AC13: ='Datos comparativos'!BB94 -> 0.92301128 | AD13: ='Datos comparativos'!BC94 -> 0.9510655 | AE13: ='Datos comparativos'!BD94 -> 0.93368909
AA14: Junio/ 2024 | AB14: ='Datos comparativos'!BA95 -> 0.96269902 | AC14: ='Datos comparativos'!BB95 -> 0.91203263 | AD14: ='Datos comparativos'!BC95 -> 0.93030154 | AE14: ='Datos comparativos'!BD95 -> 0.93501106
AA15: Julio/ 2024 | AB15: ='Datos comparativos'!BA96 -> 0.93858672 | AC15: ='Datos comparativos'!BB96 -> 0.90470248 | AD15: ='Datos comparativos'!BC96 -> 0.90113367 | AE15: ='Datos comparativos'!BD96 -> 0.91480762
AA16: Agosto/ 2024 | AB16: ='Datos comparativos'!BA97 -> 0.96298749 | AC16: ='Datos comparativos'!BB97 -> 0.91875151 | AD16: ='Datos comparativos'!BC97 -> 0.90941358 | AE16: ='Datos comparativos'!BD97 -> 0.93038419
AA17: Septiembre/ 2024 | AB17: ='Datos comparativos'!BA98 -> 0.90790989 | AC17: ='Datos comparativos'!BB98 -> 0.93928682 | AD17: ='Datos comparativos'!BC98 -> 0.93926576 | AE17: ='Datos comparativos'!BD98 -> 0.92882082
AA18: Octubre/ 2024 | AB18: ='Datos comparativos'!BA99 -> 0.93351736 | AC18: ='Datos comparativos'!BB99 -> 0.92613369 | AD18: ='Datos comparativos'!BC99 -> 0.99201426 | AE18: ='Datos comparativos'!BD99 -> 0.9505551
AA19: Noviembre/ 2024 | AB19: ='Datos comparativos'!BA100 -> 0.97614066 | AC19: ='Datos comparativos'!BB100 -> 0.9405796 | AD19: ='Datos comparativos'!BC100 -> 0.93158356 | AE19: ='Datos comparativos'!BD100 -> 0.94943461
AA20: Diciembre/ 2024 | AB20: ='Datos comparativos'!BA101 -> 0.95994496 | AC20: ='Datos comparativos'!BB101 -> 0.96838175 | AD20: ='Datos comparativos'!BC101 -> 0.85589997 | AE20: ='Datos comparativos'!BD101 -> 0.92807556
... AA31: Noviembre/ 2025 | AB31: ='Datos comparativos'!BA112 -> 0.94151215 | AC31: ='Datos comparativos'!BB112 -> 0.86755683 | AD31: ='Datos comparativos'!BC112 -> 0.91546948 | AE31: ='Datos comparativos'!BD112 -> 0.90817949
AA32: Diciembre/ 2025 | AB32: ='Datos comparativos'!BA114 -> 0.92665767 | AC32: ='Datos comparativos'!BB114 -> 0.80846731 | AD32: ='Datos comparativos'!BC114 -> 0.90511423 | AE32: ='Datos comparativos'!BD114 -> 0.88007974
D40: ÍNDICE GENERAL - SANTA CRUZ
B42: Benchmark | C42: 0.85 | AB42: 39 | AC42: 79 | AD42: 119 | AE42: 159 | AF42: 199 | AG42: 239 | AH42: 279
AB44: SANTA CRUZ
AB45: ÍNDICES GENERALES | AC45: Atención del vendedor | AD45: Atención en caja | AE45: Atención post pago | AF45: Ambiente de la tienda | AG45: Delivery | AH45: Devolución | AI45: Medidas de bioseguridad
Z46: 2024 | AA46: Enero/ 2024 | AB46: =+'Datos comparativos'!BA90 -> 0.96131998 | AC46: =+'Datos comparativos'!BA199 -> 0.94966647 | AD46: =+'Datos comparativos'!BA308 -> 0.95 | AE46: =+'Datos comparativos'!BA417 -> 0.96657 | AF46: =+'Datos comparativos'!BA526 -> 0.97916667 | AG46: =+'Datos comparativos'!BA635 -> 1 | AH46: =+'Datos comparativos'!BA744 -> 1
Z47: 2024 | AA47: Febrero/ 2024 | AB47: =+'Datos comparativos'!BA91 -> 0.9817448 | AC47: =+'Datos comparativos'!BA200 -> 0.96387208 | AD47: =+'Datos comparativos'!BA309 -> 0.99404762 | AE47: =+'Datos comparativos'!BA418 -> 1 | AF47: =+'Datos comparativos'!BA527 -> 0.99305556 | AG47: =+'Datos comparativos'!BA636 -> 1 | AH47: =+'Datos comparativos'!BA745 -> 1
Z48: 2024 | AA48: Marzo/ 2024 | AB48: =+'Datos comparativos'!BA92 -> 0.92260335 | AC48: =+'Datos comparativos'!BA201 -> 0.87923375 | AD48: =+'Datos comparativos'!BA310 -> 0.94166667 | AE48: =+'Datos comparativos'!BA419 -> 0.95 | AF48: =+'Datos comparativos'!BA528 -> 0.95138889 | AG48: =+'Datos comparativos'!BA637 -> 1 | AH48: =+'Datos comparativos'!BA746 -> 1
Z49: 2024 | AA49: Abril/ 2024 | AB49: =+'Datos comparativos'!BA93 -> 0.93813119 | AC49: =+'Datos comparativos'!BA202 -> 0.94087555 | AD49: =+'Datos comparativos'!BA311 -> 0.93928571 | AE49: =+'Datos comparativos'!BA420 -> 0.89991 | AF49: =+'Datos comparativos'!BA529 -> 0.96527778 | AG49: =+'Datos comparativos'!BA638 -> 0.875 | AH49: =+'Datos comparativos'!BA747 -> 1
Z50: 2024 | AA50: Mayo/ 2024 | AB50: =+'Datos comparativos'!BA94 -> 0.92699049 | AC50: =+'Datos comparativos'!BA203 -> 0.87532749 | AD50: =+'Datos comparativos'!BA312 -> 0.98363095 | AE50: =+'Datos comparativos'!BA421 -> 0.93324 | AF50: =+'Datos comparativos'!BA530 -> 0.93402778 | AG50: =+'Datos comparativos'!BA639 -> 1 | AH50: =+'Datos comparativos'!BA748 -> 1
Z51: 2024 | AA51: Junio/ 2024 | AB51: =+'Datos comparativos'!BA95 -> 0.96269902 | AC51: =+'Datos comparativos'!BA204 -> 0.92145302 | AD51: =+'Datos comparativos'!BA313 -> 1 | AE51: =+'Datos comparativos'!BA422 -> 0.99993 | AF51: =+'Datos comparativos'!BA531 -> 0.97916667 | AG51: =+'Datos comparativos'!BA640 -> 1 | AH51: =+'Datos comparativos'!BA749 -> 1
Z52: 2024 | AA52: Julio/ 2024 | AB52: =+'Datos comparativos'!BA96 -> 0.93858672 | AC52: =+'Datos comparativos'!BA205 -> 0.94679258 | AD52: =+'Datos comparativos'!BA314 -> 0.86458333 | AE52: =+'Datos comparativos'!BA423 -> 0.94996 | AF52: =+'Datos comparativos'!BA532 -> 0.96875 | AG52: =+'Datos comparativos'!BA641 -> 1 | AH52: =+'Datos comparativos'!BA750 -> 1
Z53: 2024 | AA53: Agosto/ 2024 | AB53: =+'Datos comparativos'!BA97 -> 0.96298749 | AC53: =+'Datos comparativos'!BA206 -> 0.95065055 | AD53: =+'Datos comparativos'!BA315 -> 0.9547619 | AE53: =+'Datos comparativos'!BA424 -> 1 | AF53: =+'Datos comparativos'!BA533 -> 0.96527778 | AG53: =+'Datos comparativos'!BA642 -> 1 | AH53: =+'Datos comparativos'!BA751 -> 1
Z54: 2024 | AA54: Septiembre/ 2024 | AB54: =+'Datos comparativos'!BA98 -> 0.90790989 | AC54: =+'Datos comparativos'!BA207 -> 0.90618713 | AD54: =+'Datos comparativos'!BA316 -> 0.91666667 | AE54: =+'Datos comparativos'!BA425 -> 1 | AF54: =+'Datos comparativos'!BA534 -> 0.78125 | AG54: =+'Datos comparativos'!BA643 -> 1 | AH54: =+'Datos comparativos'!BA752 -> 1
Z55: 2024 | AA55: Octubre/ 2024. | AB55: =+'Datos comparativos'!BA99 -> 0.93351736 | AC55: =+'Datos comparativos'!BA208 -> 0.90752467 | AD55: =+'Datos comparativos'!BA317 -> 0.9672619 | AE55: =+'Datos comparativos'!BA426 -> 1 | AF55: =+'Datos comparativos'!BA535 -> 0.86805556 | AG55: =+'Datos comparativos'!BA644 -> 1 | AH55: =+'Datos comparativos'!BA753 -> 1
Z56: 2024 | AA56: Noviembre/ 2024 | AB56: =+'Datos comparativos'!BA100 -> 0.97614066 | AC56: =+'Datos comparativos'!BA209 -> 0.95482619 | AD56: =+'Datos comparativos'!BA318 -> 0.98363095 | AE56: =+'Datos comparativos'!BA427 -> 0.9999 | AF56: =+'Datos comparativos'!BA536 -> 0.99305556 | AG56: =+'Datos comparativos'!BA645 -> 1 | AH56: =+'Datos comparativos'!BA754 -> 1
Z57: 2024 | AA57: Diciembre/ 2024 | AB57: =+'Datos comparativos'!BA101 -> 0.95994496 | AC57: =+'Datos comparativos'!BA210 -> 0.96478417 | AD57: =+'Datos comparativos'!BA319 -> 0.97222222 | AE57: =+'Datos comparativos'!BA428 -> 0.9999 | AF57: =+'Datos comparativos'!BA537 -> 0.88541667 | AG57: =+'Datos comparativos'!BA646 -> 1 | AH57: =+'Datos comparativos'!BA755 -> 0.98611111
... Z68: 2025 | AA68: Noviembre/ 2025 | AB68: =+'Datos comparativos'!BA112 -> 0.94151215 | AC68: =+'Datos comparativos'!BA221 -> 0.89837591 | AD68: =+'Datos comparativos'!BA330 -> 0.9625 | AE68: =+'Datos comparativos'!BA439 -> 0.99992 | AF68: =+'Datos comparativos'!BA548 -> 0.96527778 | AG68: =+'Datos comparativos'!BA657 -> 0.875 | AH68: =+'Datos comparativos'!BA766 -> 0.98611111
Z69: 2025 | AA69: Diciembre/ 2025 | AB69: =+'Datos comparativos'!BA114 -> 0.92665767 | AC69: =+'Datos comparativos'!BA223 -> 0.88597891 | AD69: =+'Datos comparativos'!BA332 -> 0.91153846 | AE69: =+'Datos comparativos'!BA441 -> 0.95445455 | AF69: =+'Datos comparativos'!BA550 -> 0.99358974 | AG69: =+'Datos comparativos'!BA659 -> 1 | AH69: =+'Datos comparativos'!BA768 -> 1
D75: ÍNDICE GENERAL - LA PAZ
AB76: 39 | AC76: 79 | AD76: 119 | AE76: 159 | AF76: 199 | AG76: 239 | AH76: 279
AB78: LA PAZ
AB79: ÍNDICES GENERALES | AC79: Atención del vendedor | AD79: Atención en caja | AE79: Atención post pago | AF79: Ambiente de la tienda | AG79: Delivery | AH79: Devolución | AI79: Medidas de bioseguridad
Z80: 2024 | AA80: Enero/ 2024 | AB80: =+'Datos comparativos'!BB90 -> 0.91131509 | AC80: =+'Datos comparativos'!BB199 -> 0.87700521 | AD80: =+'Datos comparativos'!BB308 -> 0.86458333 | AE80: =+'Datos comparativos'!BB417 -> 0.9999 | AF80: =+'Datos comparativos'!BB526 -> 0.95833333 | AG80: =+'Datos comparativos'!BB635 -> 0.75 | AH80: =+'Datos comparativos'!BB744 -> 1
Z81: 2024 | AA81: Febrero/ 2024 | AB81: =+'Datos comparativos'!BB91 -> 0.87008593 | AC81: =+'Datos comparativos'!BB200 -> 0.84286918 | AD81: =+'Datos comparativos'!BB309 -> 0.81666667 | AE81: =+'Datos comparativos'!BB418 -> 0.91658333 | AF81: =+'Datos comparativos'!BB527 -> 0.91666667 | AG81: =+'Datos comparativos'!BB636 -> 1 | AH81: =+'Datos comparativos'!BB745 -> 0.975
Z82: 2024 | AA82: Marzo/ 2024 | AB82: =+'Datos comparativos'!BB92 -> 0.89537224 | AC82: =+'Datos comparativos'!BB201 -> 0.87508441 | AD82: =+'Datos comparativos'!BB310 -> 0.93333333 | AE82: =+'Datos comparativos'!BB419 -> 0.89992 | AF82: =+'Datos comparativos'!BB528 -> 0.85119048 | AG82: =+'Datos comparativos'!BB637 -> 1 | AH82: =+'Datos comparativos'!BB746 -> 0.97619048
Z83: 2024 | AA83: Abril/ 2024 | AB83: =+'Datos comparativos'!BB93 -> 0.87661982 | AC83: =+'Datos comparativos'!BB202 -> 0.8612878 | AD83: =+'Datos comparativos'!BB311 -> 0.88928571 | AE83: =+'Datos comparativos'!BB420 -> 0.79994 | AF83: =+'Datos comparativos'!BB529 -> 0.875 | AG83: =+'Datos comparativos'!BB638 -> 1 | AH83: =+'Datos comparativos'!BB747 -> 0.97619048
Z84: 2024 | AA84: Mayo/ 2024 | AB84: =+'Datos comparativos'!BB94 -> 0.92301128 | AC84: =+'Datos comparativos'!BB203 -> 0.85298656 | AD84: =+'Datos comparativos'!BB312 -> 0.96428571 | AE84: =+'Datos comparativos'!BB421 -> 0.99992 | AF84: =+'Datos comparativos'!BB530 -> 0.96428571 | AG84: =+'Datos comparativos'!BB639 -> 0.625 | AH84: =+'Datos comparativos'!BB748 -> 1
Z85: 2024 | AA85: Junio/ 2024 | AB85: =+'Datos comparativos'!BB95 -> 0.91203263 | AC85: =+'Datos comparativos'!BB204 -> 0.86127021 | AD85: =+'Datos comparativos'!BB313 -> 0.88622449 | AE85: =+'Datos comparativos'!BB422 -> 0.9999 | AF85: =+'Datos comparativos'!BB531 -> 0.98809524 | AG85: =+'Datos comparativos'!BB640 -> 1 | AH85: =+'Datos comparativos'!BB749 -> 1
Z86: 2024 | AA86: Julio/ 2024 | AB86: =+'Datos comparativos'!BB96 -> 0.90470248 | AC86: =+'Datos comparativos'!BB205 -> 0.92188265 | AD86: =+'Datos comparativos'!BB314 -> 0.81666667 | AE86: =+'Datos comparativos'!BB423 -> 0.9999 | AF86: =+'Datos comparativos'!BB532 -> 0.86904762 | AG86: =+'Datos comparativos'!BB641 -> 0.875 | AH86: =+'Datos comparativos'!BB750 -> 1
Z87: 2024 | AA87: Agosto/ 2024 | AB87: =+'Datos comparativos'!BB97 -> 0.91875151 | AC87: =+'Datos comparativos'!BB206 -> 0.92676102 | AD87: =+'Datos comparativos'!BB315 -> 0.88231293 | AE87: =+'Datos comparativos'!BB424 -> 0.99992 | AF87: =+'Datos comparativos'!BB533 -> 0.85714286 | AG87: =+'Datos comparativos'!BB642 -> 1 | AH87: =+'Datos comparativos'!BB751 -> 1
Z88: 2024 | AA88: Septiembre/ 2024 | AB88: =+'Datos comparativos'!BB98 -> 0.93928682 | AC88: =+'Datos comparativos'!BB207 -> 0.94982864 | AD88: =+'Datos comparativos'!BB316 -> 0.89591837 | AE88: =+'Datos comparativos'!BB425 -> 0.99994 | AF88: =+'Datos comparativos'!BB534 -> 0.89880952 | AG88: =+'Datos comparativos'!BB643 -> 0.875 | AH88: =+'Datos comparativos'!BB752 -> 1
Z89: 2024 | AA89: Octubre/ 2024. | AB89: =+'Datos comparativos'!BB99 -> 0.92613369 | AC89: =+'Datos comparativos'!BB208 -> 0.93213782 | AD89: =+'Datos comparativos'!BB317 -> 0.88333333 | AE89: =+'Datos comparativos'!BB426 -> 0.99992 | AF89: =+'Datos comparativos'!BB535 -> 0.88095238 | AG89: =+'Datos comparativos'!BB644 -> 0.875 | AH89: =+'Datos comparativos'!BB753 -> 1
Z90: 2024 | AA90: Noviembre/ 2024 | AB90: =+'Datos comparativos'!BB100 -> 0.9405796 | AC90: =+'Datos comparativos'!BB209 -> 0.92981816 | AD90: =+'Datos comparativos'!BB318 -> 0.96190476 | AE90: =+'Datos comparativos'!BB427 -> 0.99994 | AF90: =+'Datos comparativos'!BB536 -> 0.86904762 | AG90: =+'Datos comparativos'!BB645 -> 1 | AH90: =+'Datos comparativos'!BB754 -> 1
Z91: 2024 | AA91: Diciembre/ 2024 | AB91: =+'Datos comparativos'!BB101 -> 0.96838175 | AC91: =+'Datos comparativos'!BB210 -> 0.94916704 | AD91: =+'Datos comparativos'!BB319 -> 0.98265306 | AE91: =+'Datos comparativos'!BB428 -> 0.9999 | AF91: =+'Datos comparativos'!BB537 -> 0.95833333 | AG91: =+'Datos comparativos'!BB646 -> 1 | AH91: =+'Datos comparativos'!BB755 -> 1
... Z102: 2025 | AA102: Noviembre/ 2025 | AB102: =+'Datos comparativos'!BB112 -> 0.86755683 | AC102: =+'Datos comparativos'!BB221 -> 0.78720568 | AD102: =+'Datos comparativos'!BB330 -> 0.86904762 | AE102: =+'Datos comparativos'!BB439 -> 0.9999 | AF102: =+'Datos comparativos'!BB548 -> 0.94047619 | AG102: =+'Datos comparativos'!BB657 -> 1 | AH102: =+'Datos comparativos'!BB766 -> 1
Z103: 2025 | AA103: Diciembre/ 2025 | AB103: =+'Datos comparativos'!BB114 -> 0.80846731 | AC103: =+'Datos comparativos'!BB223 -> 0.75184435 | AD103: =+'Datos comparativos'!BB332 -> 0.82857143 | AE103: =+'Datos comparativos'!BB441 -> 0.93326 | AF103: =+'Datos comparativos'!BB550 -> 0.76190476 | AG103: =+'Datos comparativos'!BB659 -> 1 | AH103: =+'Datos comparativos'!BB768 -> 0.97619048
D112: ÍNDICE GENERAL - COCHABAMBA
AB115: COCHABAMBA
AB116: ÍNDICES GENERALES | AC116: Atención del vendedor | AD116: Atención en caja | AE116: Atención post pago | AF116: Ambiente de la tienda | AG116: Delivery | AH116: Devolución | AI116: Medidas de bioseguridad
Z117: 2024 | AA117: Enero/ 2024 | AB117: =+'Datos comparativos'!BC90 -> 0.9364321 | AC117: =+'Datos comparativos'!BC199 -> 0.92962092 | AD117: =+'Datos comparativos'!BC308 -> 0.93333333 | AE117: =+'Datos comparativos'!BC417 -> 0.9999 | AF117: =+'Datos comparativos'!BC526 -> 0.88888889 | AG117: =+'Datos comparativos'!BC635 -> 1 | AH117: =+'Datos comparativos'!BC744 -> 1
Z118: 2024 | AA118: Febrero/ 2024 | AB118: =+'Datos comparativos'!BC91 -> 0.93162102 | AC118: =+'Datos comparativos'!BC200 -> 0.8867021 | AD118: =+'Datos comparativos'!BC309 -> 0.91904762 | AE118: =+'Datos comparativos'!BC418 -> 0.9999 | AF118: =+'Datos comparativos'!BC527 -> 1 | AG118: =+'Datos comparativos'!BC636 -> 1 | AH118: =+'Datos comparativos'!BC745 -> 1
Z119: 2024 | AA119: Marzo/ 2024 | AB119: =+'Datos comparativos'!BC92 -> 0.89458492 | AC119: =+'Datos comparativos'!BC201 -> 0.93816806 | AD119: =+'Datos comparativos'!BC310 -> 0.75 | AE119: =+'Datos comparativos'!BC419 -> 0.66665 | AF119: =+'Datos comparativos'!BC528 -> 1 | AG119: =+'Datos comparativos'!BC637 -> 1 | AH119: =+'Datos comparativos'!BC746 -> 1
Z120: 2024 | AA120: Abril/ 2024 | AB120: =+'Datos comparativos'!BC93 -> 0.93077354 | AC120: =+'Datos comparativos'!BC202 -> 0.8597173 | AD120: =+'Datos comparativos'!BC311 -> 0.97777778 | AE120: =+'Datos comparativos'!BC420 -> 1 | AF120: =+'Datos comparativos'!BC529 -> 1 | AG120: =+'Datos comparativos'!BC638 -> 1 | AH120: =+'Datos comparativos'!BC747 -> 1
Z121: 2024 | AA121: Mayo/ 2024 | AB121: =+'Datos comparativos'!BC94 -> 0.9510655 | AC121: =+'Datos comparativos'!BC203 -> 0.9260728 | AD121: =+'Datos comparativos'!BC312 -> 0.96666667 | AE121: =+'Datos comparativos'!BC421 -> 0.99995 | AF121: =+'Datos comparativos'!BC530 -> 0.94444444 | AG121: =+'Datos comparativos'!BC639 -> 1 | AH121: =+'Datos comparativos'!BC748 -> 1
Z122: 2024 | AA122: Junio/ 2024 | AB122: =+'Datos comparativos'!BC95 -> 0.93030154 | AC122: =+'Datos comparativos'!BC204 -> 0.88649097 | AD122: =+'Datos comparativos'!BC313 -> 0.95555556 | AE122: =+'Datos comparativos'!BC422 -> 0.99995 | AF122: =+'Datos comparativos'!BC531 -> 0.94444444 | AG122: =+'Datos comparativos'!BC640 -> 1 | AH122: =+'Datos comparativos'!BC749 -> 1
Z123: 2024 | AA123: Julio/ 2024 | AB123: =+'Datos comparativos'!BC96 -> 0.90113367 | AC123: =+'Datos comparativos'!BC205 -> 0.88051238 | AD123: =+'Datos comparativos'!BC314 -> 0.86944444 | AE123: =+'Datos comparativos'!BC423 -> 0.99995 | AF123: =+'Datos comparativos'!BC532 -> 0.94444444 | AG123: =+'Datos comparativos'!BC641 -> 1 | AH123: =+'Datos comparativos'!BC750 -> 0.94444444
Z124: 2024 | AA124: Agosto/ 2024 | AB124: =+'Datos comparativos'!BC97 -> 0.90941358 | AC124: =+'Datos comparativos'!BC206 -> 0.83876138 | AD124: =+'Datos comparativos'!BC315 -> 0.92380952 | AE124: =+'Datos comparativos'!BC424 -> 0.9999 | AF124: =+'Datos comparativos'!BC533 -> 1 | AG124: =+'Datos comparativos'!BC642 -> 1 | AH124: =+'Datos comparativos'!BC751 -> 1
Z125: 2024 | AA125: Septiembre/ 2024 | AB125: =+'Datos comparativos'!BC98 -> 0.93926576 | AC125: =+'Datos comparativos'!BC207 -> 0.95653595 | AD125: =+'Datos comparativos'!BC316 -> 0.90952381 | AE125: =+'Datos comparativos'!BC425 -> 0.99995 | AF125: =+'Datos comparativos'!BC534 -> 0.91666667 | AG125: =+'Datos comparativos'!BC643 -> 1 | AH125: =+'Datos comparativos'!BC752 -> 0.94444444
Z126: 2024 | AA126: Octubre/ 2024. | AB126: =+'Datos comparativos'!BC99 -> 0.99201426 | AC126: =+'Datos comparativos'!BC208 -> 0.98098633 | AD126: =+'Datos comparativos'!BC317 -> 1 | AE126: =+'Datos comparativos'!BC426 -> 1 | AF126: =+'Datos comparativos'!BC535 -> 1 | AG126: =+'Datos comparativos'!BC644 -> 1 | AH126: =+'Datos comparativos'!BC753 -> 1
Z127: 2024 | AA127: Noviembre/ 2024 | AB127: =+'Datos comparativos'!BC100 -> 0.93158356 | AC127: =+'Datos comparativos'!BC209 -> 0.94428886 | AD127: =+'Datos comparativos'!BC318 -> 0.82857143 | AE127: =+'Datos comparativos'!BC427 -> 0.9999 | AF127: =+'Datos comparativos'!BC536 -> 1 | AG127: =+'Datos comparativos'!BC645 -> 0 | AH127: =+'Datos comparativos'!BC754 -> 1
Z128: 2024 | AA128: Diciembre/ 2024 | AB128: =+'Datos comparativos'!BC101 -> 0.85589997 | AC128: =+'Datos comparativos'!BC210 -> 0.828246 | AD128: =+'Datos comparativos'!BC319 -> 0.72777778 | AE128: =+'Datos comparativos'!BC428 -> 0.9999 | AF128: =+'Datos comparativos'!BC537 -> 0.97222222 | AG128: =+'Datos comparativos'!BC646 -> 1 | AH128: =+'Datos comparativos'!BC755 -> 1
... Z139: 2025 | AA139: Noviembre/ 2025 | AB139: =+'Datos comparativos'!BC112 -> 0.91546948 | AC139: =+'Datos comparativos'!BC221 -> 0.86861185 | AD139: =+'Datos comparativos'!BC330 -> 0.86904762 | AE139: =+'Datos comparativos'!BC439 -> 0.9999 | AF139: =+'Datos comparativos'!BC548 -> 1 | AG139: =+'Datos comparativos'!BC657 -> 1 | AH139: =+'Datos comparativos'!BC766 -> 1
Z140: 2025 | AA140: Diciembre/ 2025 | AB140: =+'Datos comparativos'!BC114 -> 0.90511423 | AC140: =+'Datos comparativos'!BC223 -> 0.8615345 | AD140: =+'Datos comparativos'!BC332 -> 0.93333333 | AE140: =+'Datos comparativos'!BC441 -> 0.74995 | AF140: =+'Datos comparativos'!BC550 -> 1 | AG140: =+'Datos comparativos'!BC659 -> 1 | AH140: =+'Datos comparativos'!BC768 -> 1
D148: ÍNDICE GENERAL - COMPETENCIA
AB152: COMPETENCIA
AB153: ÍNDICES GENERALES | AC153: Atención del vendedor | AD153: Atención en caja | AE153: Atención post pago | AF153: Ambiente de la tienda | AG153: Delivery | AH153: Devolución
Z160: 2020 | AA160: Febrero/2020 | AB160: =+'Datos comparativos'!BE46 -> 0.70625 | AC160: =+'Datos comparativos'!BE155 -> 0.77708333 | AD160: =+'Datos comparativos'!BE264 -> n/a | AE160: =+'Datos comparativos'!BE373 -> n/a | AF160: =+'Datos comparativos'!BE482 -> 0.6 | AG160: =+'Datos comparativos'!BE591 -> n/a | AH160: =+'Datos comparativos'!BE700 -> n/a
Z161: 2020 | AA161: Marzo/2020 | AB161: =+'Datos comparativos'!BE114 -> n/a | AC161: =+'Datos comparativos'!BE223 -> n/a | AD161: =+'Datos comparativos'!BE332 -> n/a | AE161: =+'Datos comparativos'!BE441 -> n/a | AF161: =+'Datos comparativos'!BE550 -> n/a | AG161: =+'Datos comparativos'!BE659 -> n/a | AH161: =+'Datos comparativos'!BE768 -> n/a
D177: ATENCIÓN DEL VENDEDOR
AB181: SANTA CRUZ | AP181: LA PAZ | AX181: COCHABAMBA
AB182: Cristóbal de Mendoza #1055 | AC182: Doble Vía entre 5to y 6to anillo | AD182: Isabel 1 | AE182: Pampa de la Isla | AF182: Show Room (P.I.) | AG182: Viedma | AH182: Villa 1ro de Mayo | AI182: 4to Anillo e Isuto | AJ182: Plan 3000 | AK182: Omar Chávez | AL182: Av. Cristo Redentor | AM182: Av. Santos Dumont | AN182: Doble Vía km13 | AO182: Isabel 2 | AP182: Calacoto Av. Ballivian 1305 | AQ182: Eloy Salmon 1053 | AR182: El Alto 4 | AS182: Socabaya | AT182: Obrajes | AU182: Multicine Río Seco | AV182: El Alto Satélite | AW182: El Alto Cruce Villa Adela | AX182: Av. Pando # 1377 | AY182: Ayacucho 309 | AZ182: Av. América #459 | BA182: Quillacollo
AA183: Enero/ 2024 | AB183: ='Datos comparativos'!H199 -> 1 | AC183: ='Datos comparativos'!I199 -> 0.95588235 | AD183: ='Datos comparativos'!K199 -> 1 | AE183: ='Datos comparativos'!O199 -> 1 | AF183: ='Datos comparativos'!Q199 -> 0.97849462 | AG183: ='Datos comparativos'!R199 -> n/a | AH183: ='Datos comparativos'!S199 -> 1 | AI183: ='Datos comparativos'!T199 -> 0.98266254 | AJ183: ='Datos comparativos'!V199 -> 1 | AK183: ='Datos comparativos'!W199 -> 0.63524252 | AL183: ='Datos comparativos'!X199 -> 0.98513932 | AM183: ='Datos comparativos'!Y199 -> 0.8969007 | AN183: ='Datos comparativos'!Z199 -> n/a | AO183: ='Datos comparativos'!AA199 -> n/a | AP183: ='Datos comparativos'!AB199 -> 0.77261227 | AQ183: ='Datos comparativos'!AC199 -> 0.69284056 | AR183: ='Datos comparativos'!AD199 -> 0.79206199 | AS183: ='Datos comparativos'!AH199 -> 0.98333333 | AT183: ='Datos comparativos'!AI199 -> 0.89583333 | AU183: ='Datos comparativos'!AJ199 -> 1 | AV183: ='Datos comparativos'!AK199 -> 0.95098039 | AW183: ='Datos comparativos'!AL199 -> 0.92837977 | AX183: ='Datos comparativos'!AM199 -> n/a | AY183: ='Datos comparativos'!AO199 -> 0.92764706 | AZ183: ='Datos comparativos'!AP199 -> 0.90533333 | BA183: ='Datos comparativos'!AR199 -> 0.95588235
AA184: Febrero/ 2024 | AB184: ='Datos comparativos'!H200 -> 1 | AC184: ='Datos comparativos'!I200 -> 1 | AD184: ='Datos comparativos'!K200 -> 0.84912281 | AE184: ='Datos comparativos'!O200 -> 0.98039216 | AF184: ='Datos comparativos'!Q200 -> 1 | AG184: ='Datos comparativos'!R200 -> n/a | AH184: ='Datos comparativos'!S200 -> 1 | AI184: ='Datos comparativos'!T200 -> 1 | AJ184: ='Datos comparativos'!V200 -> 0.8311828 | AK184: ='Datos comparativos'!W200 -> 0.97264022 | AL184: ='Datos comparativos'!X200 -> 1 | AM184: ='Datos comparativos'!Y200 -> 1 | AN184: ='Datos comparativos'!Z200 -> n/a | AO184: ='Datos comparativos'!AA200 -> n/a | AP184: ='Datos comparativos'!AB200 -> 0.89733333 | AQ184: ='Datos comparativos'!AC200 -> 0.59391711 | AR184: ='Datos comparativos'!AD200 -> 0.94066667 | AS184: ='Datos comparativos'!AH200 -> 0.91087344 | AT184: ='Datos comparativos'!AI200 -> 0.7758467 | AU184: ='Datos comparativos'!AJ200 -> 0.78525999 | AV184: ='Datos comparativos'!AK200 -> 0.93085655 | AW184: ='Datos comparativos'!AL200 -> 0.90819964 | AX184: ='Datos comparativos'!AM200 -> n/a | AY184: ='Datos comparativos'!AO200 -> 0.88033333 | AZ184: ='Datos comparativos'!AP200 -> 0.77977296 | BA184: ='Datos comparativos'!AR200 -> 1
AA185: Marzo/ 2024 | AB185: ='Datos comparativos'!H201 -> 0.82953827 | AC185: ='Datos comparativos'!I201 -> 0.88680927 | AD185: ='Datos comparativos'!K201 -> 0.94571723 | AE185: ='Datos comparativos'!O201 -> 0.82643428 | AF185: ='Datos comparativos'!Q201 -> 0.87651515 | AG185: ='Datos comparativos'!R201 -> n/a | AH185: ='Datos comparativos'!S201 -> 0.942959 | AI185: ='Datos comparativos'!T201 -> 0.77365591 | AJ185: ='Datos comparativos'!V201 -> 0.807041 | AK185: ='Datos comparativos'!W201 -> 0.89784946 | AL185: ='Datos comparativos'!X201 -> 0.93972404 | AM185: ='Datos comparativos'!Y201 -> 0.98039216 | AN185: ='Datos comparativos'!Z201 -> n/a | AO185: ='Datos comparativos'!AA201 -> n/a | AP185: ='Datos comparativos'!AB201 -> 0.89572193 | AQ185: ='Datos comparativos'!AC201 -> 0.73255762 | AR185: ='Datos comparativos'!AD201 -> 0.90294118 | AS185: ='Datos comparativos'!AH201 -> 0.95933188 | AT185: ='Datos comparativos'!AI201 -> n/a | AU185: ='Datos comparativos'!AJ201 -> 0.86401012 | AV185: ='Datos comparativos'!AK201 -> 0.98039216 | AW185: ='Datos comparativos'!AL201 -> 0.79063596 | AX185: ='Datos comparativos'!AM201 -> n/a | AY185: ='Datos comparativos'!AO201 -> 0.84670232 | AZ185: ='Datos comparativos'!AP201 -> 1 | BA185: ='Datos comparativos'!AR201 -> 0.96780186
AA186: Abril/ 2024 | AB186: ='Datos comparativos'!H202 -> 0.98409091 | AC186: ='Datos comparativos'!I202 -> 0.92424242 | AD186: ='Datos comparativos'!K202 -> 0.88162672 | AE186: ='Datos comparativos'!O202 -> 0.76024955 | AF186: ='Datos comparativos'!Q202 -> 0.90196078 | AG186: ='Datos comparativos'!R202 -> n/a | AH186: ='Datos comparativos'!S202 -> 0.96268185 | AI186: ='Datos comparativos'!T202 -> 1 | AJ186: ='Datos comparativos'!V202 -> 1 | AK186: ='Datos comparativos'!W202 -> 1 | AL186: ='Datos comparativos'!X202 -> 1 | AM186: ='Datos comparativos'!Y202 -> 0.9527178 | AN186: ='Datos comparativos'!Z202 -> n/a | AO186: ='Datos comparativos'!AA202 -> n/a | AP186: ='Datos comparativos'!AB202 -> 0.86833105 | AQ186: ='Datos comparativos'!AC202 -> 0.9752322 | AR186: ='Datos comparativos'!AD202 -> 0.91733871 | AS186: ='Datos comparativos'!AH202 -> 0.86856061 | AT186: ='Datos comparativos'!AI202 -> n/a | AU186: ='Datos comparativos'!AJ202 -> 0.76047237 | AV186: ='Datos comparativos'!AK202 -> 0.67602496 | AW186: ='Datos comparativos'!AL202 -> 0.9630547 | AX186: ='Datos comparativos'!AM202 -> n/a | AY186: ='Datos comparativos'!AO202 -> 0.72175439 | AZ186: ='Datos comparativos'!AP202 -> 0.95588235 | BA186: ='Datos comparativos'!AR202 -> 0.90151515
AA187: Mayo/ 2024 | AB187: ='Datos comparativos'!H203 -> 0.97058824 | AC187: ='Datos comparativos'!I203 -> 0.60239651 | AD187: ='Datos comparativos'!K203 -> 0.83111954 | AE187: ='Datos comparativos'!O203 -> 0.85109649 | AF187: ='Datos comparativos'!Q203 -> 1 | AG187: ='Datos comparativos'!R203 -> n/a | AH187: ='Datos comparativos'!S203 -> 1 | AI187: ='Datos comparativos'!T203 -> 0.92424242 | AJ187: ='Datos comparativos'!V203 -> 0.94190269 | AK187: ='Datos comparativos'!W203 -> 0.88368984 | AL187: ='Datos comparativos'!X203 -> 0.72682709 | AM187: ='Datos comparativos'!Y203 -> 0.9456328 | AN187: ='Datos comparativos'!Z203 -> n/a | AO187: ='Datos comparativos'!AA203 -> n/a | AP187: ='Datos comparativos'!AB203 -> 0.86233333 | AQ187: ='Datos comparativos'!AC203 -> 0.89469697 | AR187: ='Datos comparativos'!AD203 -> 0.82352941 | AS187: ='Datos comparativos'!AH203 -> 0.82085561 | AT187: ='Datos comparativos'!AI203 -> n/a | AU187: ='Datos comparativos'!AJ203 -> 0.76381462 | AV187: ='Datos comparativos'!AK203 -> 0.82301342 | AW187: ='Datos comparativos'!AL203 -> 0.98266254 | AX187: ='Datos comparativos'!AM203 -> n/a | AY187: ='Datos comparativos'!AO203 -> 0.87254902 | AZ187: ='Datos comparativos'!AP203 -> 0.92438596 | BA187: ='Datos comparativos'!AR203 -> 0.98128342
AA188: Junio/ 2024 | AB188: ='Datos comparativos'!H204 -> 0.91208096 | AC188: ='Datos comparativos'!I204 -> 0.78938172 | AD188: ='Datos comparativos'!K204 -> 0.8573975 | AE188: ='Datos comparativos'!O204 -> 0.98039216 | AF188: ='Datos comparativos'!Q204 -> 0.98266254 | AG188: ='Datos comparativos'!R204 -> n/a | AH188: ='Datos comparativos'!S204 -> 0.92392157 | AI188: ='Datos comparativos'!T204 -> 0.93582888 | AJ188: ='Datos comparativos'!V204 -> 0.93787879 | AK188: ='Datos comparativos'!W204 -> 0.90386997 | AL188: ='Datos comparativos'!X204 -> 0.89304813 | AM188: ='Datos comparativos'!Y204 -> 0.98588235 | AN188: ='Datos comparativos'!Z204 -> n/a | AO188: ='Datos comparativos'!AA204 -> n/a | AP188: ='Datos comparativos'!AB204 -> 0.91599587 | AQ188: ='Datos comparativos'!AC204 -> 0.85729847 | AR188: ='Datos comparativos'!AD204 -> 0.7479902 | AS188: ='Datos comparativos'!AH204 -> 0.82345833 | AT188: ='Datos comparativos'!AI204 -> n/a | AU188: ='Datos comparativos'!AJ204 -> 0.88862745 | AV188: ='Datos comparativos'!AK204 -> 0.83745098 | AW188: ='Datos comparativos'!AL204 -> 0.95807018 | AX188: ='Datos comparativos'!AM204 -> n/a | AY188: ='Datos comparativos'!AO204 -> 0.85856935 | AZ188: ='Datos comparativos'!AP204 -> 0.92726123 | BA188: ='Datos comparativos'!AR204 -> 0.87364232
AA189: Julio/ 2024 | AB189: ='Datos comparativos'!H205 -> 0.98039216 | AC189: ='Datos comparativos'!I205 -> 1 | AD189: ='Datos comparativos'!K205 -> 0.92726123 | AE189: ='Datos comparativos'!O205 -> 0.98039216 | AF189: ='Datos comparativos'!Q205 -> 1 | AG189: ='Datos comparativos'!R205 -> n/a | AH189: ='Datos comparativos'!S205 -> 0.8570525 | AI189: ='Datos comparativos'!T205 -> 1 | AJ189: ='Datos comparativos'!V205 -> 0.93627451 | AK189: ='Datos comparativos'!W205 -> 0.87729618 | AL189: ='Datos comparativos'!X205 -> 0.90876028 | AM189: ='Datos comparativos'!Y205 -> 0.96627451 | AN189: ='Datos comparativos'!Z205 -> n/a | AO189: ='Datos comparativos'!AA205 -> n/a | AP189: ='Datos comparativos'!AB205 -> 1 | AQ189: ='Datos comparativos'!AC205 -> 0.95596491 | AR189: ='Datos comparativos'!AD205 -> 1 | AS189: ='Datos comparativos'!AH205 -> 0.89215686 | AT189: ='Datos comparativos'!AI205 -> n/a | AU189: ='Datos comparativos'!AJ205 -> 1 | AV189: ='Datos comparativos'!AK205 -> 0.86692466 | AW189: ='Datos comparativos'!AL205 -> 0.73813209 | AX189: ='Datos comparativos'!AM205 -> n/a | AY189: ='Datos comparativos'!AO205 -> 0.81883333 | AZ189: ='Datos comparativos'!AP205 -> 0.98039216 | BA189: ='Datos comparativos'!AR205 -> 0.84231166
AA190: Agosto/ 2024 | AB190: ='Datos comparativos'!H206 -> 0.94652406 | AC190: ='Datos comparativos'!I206 -> 0.92438596 | AD190: ='Datos comparativos'!K206 -> 0.84135472 | AE190: ='Datos comparativos'!O206 -> 0.9630547 | AF190: ='Datos comparativos'!Q206 -> 0.98039216 | AG190: ='Datos comparativos'!R206 -> n/a | AH190: ='Datos comparativos'!S206 -> 0.98266254 | AI190: ='Datos comparativos'!T206 -> 0.94980392 | AJ190: ='Datos comparativos'!V206 -> 0.98 | AK190: ='Datos comparativos'!W206 -> 0.93085655 | AL190: ='Datos comparativos'!X206 -> 0.98039216 | AM190: ='Datos comparativos'!Y206 -> 0.98266254 | AN190: ='Datos comparativos'!Z206 -> n/a | AO190: ='Datos comparativos'!AA206 -> n/a | AP190: ='Datos comparativos'!AB206 -> 0.97333333 | AQ190: ='Datos comparativos'!AC206 -> 0.96553148 | AR190: ='Datos comparativos'!AD206 -> 0.88215686 | AS190: ='Datos comparativos'!AH206 -> 0.86964912 | AT190: ='Datos comparativos'!AI206 -> n/a | AU190: ='Datos comparativos'!AJ206 -> 0.91351909 | AV190: ='Datos comparativos'!AK206 -> 0.93568627 | AW190: ='Datos comparativos'!AL206 -> 0.94745098 | AX190: ='Datos comparativos'!AM206 -> n/a | AY190: ='Datos comparativos'!AO206 -> 0.72995614 | AZ190: ='Datos comparativos'!AP206 -> 0.83980392 | BA190: ='Datos comparativos'!AR206 -> 0.94652406
